Workbook
Name CmpChild: Inputs!$D$11
Name Coverage: Inputs!$D$8
Name Ctry_Ccy: Lists!$H$2:$H$12
Name Ctry_LInf: Lists!$I$2:$I$12
Name Ctry_Name: Lists!$G$2:$G$12
Name DB_Avail: 'Cost Database'!$G$5:$G$488
Name DB_Dur: 'Cost Database'!$F$5:$F$488
Name DB_EduCcy: 'Cost Database'!$E$5:$E$488
Name DB_EstAdm: 'Cost Database'!$R$5:$R$488
Name DB_EstBase: 'Cost Database'!$O$5:$O$488
Name DB_EstCcy: 'Cost Database'!$N$5:$N$488
Name DB_EstOther: 'Cost Database'!$Q$5:$Q$488
Name DB_EstStatus: 'Cost Database'!$M$5:$M$488
Name DB_EstTuition: 'Cost Database'!$P$5:$P$488
Name DB_Key: 'Cost Database'!$A$5:$A$488
Name DB_PreAdm: 'Cost Database'!$X$5:$X$488
Name DB_PreBase: 'Cost Database'!$U$5:$U$488
Name DB_PreCcy: 'Cost Database'!$T$5:$T$488
Name DB_PreOther: 'Cost Database'!$W$5:$W$488
Name DB_PreStatus: 'Cost Database'!$S$5:$S$488
Name DB_PreTuition: 'Cost Database'!$V$5:$V$488
Name DB_PreYears: 'Cost Database'!$H$5:$H$488
Name DB_RecCcy: 'Cost Database'!$L$5:$L$488
Name DB_TInf: 'Cost Database'!$J$5:$J$488
Name DomKey: Lists!$E$2:$E$50
Name FxCodes: 'Assumptions and Currency'!$A$8:$A$17
Name FxUsed: 'Assumptions and Currency'!$D$8:$D$17
Name Liv_accommodation_Amt: 'Living Costs'!$B$5:$B$26
Name Liv_accommodation_Base: 'Living Costs'!$D$5:$D$26
Name Liv_accommodation_Ccy: 'Living Costs'!$C$5:$C$26
Name Liv_accommodation_Status: 'Living Costs'!$E$5:$E$26
Name Liv_books_Amt: 'Living Costs'!$R$5:$R$26
Name Liv_books_Base: 'Living Costs'!$T$5:$T$26
Name Liv_books_Ccy: 'Living Costs'!$S$5:$S$26
Name Liv_books_Status: 'Living Costs'!$U$5:$U$26
Name Liv_food_Amt: 'Living Costs'!$F$5:$F$26
Name Liv_food_Base: 'Living Costs'!$H$5:$H$26
Name Liv_food_Ccy: 'Living Costs'!$G$5:$G$26
Name Liv_food_Status: 'Living Costs'!$I$5:$I$26
Name Liv_healthInsurance_Amt: 'Living Costs'!$N$5:$N$26
Name Liv_healthInsurance_Base: 'Living Costs'!$P$5:$P$26
Name Liv_healthInsurance_Ccy: 'Living Costs'!$O$5:$O$26
Name Liv_healthInsurance_Status: 'Living Costs'!$Q$5:$Q$26
Name Liv_transport_Amt: 'Living Costs'!$J$5:$J$26
Name Liv_transport_Base: 'Living Costs'!$L$5:$L$26
Name Liv_transport_Ccy: 'Living Costs'!$K$5:$K$26
Name Liv_transport_Status: 'Living Costs'!$M$5:$M$26
Name LivKey: 'Living Costs'!$A$5:$A$26
Name Nationality: Inputs!$C$6
Name NumChildren: Inputs!$D$4
Name PlanYear: 'Assumptions and Currency'!$B$3
Name RecAdm: 'Fee Records'!$H$5:$H$438
Name RecKey: 'Fee Records'!$A$5:$A$438
Name RecOther: 'Fee Records'!$G$5:$G$438
Name RecTuition: 'Fee Records'!$F$5:$F$438
Name RecYear: 'Fee Records'!$D$5:$D$438
Name RepCcy: Inputs!$D$7
Name Residence: Inputs!$C$5
Name ResNoVisa: Lists!$K$2:$K$3
Name Ret_Ccy: 'Assumptions and Currency'!$A$22:$A$31

Sheet Start Here
B2: Children's Future Education Fund Calculator
B3: Sindhi Connect - sindhiconnect.org
B5: How to use
B6: 1. Go to the Inputs sheet and fill in the yellow cells: your family details and, for each child, age, education country and qualification.
B7: 2. Open the Dashboard: total education fund required, required yearly savings, amount needed now, each child, cost breakdown and the year-by-year plan.
B8: 3. Compare Countries shows the same course in all 11 study countries.
B9: 4. Each child's sheet shows every cost line with its status (Published figure / Estimated — please review / Not needed / Your figure) and the full calculation.
B10: 5. To use your own figures, type them in the 'Your own cost figures' rows on the Inputs sheet (today's prices, education country's currency).
B12: Important
B13: Educational planning tool only. Fees, living costs, inflation, exchange rates and investment returns may differ from these figures. Figures marked 'Estimated — please review' are planning estimates, not official fees. Investment returns are assumptions, not guarantees. Always confirm fees with the university.
B14: Results are in US dollars unless you choose another currency. The workbook uses formulas only (no macros). It follows the same method as the calculator on the website; see the Sources and Method sheet.
B15: Fees checked on 2026-10-15. Exchange rates of 2026-10-01 (you can enter your own on the Assumptions and Currency sheet).

Sheet Inputs
B1: Children's Future Education Fund - your inputs
B2: Fill in the yellow cells. Leave a cell blank to use the researched figure or default. Results are on the Dashboard.
B3: Family | D3: Value used
B4: Number of children (1-4) | C4: 1 | D4: =MIN(4,MAX(1,ROUND(N(C4),0))) -> 1 | G4: Children beyond this number are ignored.
B5: Country where your family lives | C5: Pakistan | G5: Used for first-travel estimates.
B6: Children's nationality | C6: Pakistan | G6: Decides local or international fees and visa costs.
B7: Show results in (currency) | C7: USD | D7: =IF(C7="Automatic",IFERROR(INDEX(Ctry_Ccy,MATCH(C17,Ctry_Name,0)),"USD"),IF(C7="","USD",C7)) -> USD | G7: 'Automatic' uses Child 1's study country currency.
B8: Covered by scholarship / part-time work | C8: 0 | D8: =MIN(1,MAX(0,N(C8))) -> 0 | G8: Reduces tuition, university fees and living costs. Visa and travel are not reduced.
B9: Investment return per year (blank = default for the currency) | D9: =IF(ISNUMBER(C9),C9,IFERROR(INDEX(Ret_Rate,MATCH(D7,Ret_Ccy,0)),0.05)) -> 0.06 | G9: An assumption, not a guarantee.
B10: Yearly increase in your savings | C10: 0 | D10: =N(C10) -> 0 | G10: 0% = the same amount every year.
B11: Compare countries for child number | C11: 1 | D11: =MIN(D4,MAX(1,ROUND(N(C11),0))) -> 1 | G11: Used on the Compare Countries sheet.
B13: Children | C13: Child 1 | D13: Child 2 | E13: Child 3 | F13: Child 4
B14: Name (optional)
B15: Current age (0-18)
B16: Current school class (0-13, for your reference)
B17: Education country
B18: Qualification
B19: College-entry age (usually 18) | C19: 18 | D19: 18 | E19: 18 | F19: 18
B20: Your own fee increase per year (blank = researched default)
B21: Your own living-cost increase per year (blank = default)
B22: Your own cost figures (optional) - per year unless one-time, today's prices, in the education country's currency
B23: Tuition
B24: Accommodation
B25: Food
B26: Local transport
B27: Health insurance
B28: Books and supplies
B29: Other university and course fees
B30: Admission and one-time fees (one-time)
B31: Visa and application (one-time)
... B36: Researched figures and their sources are on each child's sheet (Child 1 to Child 4). Figures marked 'Estimated — please review' are planning estimates, not official fees.

Sheet Dashboard
B1: Children's Future Education Fund - dashboard
B2: ="All amounts in "&RepCcy&", at future prices. Planning estimates only - not financial advice." -> All amounts in USD, at future prices. Planning estimates only - not financial advice.
B4: Total education fund required | C4: ='Child 1'!$Z$56+'Child 2'!$Z$56+'Child 3'!$Z$56+'Child 4'!$Z$56 -> 0 | D4: =IF(C4=0,"Enter your family and children's details on the Inputs sheet to see the figures.","") -> Enter your family and children's details on the Inputs sheet to see the figures.
B5: Required yearly savings (this year) | C5: ='Child 1'!$N$65+'Child 2'!$N$65+'Child 3'!$N$65+'Child 4'!$N$65 -> 0
B6: Amount needed now | C6: ='Child 1'!$B$126+'Child 2'!$B$126+'Child 3'!$B$126+'Child 4'!$B$126 -> 0 | D6: =IF(C6>0.5,"Plus about "&TEXT(C6,"#,##0")&" "&RepCcy&" needed now, because a course starts before any yearly saving can be made.","")
B7: Covered by scholarship / part-time work | C7: ='Child 1'!$B$59+'Child 2'!$B$59+'Child 3'!$B$59+'Child 4'!$B$59 -> 0
B8: Plan length (years) | C8: =MAX('Child 1'!$B$20,'Child 2'!$B$20,'Child 3'!$B$20,'Child 4'!$B$20) -> 0
B10: Each child
B11: Child | C11: Education country | D11: Qualification | E11: Course length (years) | F11: Education starts in | G11: ="Total ("&RepCcy&")" -> Total (USD) | H11: Message
B12: =IF(1<=NumChildren,IF(Inputs!$C$14<>"",Inputs!$C$14,"Child 1"),"") -> Child 1 | C12: =IF(1<=NumChildren,'Child 1'!$B$5,"") | D12: =IF(1<=NumChildren,'Child 1'!$B$6,"") | E12: =IF(AND(1<=NumChildren,'Child 1'!$B$22=1),'Child 1'!$B$13,"") | F12: =IF(AND(1<=NumChildren,'Child 1'!$B$22=1),IF('Child 1'!$B$18=0,"This year",'Child 1'!$B$18&" years")&" ("&(PlanYear+'Child 1'!$B$18)&"/"&RIGHT(PlanYear+'Child 1'!$B$18+1,2)&")","") | G12: =IF(1<=NumChildren,'Child 1'!$Z$56,"") -> 0 | H12: =IF(1<=NumChildren,'Child 1'!$B$23,"") -> Enter this child's details on the Inputs sheet.
B13: =IF(2<=NumChildren,IF(Inputs!$D$14<>"",Inputs!$D$14,"Child 2"),"") | C13: =IF(2<=NumChildren,'Child 2'!$B$5,"") | D13: =IF(2<=NumChildren,'Child 2'!$B$6,"") | E13: =IF(AND(2<=NumChildren,'Child 2'!$B$22=1),'Child 2'!$B$13,"") | F13: =IF(AND(2<=NumChildren,'Child 2'!$B$22=1),IF('Child 2'!$B$18=0,"This year",'Child 2'!$B$18&" years")&" ("&(PlanYear+'Child 2'!$B$18)&"/"&RIGHT(PlanYear+'Child 2'!$B$18+1,2)&")","") | G13: =IF(2<=NumChildren,'Child 2'!$Z$56,"") | H13: =IF(2<=NumChildren,'Child 2'!$B$23,"")
B14: =IF(3<=NumChildren,IF(Inputs!$E$14<>"",Inputs!$E$14,"Child 3"),"") | C14: =IF(3<=NumChildren,'Child 3'!$B$5,"") | D14: =IF(3<=NumChildren,'Child 3'!$B$6,"") | E14: =IF(AND(3<=NumChildren,'Child 3'!$B$22=1),'Child 3'!$B$13,"") | F14: =IF(AND(3<=NumChildren,'Child 3'!$B$22=1),IF('Child 3'!$B$18=0,"This year",'Child 3'!$B$18&" years")&" ("&(PlanYear+'Child 3'!$B$18)&"/"&RIGHT(PlanYear+'Child 3'!$B$18+1,2)&")","") | G14: =IF(3<=NumChildren,'Child 3'!$Z$56,"") | H14: =IF(3<=NumChildren,'Child 3'!$B$23,"")
B15: =IF(4<=NumChildren,IF(Inputs!$F$14<>"",Inputs!$F$14,"Child 4"),"") | C15: =IF(4<=NumChildren,'Child 4'!$B$5,"") | D15: =IF(4<=NumChildren,'Child 4'!$B$6,"") | E15: =IF(AND(4<=NumChildren,'Child 4'!$B$22=1),'Child 4'!$B$13,"") | F15: =IF(AND(4<=NumChildren,'Child 4'!$B$22=1),IF('Child 4'!$B$18=0,"This year",'Child 4'!$B$18&" years")&" ("&(PlanYear+'Child 4'!$B$18)&"/"&RIGHT(PlanYear+'Child 4'!$B$18+1,2)&")","") | G15: =IF(4<=NumChildren,'Child 4'!$Z$56,"") | H15: =IF(4<=NumChildren,'Child 4'!$B$23,"")
B16: All children | G16: =C4 -> 0
B18: Where the money goes
B19: Cost type | C19: ="Amount ("&RepCcy&")" -> Amount (USD) | D19: Share
B20: Tuition | C20: ='Child 1'!$P$56+'Child 2'!$P$56+'Child 3'!$P$56+'Child 4'!$P$56 -> 0 | D20: =IF($C$4>0,C20/$C$4,0) -> 0
B21: Accommodation | C21: ='Child 1'!$Q$56+'Child 2'!$Q$56+'Child 3'!$Q$56+'Child 4'!$Q$56 -> 0 | D21: =IF($C$4>0,C21/$C$4,0) -> 0
B22: Food | C22: ='Child 1'!$R$56+'Child 2'!$R$56+'Child 3'!$R$56+'Child 4'!$R$56 -> 0 | D22: =IF($C$4>0,C22/$C$4,0) -> 0
B23: Local transport | C23: ='Child 1'!$S$56+'Child 2'!$S$56+'Child 3'!$S$56+'Child 4'!$S$56 -> 0 | D23: =IF($C$4>0,C23/$C$4,0) -> 0
B24: Health insurance | C24: ='Child 1'!$T$56+'Child 2'!$T$56+'Child 3'!$T$56+'Child 4'!$T$56 -> 0 | D24: =IF($C$4>0,C24/$C$4,0) -> 0
B25: Books and supplies | C25: ='Child 1'!$U$56+'Child 2'!$U$56+'Child 3'!$U$56+'Child 4'!$U$56 -> 0 | D25: =IF($C$4>0,C25/$C$4,0) -> 0
B26: Other university and course fees | C26: ='Child 1'!$V$56+'Child 1'!$W$56+'Child 2'!$V$56+'Child 2'!$W$56+'Child 3'!$V$56+'Child 3'!$W$56+'Child 4'!$V$56+'Child 4'!$W$56 -> 0 | D26: =IF($C$4>0,C26/$C$4,0) -> 0
B27: Visa, application, travel and relocation | C27: ='Child 1'!$X$56+'Child 1'!$Y$56+'Child 2'!$X$56+'Child 2'!$Y$56+'Child 3'!$X$56+'Child 3'!$Y$56+'Child 4'!$X$56+'Child 4'!$Y$56 -> 0 | D27: =IF($C$4>0,C27/$C$4,0) -> 0
B28: Total | C28: =SUM(C20:C27) -> 0
B30: Year-by-year plan - how the education fund builds up and is spent
B31: Year | C31: Studying | D31: Opening fund | E31: Family savings added | F31: Investment growth | G31: Education expenses | H31: Closing fund | T31: Year | U31: =IF(Inputs!$C$14<>"",Inputs!$C$14,"Child 1") -> Child 1 | V31: =IF(Inputs!$D$14<>"",Inputs!$D$14,"Child 2") -> Child 2 | W31: =IF(Inputs!$E$14<>"",Inputs!$E$14,"Child 3") -> Child 3 | X31: =IF(Inputs!$F$14<>"",Inputs!$F$14,"Child 4") -> Child 4 | Y31: Family savings
B32: =IF(1<=$C$8,(PlanYear+0)&"/"&RIGHT(PlanYear+1,2),"") | C32: =IF(1<=$C$8,MID(IF('Child 1'!$Q$65=1,", "&IF(Inputs!$C$14<>"",Inputs!$C$14,"Child 1"),"")&IF('Child 2'!$Q$65=1,", "&IF(Inputs!$D$14<>"",Inputs!$D$14,"Child 2"),"")&IF('Child 3'!$Q$65=1,", "&IF(Inputs!$E$14<>"",Inputs!$E$14,"Child 3"),"")&IF('Child 4'!$Q$65=1,", "&IF(Inputs!$F$14<>"",Inputs!$F$14,"Child 4"),""),3,200),"") | D32: =IF(1<=$C$8,ROUND('Child 1'!$M$65+'Child 2'!$M$65+'Child 3'!$M$65+'Child 4'!$M$65,2),"") | E32: =IF(1<=$C$8,ROUND('Child 1'!$N$65+'Child 2'!$N$65+'Child 3'!$N$65+'Child 4'!$N$65,2),"") | F32: =IF(1<=$C$8,ROUND('Child 1'!$O$65+'Child 2'!$O$65+'Child 3'!$O$65+'Child 4'!$O$65,2),"") | G32: =IF(1<=$C$8,ROUND('Child 1'!$D$65+'Child 2'!$D$65+'Child 3'!$D$65+'Child 4'!$D$65,2),"") | H32: =IF(1<=$C$8,ROUND('Child 1'!$P$65+'Child 2'!$P$65+'Child 3'!$P$65+'Child 4'!$P$65,2),"") | T32: =IF(1<=$C$8,B32,"") | U32: =IF(1<=$C$8,'Child 1'!$D$65,NA()) -> #N/A | V32: =IF(1<=$C$8,'Child 2'!$D$65,NA()) -> #N/A | W32: =IF(1<=$C$8,'Child 3'!$D$65,NA()) -> #N/A | X32: =IF(1<=$C$8,'Child 4'!$D$65,NA()) -> #N/A | Y32: =IF(1<=$C$8,E32,NA()) -> #N/A
B33: =IF(2<=$C$8,(PlanYear+1)&"/"&RIGHT(PlanYear+2,2),"") | C33: =IF(2<=$C$8,MID(IF('Child 1'!$Q$66=1,", "&IF(Inputs!$C$14<>"",Inputs!$C$14,"Child 1"),"")&IF('Child 2'!$Q$66=1,", "&IF(Inputs!$D$14<>"",Inputs!$D$14,"Child 2"),"")&IF('Child 3'!$Q$66=1,", "&IF(Inputs!$E$14<>"",Inputs!$E$14,"Child 3"),"")&IF('Child 4'!$Q$66=1,", "&IF(Inputs!$F$14<>"",Inputs!$F$14,"Child 4"),""),3,200),"") | D33: =IF(2<=$C$8,ROUND('Child 1'!$M$66+'Child 2'!$M$66+'Child 3'!$M$66+'Child 4'!$M$66,2),"") | E33: =IF(2<=$C$8,ROUND('Child 1'!$N$66+'Child 2'!$N$66+'Child 3'!$N$66+'Child 4'!$N$66,2),"") | F33: =IF(2<=$C$8,ROUND('Child 1'!$O$66+'Child 2'!$O$66+'Child 3'!$O$66+'Child 4'!$O$66,2),"") | G33: =IF(2<=$C$8,ROUND('Child 1'!$D$66+'Child 2'!$D$66+'Child 3'!$D$66+'Child 4'!$D$66,2),"") | H33: =IF(2<=$C$8,ROUND('Child 1'!$P$66+'Child 2'!$P$66+'Child 3'!$P$66+'Child 4'!$P$66,2),"") | T33: =IF(2<=$C$8,B33,"") | U33: =IF(2<=$C$8,'Child 1'!$D$66,NA()) -> #N/A | V33: =IF(2<=$C$8,'Child 2'!$D$66,NA()) -> #N/A | W33: =IF(2<=$C$8,'Child 3'!$D$66,NA()) -> #N/A | X33: =IF(2<=$C$8,'Child 4'!$D$66,NA()) -> #N/A | Y33: =IF(2<=$C$8,E33,NA()) -> #N/A
B34: =IF(3<=$C$8,(PlanYear+2)&"/"&RIGHT(PlanYear+3,2),"") | C34: =IF(3<=$C$8,MID(IF('Child 1'!$Q$67=1,", "&IF(Inputs!$C$14<>"",Inputs!$C$14,"Child 1"),"")&IF('Child 2'!$Q$67=1,", "&IF(Inputs!$D$14<>"",Inputs!$D$14,"Child 2"),"")&IF('Child 3'!$Q$67=1,", "&IF(Inputs!$E$14<>"",Inputs!$E$14,"Child 3"),"")&IF('Child 4'!$Q$67=1,", "&IF(Inputs!$F$14<>"",Inputs!$F$14,"Child 4"),""),3,200),"") | D34: =IF(3<=$C$8,ROUND('Child 1'!$M$67+'Child 2'!$M$67+'Child 3'!$M$67+'Child 4'!$M$67,2),"") | E34: =IF(3<=$C$8,ROUND('Child 1'!$N$67+'Child 2'!$N$67+'Child 3'!$N$67+'Child 4'!$N$67,2),"") | F34: =IF(3<=$C$8,ROUND('Child 1'!$O$67+'Child 2'!$O$67+'Child 3'!$O$67+'Child 4'!$O$67,2),"") | G34: =IF(3<=$C$8,ROUND('Child 1'!$D$67+'Child 2'!$D$67+'Child 3'!$D$67+'Child 4'!$D$67,2),"") | H34: =IF(3<=$C$8,ROUND('Child 1'!$P$67+'Child 2'!$P$67+'Child 3'!$P$67+'Child 4'!$P$67,2),"") | T34: =IF(3<=$C$8,B34,"") | U34: =IF(3<=$C$8,'Child 1'!$D$67,NA()) -> #N/A | V34: =IF(3<=$C$8,'Child 2'!$D$67,NA()) -> #N/A | W34: =IF(3<=$C$8,'Child 3'!$D$67,NA()) -> #N/A | X34: =IF(3<=$C$8,'Child 4'!$D$67,NA()) -> #N/A | Y34: =IF(3<=$C$8,E34,NA()) -> #N/A
B35: =IF(4<=$C$8,(PlanYear+3)&"/"&RIGHT(PlanYear+4,2),"") | C35: =IF(4<=$C$8,MID(IF('Child 1'!$Q$68=1,", "&IF(Inputs!$C$14<>"",Inputs!$C$14,"Child 1"),"")&IF('Child 2'!$Q$68=1,", "&IF(Inputs!$D$14<>"",Inputs!$D$14,"Child 2"),"")&IF('Child 3'!$Q$68=1,", "&IF(Inputs!$E$14<>"",Inputs!$E$14,"Child 3"),"")&IF('Child 4'!$Q$68=1,", "&IF(Inputs!$F$14<>"",Inputs!$F$14,"Child 4"),""),3,200),"") | D35: =IF(4<=$C$8,ROUND('Child 1'!$M$68+'Child 2'!$M$68+'Child 3'!$M$68+'Child 4'!$M$68,2),"") | E35: =IF(4<=$C$8,ROUND('Child 1'!$N$68+'Child 2'!$N$68+'Child 3'!$N$68+'Child 4'!$N$68,2),"") | F35: =IF(4<=$C$8,ROUND('Child 1'!$O$68+'Child 2'!$O$68+'Child 3'!$O$68+'Child 4'!$O$68,2),"") | G35: =IF(4<=$C$8,ROUND('Child 1'!$D$68+'Child 2'!$D$68+'Child 3'!$D$68+'Child 4'!$D$68,2),"") | H35: =IF(4<=$C$8,ROUND('Child 1'!$P$68+'Child 2'!$P$68+'Child 3'!$P$68+'Child 4'!$P$68,2),"") | T35: =IF(4<=$C$8,B35,"") | U35: =IF(4<=$C$8,'Child 1'!$D$68,NA()) -> #N/A | V35: =IF(4<=$C$8,'Child 2'!$D$68,NA()) -> #N/A | W35: =IF(4<=$C$8,'Child 3'!$D$68,NA()) -> #N/A | X35: =IF(4<=$C$8,'Child 4'!$D$68,NA()) -> #N/A | Y35: =IF(4<=$C$8,E35,NA()) -> #N/A
B36: =IF(5<=$C$8,(PlanYear+4)&"/"&RIGHT(PlanYear+5,2),"") | C36: =IF(5<=$C$8,MID(IF('Child 1'!$Q$69=1,", "&IF(Inputs!$C$14<>"",Inputs!$C$14,"Child 1"),"")&IF('Child 2'!$Q$69=1,", "&IF(Inputs!$D$14<>"",Inputs!$D$14,"Child 2"),"")&IF('Child 3'!$Q$69=1,", "&IF(Inputs!$E$14<>"",Inputs!$E$14,"Child 3"),"")&IF('Child 4'!$Q$69=1,", "&IF(Inputs!$F$14<>"",Inputs!$F$14,"Child 4"),""),3,200),"") | D36: =IF(5<=$C$8,ROUND('Child 1'!$M$69+'Child 2'!$M$69+'Child 3'!$M$69+'Child 4'!$M$69,2),"") | E36: =IF(5<=$C$8,ROUND('Child 1'!$N$69+'Child 2'!$N$69+'Child 3'!$N$69+'Child 4'!$N$69,2),"") | F36: =IF(5<=$C$8,ROUND('Child 1'!$O$69+'Child 2'!$O$69+'Child 3'!$O$69+'Child 4'!$O$69,2),"") | G36: =IF(5<=$C$8,ROUND('Child 1'!$D$69+'Child 2'!$D$69+'Child 3'!$D$69+'Child 4'!$D$69,2),"") | H36: =IF(5<=$C$8,ROUND('Child 1'!$P$69+'Child 2'!$P$69+'Child 3'!$P$69+'Child 4'!$P$69,2),"") | T36: =IF(5<=$C$8,B36,"") | U36: =IF(5<=$C$8,'Child 1'!$D$69,NA()) -> #N/A | V36: =IF(5<=$C$8,'Child 2'!$D$69,NA()) -> #N/A | W36: =IF(5<=$C$8,'Child 3'!$D$69,NA()) -> #N/A | X36: =IF(5<=$C$8,'Child 4'!$D$69,NA()) -> #N/A | Y36: =IF(5<=$C$8,E36,NA()) -> #N/A
B37: =IF(6<=$C$8,(PlanYear+5)&"/"&RIGHT(PlanYear+6,2),"") | C37: =IF(6<=$C$8,MID(IF('Child 1'!$Q$70=1,", "&IF(Inputs!$C$14<>"",Inputs!$C$14,"Child 1"),"")&IF('Child 2'!$Q$70=1,", "&IF(Inputs!$D$14<>"",Inputs!$D$14,"Child 2"),"")&IF('Child 3'!$Q$70=1,", "&IF(Inputs!$E$14<>"",Inputs!$E$14,"Child 3"),"")&IF('Child 4'!$Q$70=1,", "&IF(Inputs!$F$14<>"",Inputs!$F$14,"Child 4"),""),3,200),"") | D37: =IF(6<=$C$8,ROUND('Child 1'!$M$70+'Child 2'!$M$70+'Child 3'!$M$70+'Child 4'!$M$70,2),"") | E37: =IF(6<=$C$8,ROUND('Child 1'!$N$70+'Child 2'!$N$70+'Child 3'!$N$70+'Child 4'!$N$70,2),"") | F37: =IF(6<=$C$8,ROUND('Child 1'!$O$70+'Child 2'!$O$70+'Child 3'!$O$70+'Child 4'!$O$70,2),"") | G37: =IF(6<=$C$8,ROUND('Child 1'!$D$70+'Child 2'!$D$70+'Child 3'!$D$70+'Child 4'!$D$70,2),"") | H37: =IF(6<=$C$8,ROUND('Child 1'!$P$70+'Child 2'!$P$70+'Child 3'!$P$70+'Child 4'!$P$70,2),"") | T37: =IF(6<=$C$8,B37,"") | U37: =IF(6<=$C$8,'Child 1'!$D$70,NA()) -> #N/A | V37: =IF(6<=$C$8,'Child 2'!$D$70,NA()) -> #N/A | W37: =IF(6<=$C$8,'Child 3'!$D$70,NA()) -> #N/A | X37: =IF(6<=$C$8,'Child 4'!$D$70,NA()) -> #N/A | Y37: =IF(6<=$C$8,E37,NA()) -> #N/A
B38: =IF(7<=$C$8,(PlanYear+6)&"/"&RIGHT(PlanYear+7,2),"") | C38: =IF(7<=$C$8,MID(IF('Child 1'!$Q$71=1,", "&IF(Inputs!$C$14<>"",Inputs!$C$14,"Child 1"),"")&IF('Child 2'!$Q$71=1,", "&IF(Inputs!$D$14<>"",Inputs!$D$14,"Child 2"),"")&IF('Child 3'!$Q$71=1,", "&IF(Inputs!$E$14<>"",Inputs!$E$14,"Child 3"),"")&IF('Child 4'!$Q$71=1,", "&IF(Inputs!$F$14<>"",Inputs!$F$14,"Child 4"),""),3,200),"") | D38: =IF(7<=$C$8,ROUND('Child 1'!$M$71+'Child 2'!$M$71+'Child 3'!$M$71+'Child 4'!$M$71,2),"") | E38: =IF(7<=$C$8,ROUND('Child 1'!$N$71+'Child 2'!$N$71+'Child 3'!$N$71+'Child 4'!$N$71,2),"") | F38: =IF(7<=$C$8,ROUND('Child 1'!$O$71+'Child 2'!$O$71+'Child 3'!$O$71+'Child 4'!$O$71,2),"") | G38: =IF(7<=$C$8,ROUND('Child 1'!$D$71+'Child 2'!$D$71+'Child 3'!$D$71+'Child 4'!$D$71,2),"") | H38: =IF(7<=$C$8,ROUND('Child 1'!$P$71+'Child 2'!$P$71+'Child 3'!$P$71+'Child 4'!$P$71,2),"") | T38: =IF(7<=$C$8,B38,"") | U38: =IF(7<=$C$8,'Child 1'!$D$71,NA()) -> #N/A | V38: =IF(7<=$C$8,'Child 2'!$D$71,NA()) -> #N/A | W38: =IF(7<=$C$8,'Child 3'!$D$71,NA()) -> #N/A | X38: =IF(7<=$C$8,'Child 4'!$D$71,NA()) -> #N/A | Y38: =IF(7<=$C$8,E38,NA()) -> #N/A
B39: =IF(8<=$C$8,(PlanYear+7)&"/"&RIGHT(PlanYear+8,2),"") | C39: =IF(8<=$C$8,MID(IF('Child 1'!$Q$72=1,", "&IF(Inputs!$C$14<>"",Inputs!$C$14,"Child 1"),"")&IF('Child 2'!$Q$72=1,", "&IF(Inputs!$D$14<>"",Inputs!$D$14,"Child 2"),"")&IF('Child 3'!$Q$72=1,", "&IF(Inputs!$E$14<>"",Inputs!$E$14,"Child 3"),"")&IF('Child 4'!$Q$72=1,", "&IF(Inputs!$F$14<>"",Inputs!$F$14,"Child 4"),""),3,200),"") | D39: =IF(8<=$C$8,ROUND('Child 1'!$M$72+'Child 2'!$M$72+'Child 3'!$M$72+'Child 4'!$M$72,2),"") | E39: =IF(8<=$C$8,ROUND('Child 1'!$N$72+'Child 2'!$N$72+'Child 3'!$N$72+'Child 4'!$N$72,2),"") | F39: =IF(8<=$C$8,ROUND('Child 1'!$O$72+'Child 2'!$O$72+'Child 3'!$O$72+'Child 4'!$O$72,2),"") | G39: =IF(8<=$C$8,ROUND('Child 1'!$D$72+'Child 2'!$D$72+'Child 3'!$D$72+'Child 4'!$D$72,2),"") | H39: =IF(8<=$C$8,ROUND('Child 1'!$P$72+'Child 2'!$P$72+'Child 3'!$P$72+'Child 4'!$P$72,2),"") | T39: =IF(8<=$C$8,B39,"") | U39: =IF(8<=$C$8,'Child 1'!$D$72,NA()) -> #N/A | V39: =IF(8<=$C$8,'Child 2'!$D$72,NA()) -> #N/A | W39: =IF(8<=$C$8,'Child 3'!$D$72,NA()) -> #N/A | X39: =IF(8<=$C$8,'Child 4'!$D$72,NA()) -> #N/A | Y39: =IF(8<=$C$8,E39,NA()) -> #N/A
B40: =IF(9<=$C$8,(PlanYear+8)&"/"&RIGHT(PlanYear+9,2),"") | C40: =IF(9<=$C$8,MID(IF('Child 1'!$Q$73=1,", "&IF(Inputs!$C$14<>"",Inputs!$C$14,"Child 1"),"")&IF('Child 2'!$Q$73=1,", "&IF(Inputs!$D$14<>"",Inputs!$D$14,"Child 2"),"")&IF('Child 3'!$Q$73=1,", "&IF(Inputs!$E$14<>"",Inputs!$E$14,"Child 3"),"")&IF('Child 4'!$Q$73=1,", "&IF(Inputs!$F$14<>"",Inputs!$F$14,"Child 4"),""),3,200),"") | D40: =IF(9<=$C$8,ROUND('Child 1'!$M$73+'Child 2'!$M$73+'Child 3'!$M$73+'Child 4'!$M$73,2),"") | E40: =IF(9<=$C$8,ROUND('Child 1'!$N$73+'Child 2'!$N$73+'Child 3'!$N$73+'Child 4'!$N$73,2),"") | F40: =IF(9<=$C$8,ROUND('Child 1'!$O$73+'Child 2'!$O$73+'Child 3'!$O$73+'Child 4'!$O$73,2),"") | G40: =IF(9<=$C$8,ROUND('Child 1'!$D$73+'Child 2'!$D$73+'Child 3'!$D$73+'Child 4'!$D$73,2),"") | H40: =IF(9<=$C$8,ROUND('Child 1'!$P$73+'Child 2'!$P$73+'Child 3'!$P$73+'Child 4'!$P$73,2),"") | T40: =IF(9<=$C$8,B40,"") | U40: =IF(9<=$C$8,'Child 1'!$D$73,NA()) -> #N/A | V40: =IF(9<=$C$8,'Child 2'!$D$73,NA()) -> #N/A | W40: =IF(9<=$C$8,'Child 3'!$D$73,NA()) -> #N/A | X40: =IF(9<=$C$8,'Child 4'!$D$73,NA()) -> #N/A | Y40: =IF(9<=$C$8,E40,NA()) -> #N/A
B41: =IF(10<=$C$8,(PlanYear+9)&"/"&RIGHT(PlanYear+10,2),"") | C41: =IF(10<=$C$8,MID(IF('Child 1'!$Q$74=1,", "&IF(Inputs!$C$14<>"",Inputs!$C$14,"Child 1"),"")&IF('Child 2'!$Q$74=1,", "&IF(Inputs!$D$14<>"",Inputs!$D$14,"Child 2"),"")&IF('Child 3'!$Q$74=1,", "&IF(Inputs!$E$14<>"",Inputs!$E$14,"Child 3"),"")&IF('Child 4'!$Q$74=1,", "&IF(Inputs!$F$14<>"",Inputs!$F$14,"Child 4"),""),3,200),"") | D41: =IF(10<=$C$8,ROUND('Child 1'!$M$74+'Child 2'!$M$74+'Child 3'!$M$74+'Child 4'!$M$74,2),"") | E41: =IF(10<=$C$8,ROUND('Child 1'!$N$74+'Child 2'!$N$74+'Child 3'!$N$74+'Child 4'!$N$74,2),"") | F41: =IF(10<=$C$8,ROUND('Child 1'!$O$74+'Child 2'!$O$74+'Child 3'!$O$74+'Child 4'!$O$74,2),"") | G41: =IF(10<=$C$8,ROUND('Child 1'!$D$74+'Child 2'!$D$74+'Child 3'!$D$74+'Child 4'!$D$74,2),"") | H41: =IF(10<=$C$8,ROUND('Child 1'!$P$74+'Child 2'!$P$74+'Child 3'!$P$74+'Child 4'!$P$74,2),"") | T41: =IF(10<=$C$8,B41,"") | U41: =IF(10<=$C$8,'Child 1'!$D$74,NA()) -> #N/A | V41: =IF(10<=$C$8,'Child 2'!$D$74,NA()) -> #N/A | W41: =IF(10<=$C$8,'Child 3'!$D$74,NA()) -> #N/A | X41: =IF(10<=$C$8,'Child 4'!$D$74,NA()) -> #N/A | Y41: =IF(10<=$C$8,E41,NA()) -> #N/A
B42: =IF(11<=$C$8,(PlanYear+10)&"/"&RIGHT(PlanYear+11,2),"") | C42: =IF(11<=$C$8,MID(IF('Child 1'!$Q$75=1,", "&IF(Inputs!$C$14<>"",Inputs!$C$14,"Child 1"),"")&IF('Child 2'!$Q$75=1,", "&IF(Inputs!$D$14<>"",Inputs!$D$14,"Child 2"),"")&IF('Child 3'!$Q$75=1,", "&IF(Inputs!$E$14<>"",Inputs!$E$14,"Child 3"),"")&IF('Child 4'!$Q$75=1,", "&IF(Inputs!$F$14<>"",Inputs!$F$14,"Child 4"),""),3,200),"") | D42: =IF(11<=$C$8,ROUND('Child 1'!$M$75+'Child 2'!$M$75+'Child 3'!$M$75+'Child 4'!$M$75,2),"") | E42: =IF(11<=$C$8,ROUND('Child 1'!$N$75+'Child 2'!$N$75+'Child 3'!$N$75+'Child 4'!$N$75,2),"") | F42: =IF(11<=$C$8,ROUND('Child 1'!$O$75+'Child 2'!$O$75+'Child 3'!$O$75+'Child 4'!$O$75,2),"") | G42: =IF(11<=$C$8,ROUND('Child 1'!$D$75+'Child 2'!$D$75+'Child 3'!$D$75+'Child 4'!$D$75,2),"") | H42: =IF(11<=$C$8,ROUND('Child 1'!$P$75+'Child 2'!$P$75+'Child 3'!$P$75+'Child 4'!$P$75,2),"") | T42: =IF(11<=$C$8,B42,"") | U42: =IF(11<=$C$8,'Child 1'!$D$75,NA()) -> #N/A | V42: =IF(11<=$C$8,'Child 2'!$D$75,NA()) -> #N/A | W42: =IF(11<=$C$8,'Child 3'!$D$75,NA()) -> #N/A | X42: =IF(11<=$C$8,'Child 4'!$D$75,NA()) -> #N/A | Y42: =IF(11<=$C$8,E42,NA()) -> #N/A
B43: =IF(12<=$C$8,(PlanYear+11)&"/"&RIGHT(PlanYear+12,2),"") | C43: =IF(12<=$C$8,MID(IF('Child 1'!$Q$76=1,", "&IF(Inputs!$C$14<>"",Inputs!$C$14,"Child 1"),"")&IF('Child 2'!$Q$76=1,", "&IF(Inputs!$D$14<>"",Inputs!$D$14,"Child 2"),"")&IF('Child 3'!$Q$76=1,", "&IF(Inputs!$E$14<>"",Inputs!$E$14,"Child 3"),"")&IF('Child 4'!$Q$76=1,", "&IF(Inputs!$F$14<>"",Inputs!$F$14,"Child 4"),""),3,200),"") | D43: =IF(12<=$C$8,ROUND('Child 1'!$M$76+'Child 2'!$M$76+'Child 3'!$M$76+'Child 4'!$M$76,2),"") | E43: =IF(12<=$C$8,ROUND('Child 1'!$N$76+'Child 2'!$N$76+'Child 3'!$N$76+'Child 4'!$N$76,2),"") | F43: =IF(12<=$C$8,ROUND('Child 1'!$O$76+'Child 2'!$O$76+'Child 3'!$O$76+'Child 4'!$O$76,2),"") | G43: =IF(12<=$C$8,ROUND('Child 1'!$D$76+'Child 2'!$D$76+'Child 3'!$D$76+'Child 4'!$D$76,2),"") | H43: =IF(12<=$C$8,ROUND('Child 1'!$P$76+'Child 2'!$P$76+'Child 3'!$P$76+'Child 4'!$P$76,2),"") | T43: =IF(12<=$C$8,B43,"") | U43: =IF(12<=$C$8,'Child 1'!$D$76,NA()) -> #N/A | V43: =IF(12<=$C$8,'Child 2'!$D$76,NA()) -> #N/A | W43: =IF(12<=$C$8,'Child 3'!$D$76,NA()) -> #N/A | X43: =IF(12<=$C$8,'Child 4'!$D$76,NA()) -> #N/A | Y43: =IF(12<=$C$8,E43,NA()) -> #N/A
B44: =IF(13<=$C$8,(PlanYear+12)&"/"&RIGHT(PlanYear+13,2),"") | C44: =IF(13<=$C$8,MID(IF('Child 1'!$Q$77=1,", "&IF(Inputs!$C$14<>"",Inputs!$C$14,"Child 1"),"")&IF('Child 2'!$Q$77=1,", "&IF(Inputs!$D$14<>"",Inputs!$D$14,"Child 2"),"")&IF('Child 3'!$Q$77=1,", "&IF(Inputs!$E$14<>"",Inputs!$E$14,"Child 3"),"")&IF('Child 4'!$Q$77=1,", "&IF(Inputs!$F$14<>"",Inputs!$F$14,"Child 4"),""),3,200),"") | D44: =IF(13<=$C$8,ROUND('Child 1'!$M$77+'Child 2'!$M$77+'Child 3'!$M$77+'Child 4'!$M$77,2),"") | E44: =IF(13<=$C$8,ROUND('Child 1'!$N$77+'Child 2'!$N$77+'Child 3'!$N$77+'Child 4'!$N$77,2),"") | F44: =IF(13<=$C$8,ROUND('Child 1'!$O$77+'Child 2'!$O$77+'Child 3'!$O$77+'Child 4'!$O$77,2),"") | G44: =IF(13<=$C$8,ROUND('Child 1'!$D$77+'Child 2'!$D$77+'Child 3'!$D$77+'Child 4'!$D$77,2),"") | H44: =IF(13<=$C$8,ROUND('Child 1'!$P$77+'Child 2'!$P$77+'Child 3'!$P$77+'Child 4'!$P$77,2),"") | T44: =IF(13<=$C$8,B44,"") | U44: =IF(13<=$C$8,'Child 1'!$D$77,NA()) -> #N/A | V44: =IF(13<=$C$8,'Child 2'!$D$77,NA()) -> #N/A | W44: =IF(13<=$C$8,'Child 3'!$D$77,NA()) -> #N/A | X44: =IF(13<=$C$8,'Child 4'!$D$77,NA()) -> #N/A | Y44: =IF(13<=$C$8,E44,NA()) -> #N/A
B45: =IF(14<=$C$8,(PlanYear+13)&"/"&RIGHT(PlanYear+14,2),"") | C45: =IF(14<=$C$8,MID(IF('Child 1'!$Q$78=1,", "&IF(Inputs!$C$14<>"",Inputs!$C$14,"Child 1"),"")&IF('Child 2'!$Q$78=1,", "&IF(Inputs!$D$14<>"",Inputs!$D$14,"Child 2"),"")&IF('Child 3'!$Q$78=1,", "&IF(Inputs!$E$14<>"",Inputs!$E$14,"Child 3"),"")&IF('Child 4'!$Q$78=1,", "&IF(Inputs!$F$14<>"",Inputs!$F$14,"Child 4"),""),3,200),"") | D45: =IF(14<=$C$8,ROUND('Child 1'!$M$78+'Child 2'!$M$78+'Child 3'!$M$78+'Child 4'!$M$78,2),"") | E45: =IF(14<=$C$8,ROUND('Child 1'!$N$78+'Child 2'!$N$78+'Child 3'!$N$78+'Child 4'!$N$78,2),"") | F45: =IF(14<=$C$8,ROUND('Child 1'!$O$78+'Child 2'!$O$78+'Child 3'!$O$78+'Child 4'!$O$78,2),"") | G45: =IF(14<=$C$8,ROUND('Child 1'!$D$78+'Child 2'!$D$78+'Child 3'!$D$78+'Child 4'!$D$78,2),"") | H45: =IF(14<=$C$8,ROUND('Child 1'!$P$78+'Child 2'!$P$78+'Child 3'!$P$78+'Child 4'!$P$78,2),"") | T45: =IF(14<=$C$8,B45,"") | U45: =IF(14<=$C$8,'Child 1'!$D$78,NA()) -> #N/A | V45: =IF(14<=$C$8,'Child 2'!$D$78,NA()) -> #N/A | W45: =IF(14<=$C$8,'Child 3'!$D$78,NA()) -> #N/A | X45: =IF(14<=$C$8,'Child 4'!$D$78,NA()) -> #N/A | Y45: =IF(14<=$C$8,E45,NA()) -> #N/A
B46: =IF(15<=$C$8,(PlanYear+14)&"/"&RIGHT(PlanYear+15,2),"") | C46: =IF(15<=$C$8,MID(IF('Child 1'!$Q$79=1,", "&IF(Inputs!$C$14<>"",Inputs!$C$14,"Child 1"),"")&IF('Child 2'!$Q$79=1,", "&IF(Inputs!$D$14<>"",Inputs!$D$14,"Child 2"),"")&IF('Child 3'!$Q$79=1,", "&IF(Inputs!$E$14<>"",Inputs!$E$14,"Child 3"),"")&IF('Child 4'!$Q$79=1,", "&IF(Inputs!$F$14<>"",Inputs!$F$14,"Child 4"),""),3,200),"") | D46: =IF(15<=$C$8,ROUND('Child 1'!$M$79+'Child 2'!$M$79+'Child 3'!$M$79+'Child 4'!$M$79,2),"") | E46: =IF(15<=$C$8,ROUND('Child 1'!$N$79+'Child 2'!$N$79+'Child 3'!$N$79+'Child 4'!$N$79,2),"") | F46: =IF(15<=$C$8,ROUND('Child 1'!$O$79+'Child 2'!$O$79+'Child 3'!$O$79+'Child 4'!$O$79,2),"") | G46: =IF(15<=$C$8,ROUND('Child 1'!$D$79+'Child 2'!$D$79+'Child 3'!$D$79+'Child 4'!$D$79,2),"") | H46: =IF(15<=$C$8,ROUND('Child 1'!$P$79+'Child 2'!$P$79+'Child 3'!$P$79+'Child 4'!$P$79,2),"") | T46: =IF(15<=$C$8,B46,"") | U46: =IF(15<=$C$8,'Child 1'!$D$79,NA()) -> #N/A | V46: =IF(15<=$C$8,'Child 2'!$D$79,NA()) -> #N/A | W46: =IF(15<=$C$8,'Child 3'!$D$79,NA()) -> #N/A | X46: =IF(15<=$C$8,'Child 4'!$D$79,NA()) -> #N/A | Y46: =IF(15<=$C$8,E46,NA()) -> #N/A
B47: =IF(16<=$C$8,(PlanYear+15)&"/"&RIGHT(PlanYear+16,2),"") | C47: =IF(16<=$C$8,MID(IF('Child 1'!$Q$80=1,", "&IF(Inputs!$C$14<>"",Inputs!$C$14,"Child 1"),"")&IF('Child 2'!$Q$80=1,", "&IF(Inputs!$D$14<>"",Inputs!$D$14,"Child 2"),"")&IF('Child 3'!$Q$80=1,", "&IF(Inputs!$E$14<>"",Inputs!$E$14,"Child 3"),"")&IF('Child 4'!$Q$80=1,", "&IF(Inputs!$F$14<>"",Inputs!$F$14,"Child 4"),""),3,200),"") | D47: =IF(16<=$C$8,ROUND('Child 1'!$M$80+'Child 2'!$M$80+'Child 3'!$M$80+'Child 4'!$M$80,2),"") | E47: =IF(16<=$C$8,ROUND('Child 1'!$N$80+'Child 2'!$N$80+'Child 3'!$N$80+'Child 4'!$N$80,2),"") | F47: =IF(16<=$C$8,ROUND('Child 1'!$O$80+'Child 2'!$O$80+'Child 3'!$O$80+'Child 4'!$O$80,2),"") | G47: =IF(16<=$C$8,ROUND('Child 1'!$D$80+'Child 2'!$D$80+'Child 3'!$D$80+'Child 4'!$D$80,2),"") | H47: =IF(16<=$C$8,ROUND('Child 1'!$P$80+'Child 2'!$P$80+'Child 3'!$P$80+'Child 4'!$P$80,2),"") | T47: =IF(16<=$C$8,B47,"") | U47: =IF(16<=$C$8,'Child 1'!$D$80,NA()) -> #N/A | V47: =IF(16<=$C$8,'Child 2'!$D$80,NA()) -> #N/A | W47: =IF(16<=$C$8,'Child 3'!$D$80,NA()) -> #N/A | X47: =IF(16<=$C$8,'Child 4'!$D$80,NA()) -> #N/A | Y47: =IF(16<=$C$8,E47,NA()) -> #N/A
B48: =IF(17<=$C$8,(PlanYear+16)&"/"&RIGHT(PlanYear+17,2),"") | C48: =IF(17<=$C$8,MID(IF('Child 1'!$Q$81=1,", "&IF(Inputs!$C$14<>"",Inputs!$C$14,"Child 1"),"")&IF('Child 2'!$Q$81=1,", "&IF(Inputs!$D$14<>"",Inputs!$D$14,"Child 2"),"")&IF('Child 3'!$Q$81=1,", "&IF(Inputs!$E$14<>"",Inputs!$E$14,"Child 3"),"")&IF('Child 4'!$Q$81=1,", "&IF(Inputs!$F$14<>"",Inputs!$F$14,"Child 4"),""),3,200),"") | D48: =IF(17<=$C$8,ROUND('Child 1'!$M$81+'Child 2'!$M$81+'Child 3'!$M$81+'Child 4'!$M$81,2),"") | E48: =IF(17<=$C$8,ROUND('Child 1'!$N$81+'Child 2'!$N$81+'Child 3'!$N$81+'Child 4'!$N$81,2),"") | F48: =IF(17<=$C$8,ROUND('Child 1'!$O$81+'Child 2'!$O$81+'Child 3'!$O$81+'Child 4'!$O$81,2),"") | G48: =IF(17<=$C$8,ROUND('Child 1'!$D$81+'Child 2'!$D$81+'Child 3'!$D$81+'Child 4'!$D$81,2),"") | H48: =IF(17<=$C$8,ROUND('Child 1'!$P$81+'Child 2'!$P$81+'Child 3'!$P$81+'Child 4'!$P$81,2),"") | T48: =IF(17<=$C$8,B48,"") | U48: =IF(17<=$C$8,'Child 1'!$D$81,NA()) -> #N/A | V48: =IF(17<=$C$8,'Child 2'!$D$81,NA()) -> #N/A | W48: =IF(17<=$C$8,'Child 3'!$D$81,NA()) -> #N/A | X48: =IF(17<=$C$8,'Child 4'!$D$81,NA()) -> #N/A | Y48: =IF(17<=$C$8,E48,NA()) -> #N/A
B49: =IF(18<=$C$8,(PlanYear+17)&"/"&RIGHT(PlanYear+18,2),"") | C49: =IF(18<=$C$8,MID(IF('Child 1'!$Q$82=1,", "&IF(Inputs!$C$14<>"",Inputs!$C$14,"Child 1"),"")&IF('Child 2'!$Q$82=1,", "&IF(Inputs!$D$14<>"",Inputs!$D$14,"Child 2"),"")&IF('Child 3'!$Q$82=1,", "&IF(Inputs!$E$14<>"",Inputs!$E$14,"Child 3"),"")&IF('Child 4'!$Q$82=1,", "&IF(Inputs!$F$14<>"",Inputs!$F$14,"Child 4"),""),3,200),"") | D49: =IF(18<=$C$8,ROUND('Child 1'!$M$82+'Child 2'!$M$82+'Child 3'!$M$82+'Child 4'!$M$82,2),"") | E49: =IF(18<=$C$8,ROUND('Child 1'!$N$82+'Child 2'!$N$82+'Child 3'!$N$82+'Child 4'!$N$82,2),"") | F49: =IF(18<=$C$8,ROUND('Child 1'!$O$82+'Child 2'!$O$82+'Child 3'!$O$82+'Child 4'!$O$82,2),"") | G49: =IF(18<=$C$8,ROUND('Child 1'!$D$82+'Child 2'!$D$82+'Child 3'!$D$82+'Child 4'!$D$82,2),"") | H49: =IF(18<=$C$8,ROUND('Child 1'!$P$82+'Child 2'!$P$82+'Child 3'!$P$82+'Child 4'!$P$82,2),"") | T49: =IF(18<=$C$8,B49,"") | U49: =IF(18<=$C$8,'Child 1'!$D$82,NA()) -> #N/A | V49: =IF(18<=$C$8,'Child 2'!$D$82,NA()) -> #N/A | W49: =IF(18<=$C$8,'Child 3'!$D$82,NA()) -> #N/A | X49: =IF(18<=$C$8,'Child 4'!$D$82,NA()) -> #N/A | Y49: =IF(18<=$C$8,E49,NA()) -> #N/A
B50: =IF(19<=$C$8,(PlanYear+18)&"/"&RIGHT(PlanYear+19,2),"") | C50: =IF(19<=$C$8,MID(IF('Child 1'!$Q$83=1,", "&IF(Inputs!$C$14<>"",Inputs!$C$14,"Child 1"),"")&IF('Child 2'!$Q$83=1,", "&IF(Inputs!$D$14<>"",Inputs!$D$14,"Child 2"),"")&IF('Child 3'!$Q$83=1,", "&IF(Inputs!$E$14<>"",Inputs!$E$14,"Child 3"),"")&IF('Child 4'!$Q$83=1,", "&IF(Inputs!$F$14<>"",Inputs!$F$14,"Child 4"),""),3,200),"") | D50: =IF(19<=$C$8,ROUND('Child 1'!$M$83+'Child 2'!$M$83+'Child 3'!$M$83+'Child 4'!$M$83,2),"") | E50: =IF(19<=$C$8,ROUND('Child 1'!$N$83+'Child 2'!$N$83+'Child 3'!$N$83+'Child 4'!$N$83,2),"") | F50: =IF(19<=$C$8,ROUND('Child 1'!$O$83+'Child 2'!$O$83+'Child 3'!$O$83+'Child 4'!$O$83,2),"") | G50: =IF(19<=$C$8,ROUND('Child 1'!$D$83+'Child 2'!$D$83+'Child 3'!$D$83+'Child 4'!$D$83,2),"") | H50: =IF(19<=$C$8,ROUND('Child 1'!$P$83+'Child 2'!$P$83+'Child 3'!$P$83+'Child 4'!$P$83,2),"") | T50: =IF(19<=$C$8,B50,"") | U50: =IF(19<=$C$8,'Child 1'!$D$83,NA()) -> #N/A | V50: =IF(19<=$C$8,'Child 2'!$D$83,NA()) -> #N/A | W50: =IF(19<=$C$8,'Child 3'!$D$83,NA()) -> #N/A | X50: =IF(19<=$C$8,'Child 4'!$D$83,NA()) -> #N/A | Y50: =IF(19<=$C$8,E50,NA()) -> #N/A
B51: =IF(20<=$C$8,(PlanYear+19)&"/"&RIGHT(PlanYear+20,2),"") | C51: =IF(20<=$C$8,MID(IF('Child 1'!$Q$84=1,", "&IF(Inputs!$C$14<>"",Inputs!$C$14,"Child 1"),"")&IF('Child 2'!$Q$84=1,", "&IF(Inputs!$D$14<>"",Inputs!$D$14,"Child 2"),"")&IF('Child 3'!$Q$84=1,", "&IF(Inputs!$E$14<>"",Inputs!$E$14,"Child 3"),"")&IF('Child 4'!$Q$84=1,", "&IF(Inputs!$F$14<>"",Inputs!$F$14,"Child 4"),""),3,200),"") | D51: =IF(20<=$C$8,ROUND('Child 1'!$M$84+'Child 2'!$M$84+'Child 3'!$M$84+'Child 4'!$M$84,2),"") | E51: =IF(20<=$C$8,ROUND('Child 1'!$N$84+'Child 2'!$N$84+'Child 3'!$N$84+'Child 4'!$N$84,2),"") | F51: =IF(20<=$C$8,ROUND('Child 1'!$O$84+'Child 2'!$O$84+'Child 3'!$O$84+'Child 4'!$O$84,2),"") | G51: =IF(20<=$C$8,ROUND('Child 1'!$D$84+'Child 2'!$D$84+'Child 3'!$D$84+'Child 4'!$D$84,2),"") | H51: =IF(20<=$C$8,ROUND('Child 1'!$P$84+'Child 2'!$P$84+'Child 3'!$P$84+'Child 4'!$P$84,2),"") | T51: =IF(20<=$C$8,B51,"") | U51: =IF(20<=$C$8,'Child 1'!$D$84,NA()) -> #N/A | V51: =IF(20<=$C$8,'Child 2'!$D$84,NA()) -> #N/A | W51: =IF(20<=$C$8,'Child 3'!$D$84,NA()) -> #N/A | X51: =IF(20<=$C$8,'Child 4'!$D$84,NA()) -> #N/A | Y51: =IF(20<=$C$8,E51,NA()) -> #N/A
B52: =IF(21<=$C$8,(PlanYear+20)&"/"&RIGHT(PlanYear+21,2),"") | C52: =IF(21<=$C$8,MID(IF('Child 1'!$Q$85=1,", "&IF(Inputs!$C$14<>"",Inputs!$C$14,"Child 1"),"")&IF('Child 2'!$Q$85=1,", "&IF(Inputs!$D$14<>"",Inputs!$D$14,"Child 2"),"")&IF('Child 3'!$Q$85=1,", "&IF(Inputs!$E$14<>"",Inputs!$E$14,"Child 3"),"")&IF('Child 4'!$Q$85=1,", "&IF(Inputs!$F$14<>"",Inputs!$F$14,"Child 4"),""),3,200),"") | D52: =IF(21<=$C$8,ROUND('Child 1'!$M$85+'Child 2'!$M$85+'Child 3'!$M$85+'Child 4'!$M$85,2),"") | E52: =IF(21<=$C$8,ROUND('Child 1'!$N$85+'Child 2'!$N$85+'Child 3'!$N$85+'Child 4'!$N$85,2),"") | F52: =IF(21<=$C$8,ROUND('Child 1'!$O$85+'Child 2'!$O$85+'Child 3'!$O$85+'Child 4'!$O$85,2),"") | G52: =IF(21<=$C$8,ROUND('Child 1'!$D$85+'Child 2'!$D$85+'Child 3'!$D$85+'Child 4'!$D$85,2),"") | H52: =IF(21<=$C$8,ROUND('Child 1'!$P$85+'Child 2'!$P$85+'Child 3'!$P$85+'Child 4'!$P$85,2),"") | T52: =IF(21<=$C$8,B52,"") | U52: =IF(21<=$C$8,'Child 1'!$D$85,NA()) -> #N/A | V52: =IF(21<=$C$8,'Child 2'!$D$85,NA()) -> #N/A | W52: =IF(21<=$C$8,'Child 3'!$D$85,NA()) -> #N/A | X52: =IF(21<=$C$8,'Child 4'!$D$85,NA()) -> #N/A | Y52: =IF(21<=$C$8,E52,NA()) -> #N/A
B53: =IF(22<=$C$8,(PlanYear+21)&"/"&RIGHT(PlanYear+22,2),"") | C53: =IF(22<=$C$8,MID(IF('Child 1'!$Q$86=1,", "&IF(Inputs!$C$14<>"",Inputs!$C$14,"Child 1"),"")&IF('Child 2'!$Q$86=1,", "&IF(Inputs!$D$14<>"",Inputs!$D$14,"Child 2"),"")&IF('Child 3'!$Q$86=1,", "&IF(Inputs!$E$14<>"",Inputs!$E$14,"Child 3"),"")&IF('Child 4'!$Q$86=1,", "&IF(Inputs!$F$14<>"",Inputs!$F$14,"Child 4"),""),3,200),"") | D53: =IF(22<=$C$8,ROUND('Child 1'!$M$86+'Child 2'!$M$86+'Child 3'!$M$86+'Child 4'!$M$86,2),"") | E53: =IF(22<=$C$8,ROUND('Child 1'!$N$86+'Child 2'!$N$86+'Child 3'!$N$86+'Child 4'!$N$86,2),"") | F53: =IF(22<=$C$8,ROUND('Child 1'!$O$86+'Child 2'!$O$86+'Child 3'!$O$86+'Child 4'!$O$86,2),"") | G53: =IF(22<=$C$8,ROUND('Child 1'!$D$86+'Child 2'!$D$86+'Child 3'!$D$86+'Child 4'!$D$86,2),"") | H53: =IF(22<=$C$8,ROUND('Child 1'!$P$86+'Child 2'!$P$86+'Child 3'!$P$86+'Child 4'!$P$86,2),"") | T53: =IF(22<=$C$8,B53,"") | U53: =IF(22<=$C$8,'Child 1'!$D$86,NA()) -> #N/A | V53: =IF(22<=$C$8,'Child 2'!$D$86,NA()) -> #N/A | W53: =IF(22<=$C$8,'Child 3'!$D$86,NA()) -> #N/A | X53: =IF(22<=$C$8,'Child 4'!$D$86,NA()) -> #N/A | Y53: =IF(22<=$C$8,E53,NA()) -> #N/A
B54: =IF(23<=$C$8,(PlanYear+22)&"/"&RIGHT(PlanYear+23,2),"") | C54: =IF(23<=$C$8,MID(IF('Child 1'!$Q$87=1,", "&IF(Inputs!$C$14<>"",Inputs!$C$14,"Child 1"),"")&IF('Child 2'!$Q$87=1,", "&IF(Inputs!$D$14<>"",Inputs!$D$14,"Child 2"),"")&IF('Child 3'!$Q$87=1,", "&IF(Inputs!$E$14<>"",Inputs!$E$14,"Child 3"),"")&IF('Child 4'!$Q$87=1,", "&IF(Inputs!$F$14<>"",Inputs!$F$14,"Child 4"),""),3,200),"") | D54: =IF(23<=$C$8,ROUND('Child 1'!$M$87+'Child 2'!$M$87+'Child 3'!$M$87+'Child 4'!$M$87,2),"") | E54: =IF(23<=$C$8,ROUND('Child 1'!$N$87+'Child 2'!$N$87+'Child 3'!$N$87+'Child 4'!$N$87,2),"") | F54: =IF(23<=$C$8,ROUND('Child 1'!$O$87+'Child 2'!$O$87+'Child 3'!$O$87+'Child 4'!$O$87,2),"") | G54: =IF(23<=$C$8,ROUND('Child 1'!$D$87+'Child 2'!$D$87+'Child 3'!$D$87+'Child 4'!$D$87,2),"") | H54: =IF(23<=$C$8,ROUND('Child 1'!$P$87+'Child 2'!$P$87+'Child 3'!$P$87+'Child 4'!$P$87,2),"") | T54: =IF(23<=$C$8,B54,"") | U54: =IF(23<=$C$8,'Child 1'!$D$87,NA()) -> #N/A | V54: =IF(23<=$C$8,'Child 2'!$D$87,NA()) -> #N/A | W54: =IF(23<=$C$8,'Child 3'!$D$87,NA()) -> #N/A | X54: =IF(23<=$C$8,'Child 4'!$D$87,NA()) -> #N/A | Y54: =IF(23<=$C$8,E54,NA()) -> #N/A
B55: =IF(24<=$C$8,(PlanYear+23)&"/"&RIGHT(PlanYear+24,2),"") | C55: =IF(24<=$C$8,MID(IF('Child 1'!$Q$88=1,", "&IF(Inputs!$C$14<>"",Inputs!$C$14,"Child 1"),"")&IF('Child 2'!$Q$88=1,", "&IF(Inputs!$D$14<>"",Inputs!$D$14,"Child 2"),"")&IF('Child 3'!$Q$88=1,", "&IF(Inputs!$E$14<>"",Inputs!$E$14,"Child 3"),"")&IF('Child 4'!$Q$88=1,", "&IF(Inputs!$F$14<>"",Inputs!$F$14,"Child 4"),""),3,200),"") | D55: =IF(24<=$C$8,ROUND('Child 1'!$M$88+'Child 2'!$M$88+'Child 3'!$M$88+'Child 4'!$M$88,2),"") | E55: =IF(24<=$C$8,ROUND('Child 1'!$N$88+'Child 2'!$N$88+'Child 3'!$N$88+'Child 4'!$N$88,2),"") | F55: =IF(24<=$C$8,ROUND('Child 1'!$O$88+'Child 2'!$O$88+'Child 3'!$O$88+'Child 4'!$O$88,2),"") | G55: =IF(24<=$C$8,ROUND('Child 1'!$D$88+'Child 2'!$D$88+'Child 3'!$D$88+'Child 4'!$D$88,2),"") | H55: =IF(24<=$C$8,ROUND('Child 1'!$P$88+'Child 2'!$P$88+'Child 3'!$P$88+'Child 4'!$P$88,2),"") | T55: =IF(24<=$C$8,B55,"") | U55: =IF(24<=$C$8,'Child 1'!$D$88,NA()) -> #N/A | V55: =IF(24<=$C$8,'Child 2'!$D$88,NA()) -> #N/A | W55: =IF(24<=$C$8,'Child 3'!$D$88,NA()) -> #N/A | X55: =IF(24<=$C$8,'Child 4'!$D$88,NA()) -> #N/A | Y55: =IF(24<=$C$8,E55,NA()) -> #N/A
B56: =IF(25<=$C$8,(PlanYear+24)&"/"&RIGHT(PlanYear+25,2),"") | C56: =IF(25<=$C$8,MID(IF('Child 1'!$Q$89=1,", "&IF(Inputs!$C$14<>"",Inputs!$C$14,"Child 1"),"")&IF('Child 2'!$Q$89=1,", "&IF(Inputs!$D$14<>"",Inputs!$D$14,"Child 2"),"")&IF('Child 3'!$Q$89=1,", "&IF(Inputs!$E$14<>"",Inputs!$E$14,"Child 3"),"")&IF('Child 4'!$Q$89=1,", "&IF(Inputs!$F$14<>"",Inputs!$F$14,"Child 4"),""),3,200),"") | D56: =IF(25<=$C$8,ROUND('Child 1'!$M$89+'Child 2'!$M$89+'Child 3'!$M$89+'Child 4'!$M$89,2),"") | E56: =IF(25<=$C$8,ROUND('Child 1'!$N$89+'Child 2'!$N$89+'Child 3'!$N$89+'Child 4'!$N$89,2),"") | F56: =IF(25<=$C$8,ROUND('Child 1'!$O$89+'Child 2'!$O$89+'Child 3'!$O$89+'Child 4'!$O$89,2),"") | G56: =IF(25<=$C$8,ROUND('Child 1'!$D$89+'Child 2'!$D$89+'Child 3'!$D$89+'Child 4'!$D$89,2),"") | H56: =IF(25<=$C$8,ROUND('Child 1'!$P$89+'Child 2'!$P$89+'Child 3'!$P$89+'Child 4'!$P$89,2),"") | T56: =IF(25<=$C$8,B56,"") | U56: =IF(25<=$C$8,'Child 1'!$D$89,NA()) -> #N/A | V56: =IF(25<=$C$8,'Child 2'!$D$89,NA()) -> #N/A | W56: =IF(25<=$C$8,'Child 3'!$D$89,NA()) -> #N/A | X56: =IF(25<=$C$8,'Child 4'!$D$89,NA()) -> #N/A | Y56: =IF(25<=$C$8,E56,NA()) -> #N/A
B57: =IF(26<=$C$8,(PlanYear+25)&"/"&RIGHT(PlanYear+26,2),"") | C57: =IF(26<=$C$8,MID(IF('Child 1'!$Q$90=1,", "&IF(Inputs!$C$14<>"",Inputs!$C$14,"Child 1"),"")&IF('Child 2'!$Q$90=1,", "&IF(Inputs!$D$14<>"",Inputs!$D$14,"Child 2"),"")&IF('Child 3'!$Q$90=1,", "&IF(Inputs!$E$14<>"",Inputs!$E$14,"Child 3"),"")&IF('Child 4'!$Q$90=1,", "&IF(Inputs!$F$14<>"",Inputs!$F$14,"Child 4"),""),3,200),"") | D57: =IF(26<=$C$8,ROUND('Child 1'!$M$90+'Child 2'!$M$90+'Child 3'!$M$90+'Child 4'!$M$90,2),"") | E57: =IF(26<=$C$8,ROUND('Child 1'!$N$90+'Child 2'!$N$90+'Child 3'!$N$90+'Child 4'!$N$90,2),"") | F57: =IF(26<=$C$8,ROUND('Child 1'!$O$90+'Child 2'!$O$90+'Child 3'!$O$90+'Child 4'!$O$90,2),"") | G57: =IF(26<=$C$8,ROUND('Child 1'!$D$90+'Child 2'!$D$90+'Child 3'!$D$90+'Child 4'!$D$90,2),"") | H57: =IF(26<=$C$8,ROUND('Child 1'!$P$90+'Child 2'!$P$90+'Child 3'!$P$90+'Child 4'!$P$90,2),"") | T57: =IF(26<=$C$8,B57,"") | U57: =IF(26<=$C$8,'Child 1'!$D$90,NA()) -> #N/A | V57: =IF(26<=$C$8,'Child 2'!$D$90,NA()) -> #N/A | W57: =IF(26<=$C$8,'Child 3'!$D$90,NA()) -> #N/A | X57: =IF(26<=$C$8,'Child 4'!$D$90,NA()) -> #N/A | Y57: =IF(26<=$C$8,E57,NA()) -> #N/A
B58: =IF(27<=$C$8,(PlanYear+26)&"/"&RIGHT(PlanYear+27,2),"") | C58: =IF(27<=$C$8,MID(IF('Child 1'!$Q$91=1,", "&IF(Inputs!$C$14<>"",Inputs!$C$14,"Child 1"),"")&IF('Child 2'!$Q$91=1,", "&IF(Inputs!$D$14<>"",Inputs!$D$14,"Child 2"),"")&IF('Child 3'!$Q$91=1,", "&IF(Inputs!$E$14<>"",Inputs!$E$14,"Child 3"),"")&IF('Child 4'!$Q$91=1,", "&IF(Inputs!$F$14<>"",Inputs!$F$14,"Child 4"),""),3,200),"") | D58: =IF(27<=$C$8,ROUND('Child 1'!$M$91+'Child 2'!$M$91+'Child 3'!$M$91+'Child 4'!$M$91,2),"") | E58: =IF(27<=$C$8,ROUND('Child 1'!$N$91+'Child 2'!$N$91+'Child 3'!$N$91+'Child 4'!$N$91,2),"") | F58: =IF(27<=$C$8,ROUND('Child 1'!$O$91+'Child 2'!$O$91+'Child 3'!$O$91+'Child 4'!$O$91,2),"") | G58: =IF(27<=$C$8,ROUND('Child 1'!$D$91+'Child 2'!$D$91+'Child 3'!$D$91+'Child 4'!$D$91,2),"") | H58: =IF(27<=$C$8,ROUND('Child 1'!$P$91+'Child 2'!$P$91+'Child 3'!$P$91+'Child 4'!$P$91,2),"") | T58: =IF(27<=$C$8,B58,"") | U58: =IF(27<=$C$8,'Child 1'!$D$91,NA()) -> #N/A | V58: =IF(27<=$C$8,'Child 2'!$D$91,NA()) -> #N/A | W58: =IF(27<=$C$8,'Child 3'!$D$91,NA()) -> #N/A | X58: =IF(27<=$C$8,'Child 4'!$D$91,NA()) -> #N/A | Y58: =IF(27<=$C$8,E58,NA()) -> #N/A
B59: =IF(28<=$C$8,(PlanYear+27)&"/"&RIGHT(PlanYear+28,2),"") | C59: =IF(28<=$C$8,MID(IF('Child 1'!$Q$92=1,", "&IF(Inputs!$C$14<>"",Inputs!$C$14,"Child 1"),"")&IF('Child 2'!$Q$92=1,", "&IF(Inputs!$D$14<>"",Inputs!$D$14,"Child 2"),"")&IF('Child 3'!$Q$92=1,", "&IF(Inputs!$E$14<>"",Inputs!$E$14,"Child 3"),"")&IF('Child 4'!$Q$92=1,", "&IF(Inputs!$F$14<>"",Inputs!$F$14,"Child 4"),""),3,200),"") | D59: =IF(28<=$C$8,ROUND('Child 1'!$M$92+'Child 2'!$M$92+'Child 3'!$M$92+'Child 4'!$M$92,2),"") | E59: =IF(28<=$C$8,ROUND('Child 1'!$N$92+'Child 2'!$N$92+'Child 3'!$N$92+'Child 4'!$N$92,2),"") | F59: =IF(28<=$C$8,ROUND('Child 1'!$O$92+'Child 2'!$O$92+'Child 3'!$O$92+'Child 4'!$O$92,2),"") | G59: =IF(28<=$C$8,ROUND('Child 1'!$D$92+'Child 2'!$D$92+'Child 3'!$D$92+'Child 4'!$D$92,2),"") | H59: =IF(28<=$C$8,ROUND('Child 1'!$P$92+'Child 2'!$P$92+'Child 3'!$P$92+'Child 4'!$P$92,2),"") | T59: =IF(28<=$C$8,B59,"") | U59: =IF(28<=$C$8,'Child 1'!$D$92,NA()) -> #N/A | V59: =IF(28<=$C$8,'Child 2'!$D$92,NA()) -> #N/A | W59: =IF(28<=$C$8,'Child 3'!$D$92,NA()) -> #N/A | X59: =IF(28<=$C$8,'Child 4'!$D$92,NA()) -> #N/A | Y59: =IF(28<=$C$8,E59,NA()) -> #N/A
B60: =IF(29<=$C$8,(PlanYear+28)&"/"&RIGHT(PlanYear+29,2),"") | C60: =IF(29<=$C$8,MID(IF('Child 1'!$Q$93=1,", "&IF(Inputs!$C$14<>"",Inputs!$C$14,"Child 1"),"")&IF('Child 2'!$Q$93=1,", "&IF(Inputs!$D$14<>"",Inputs!$D$14,"Child 2"),"")&IF('Child 3'!$Q$93=1,", "&IF(Inputs!$E$14<>"",Inputs!$E$14,"Child 3"),"")&IF('Child 4'!$Q$93=1,", "&IF(Inputs!$F$14<>"",Inputs!$F$14,"Child 4"),""),3,200),"") | D60: =IF(29<=$C$8,ROUND('Child 1'!$M$93+'Child 2'!$M$93+'Child 3'!$M$93+'Child 4'!$M$93,2),"") | E60: =IF(29<=$C$8,ROUND('Child 1'!$N$93+'Child 2'!$N$93+'Child 3'!$N$93+'Child 4'!$N$93,2),"") | F60: =IF(29<=$C$8,ROUND('Child 1'!$O$93+'Child 2'!$O$93+'Child 3'!$O$93+'Child 4'!$O$93,2),"") | G60: =IF(29<=$C$8,ROUND('Child 1'!$D$93+'Child 2'!$D$93+'Child 3'!$D$93+'Child 4'!$D$93,2),"") | H60: =IF(29<=$C$8,ROUND('Child 1'!$P$93+'Child 2'!$P$93+'Child 3'!$P$93+'Child 4'!$P$93,2),"") | T60: =IF(29<=$C$8,B60,"") | U60: =IF(29<=$C$8,'Child 1'!$D$93,NA()) -> #N/A | V60: =IF(29<=$C$8,'Child 2'!$D$93,NA()) -> #N/A | W60: =IF(29<=$C$8,'Child 3'!$D$93,NA()) -> #N/A | X60: =IF(29<=$C$8,'Child 4'!$D$93,NA()) -> #N/A | Y60: =IF(29<=$C$8,E60,NA()) -> #N/A
B61: =IF(30<=$C$8,(PlanYear+29)&"/"&RIGHT(PlanYear+30,2),"") | C61: =IF(30<=$C$8,MID(IF('Child 1'!$Q$94=1,", "&IF(Inputs!$C$14<>"",Inputs!$C$14,"Child 1"),"")&IF('Child 2'!$Q$94=1,", "&IF(Inputs!$D$14<>"",Inputs!$D$14,"Child 2"),"")&IF('Child 3'!$Q$94=1,", "&IF(Inputs!$E$14<>"",Inputs!$E$14,"Child 3"),"")&IF('Child 4'!$Q$94=1,", "&IF(Inputs!$F$14<>"",Inputs!$F$14,"Child 4"),""),3,200),"") | D61: =IF(30<=$C$8,ROUND('Child 1'!$M$94+'Child 2'!$M$94+'Child 3'!$M$94+'Child 4'!$M$94,2),"") | E61: =IF(30<=$C$8,ROUND('Child 1'!$N$94+'Child 2'!$N$94+'Child 3'!$N$94+'Child 4'!$N$94,2),"") | F61: =IF(30<=$C$8,ROUND('Child 1'!$O$94+'Child 2'!$O$94+'Child 3'!$O$94+'Child 4'!$O$94,2),"") | G61: =IF(30<=$C$8,ROUND('Child 1'!$D$94+'Child 2'!$D$94+'Child 3'!$D$94+'Child 4'!$D$94,2),"") | H61: =IF(30<=$C$8,ROUND('Child 1'!$P$94+'Child 2'!$P$94+'Child 3'!$P$94+'Child 4'!$P$94,2),"") | T61: =IF(30<=$C$8,B61,"") | U61: =IF(30<=$C$8,'Child 1'!$D$94,NA()) -> #N/A | V61: =IF(30<=$C$8,'Child 2'!$D$94,NA()) -> #N/A | W61: =IF(30<=$C$8,'Child 3'!$D$94,NA()) -> #N/A | X61: =IF(30<=$C$8,'Child 4'!$D$94,NA()) -> #N/A | Y61: =IF(30<=$C$8,E61,NA()) -> #N/A
B62: =IF(31<=$C$8,(PlanYear+30)&"/"&RIGHT(PlanYear+31,2),"") | C62: =IF(31<=$C$8,MID(IF('Child 1'!$Q$95=1,", "&IF(Inputs!$C$14<>"",Inputs!$C$14,"Child 1"),"")&IF('Child 2'!$Q$95=1,", "&IF(Inputs!$D$14<>"",Inputs!$D$14,"Child 2"),"")&IF('Child 3'!$Q$95=1,", "&IF(Inputs!$E$14<>"",Inputs!$E$14,"Child 3"),"")&IF('Child 4'!$Q$95=1,", "&IF(Inputs!$F$14<>"",Inputs!$F$14,"Child 4"),""),3,200),"") | D62: =IF(31<=$C$8,ROUND('Child 1'!$M$95+'Child 2'!$M$95+'Child 3'!$M$95+'Child 4'!$M$95,2),"") | E62: =IF(31<=$C$8,ROUND('Child 1'!$N$95+'Child 2'!$N$95+'Child 3'!$N$95+'Child 4'!$N$95,2),"") | F62: =IF(31<=$C$8,ROUND('Child 1'!$O$95+'Child 2'!$O$95+'Child 3'!$O$95+'Child 4'!$O$95,2),"") | G62: =IF(31<=$C$8,ROUND('Child 1'!$D$95+'Child 2'!$D$95+'Child 3'!$D$95+'Child 4'!$D$95,2),"") | H62: =IF(31<=$C$8,ROUND('Child 1'!$P$95+'Child 2'!$P$95+'Child 3'!$P$95+'Child 4'!$P$95,2),"")
B63: =IF(32<=$C$8,(PlanYear+31)&"/"&RIGHT(PlanYear+32,2),"") | C63: =IF(32<=$C$8,MID(IF('Child 1'!$Q$96=1,", "&IF(Inputs!$C$14<>"",Inputs!$C$14,"Child 1"),"")&IF('Child 2'!$Q$96=1,", "&IF(Inputs!$D$14<>"",Inputs!$D$14,"Child 2"),"")&IF('Child 3'!$Q$96=1,", "&IF(Inputs!$E$14<>"",Inputs!$E$14,"Child 3"),"")&IF('Child 4'!$Q$96=1,", "&IF(Inputs!$F$14<>"",Inputs!$F$14,"Child 4"),""),3,200),"") | D63: =IF(32<=$C$8,ROUND('Child 1'!$M$96+'Child 2'!$M$96+'Child 3'!$M$96+'Child 4'!$M$96,2),"") | E63: =IF(32<=$C$8,ROUND('Child 1'!$N$96+'Child 2'!$N$96+'Child 3'!$N$96+'Child 4'!$N$96,2),"") | F63: =IF(32<=$C$8,ROUND('Child 1'!$O$96+'Child 2'!$O$96+'Child 3'!$O$96+'Child 4'!$O$96,2),"") | G63: =IF(32<=$C$8,ROUND('Child 1'!$D$96+'Child 2'!$D$96+'Child 3'!$D$96+'Child 4'!$D$96,2),"") | H63: =IF(32<=$C$8,ROUND('Child 1'!$P$96+'Child 2'!$P$96+'Child 3'!$P$96+'Child 4'!$P$96,2),"")
B64: =IF(33<=$C$8,(PlanYear+32)&"/"&RIGHT(PlanYear+33,2),"") | C64: =IF(33<=$C$8,MID(IF('Child 1'!$Q$97=1,", "&IF(Inputs!$C$14<>"",Inputs!$C$14,"Child 1"),"")&IF('Child 2'!$Q$97=1,", "&IF(Inputs!$D$14<>"",Inputs!$D$14,"Child 2"),"")&IF('Child 3'!$Q$97=1,", "&IF(Inputs!$E$14<>"",Inputs!$E$14,"Child 3"),"")&IF('Child 4'!$Q$97=1,", "&IF(Inputs!$F$14<>"",Inputs!$F$14,"Child 4"),""),3,200),"") | D64: =IF(33<=$C$8,ROUND('Child 1'!$M$97+'Child 2'!$M$97+'Child 3'!$M$97+'Child 4'!$M$97,2),"") | E64: =IF(33<=$C$8,ROUND('Child 1'!$N$97+'Child 2'!$N$97+'Child 3'!$N$97+'Child 4'!$N$97,2),"") | F64: =IF(33<=$C$8,ROUND('Child 1'!$O$97+'Child 2'!$O$97+'Child 3'!$O$97+'Child 4'!$O$97,2),"") | G64: =IF(33<=$C$8,ROUND('Child 1'!$D$97+'Child 2'!$D$97+'Child 3'!$D$97+'Child 4'!$D$97,2),"") | H64: =IF(33<=$C$8,ROUND('Child 1'!$P$97+'Child 2'!$P$97+'Child 3'!$P$97+'Child 4'!$P$97,2),"")
B65: =IF(34<=$C$8,(PlanYear+33)&"/"&RIGHT(PlanYear+34,2),"") | C65: =IF(34<=$C$8,MID(IF('Child 1'!$Q$98=1,", "&IF(Inputs!$C$14<>"",Inputs!$C$14,"Child 1"),"")&IF('Child 2'!$Q$98=1,", "&IF(Inputs!$D$14<>"",Inputs!$D$14,"Child 2"),"")&IF('Child 3'!$Q$98=1,", "&IF(Inputs!$E$14<>"",Inputs!$E$14,"Child 3"),"")&IF('Child 4'!$Q$98=1,", "&IF(Inputs!$F$14<>"",Inputs!$F$14,"Child 4"),""),3,200),"") | D65: =IF(34<=$C$8,ROUND('Child 1'!$M$98+'Child 2'!$M$98+'Child 3'!$M$98+'Child 4'!$M$98,2),"") | E65: =IF(34<=$C$8,ROUND('Child 1'!$N$98+'Child 2'!$N$98+'Child 3'!$N$98+'Child 4'!$N$98,2),"") | F65: =IF(34<=$C$8,ROUND('Child 1'!$O$98+'Child 2'!$O$98+'Child 3'!$O$98+'Child 4'!$O$98,2),"") | G65: =IF(34<=$C$8,ROUND('Child 1'!$D$98+'Child 2'!$D$98+'Child 3'!$D$98+'Child 4'!$D$98,2),"") | H65: =IF(34<=$C$8,ROUND('Child 1'!$P$98+'Child 2'!$P$98+'Child 3'!$P$98+'Child 4'!$P$98,2),"")
B66: =IF(35<=$C$8,(PlanYear+34)&"/"&RIGHT(PlanYear+35,2),"") | C66: =IF(35<=$C$8,MID(IF('Child 1'!$Q$99=1,", "&IF(Inputs!$C$14<>"",Inputs!$C$14,"Child 1"),"")&IF('Child 2'!$Q$99=1,", "&IF(Inputs!$D$14<>"",Inputs!$D$14,"Child 2"),"")&IF('Child 3'!$Q$99=1,", "&IF(Inputs!$E$14<>"",Inputs!$E$14,"Child 3"),"")&IF('Child 4'!$Q$99=1,", "&IF(Inputs!$F$14<>"",Inputs!$F$14,"Child 4"),""),3,200),"") | D66: =IF(35<=$C$8,ROUND('Child 1'!$M$99+'Child 2'!$M$99+'Child 3'!$M$99+'Child 4'!$M$99,2),"") | E66: =IF(35<=$C$8,ROUND('Child 1'!$N$99+'Child 2'!$N$99+'Child 3'!$N$99+'Child 4'!$N$99,2),"") | F66: =IF(35<=$C$8,ROUND('Child 1'!$O$99+'Child 2'!$O$99+'Child 3'!$O$99+'Child 4'!$O$99,2),"") | G66: =IF(35<=$C$8,ROUND('Child 1'!$D$99+'Child 2'!$D$99+'Child 3'!$D$99+'Child 4'!$D$99,2),"") | H66: =IF(35<=$C$8,ROUND('Child 1'!$P$99+'Child 2'!$P$99+'Child 3'!$P$99+'Child 4'!$P$99,2),"")
B67: =IF(36<=$C$8,(PlanYear+35)&"/"&RIGHT(PlanYear+36,2),"") | C67: =IF(36<=$C$8,MID(IF('Child 1'!$Q$100=1,", "&IF(Inputs!$C$14<>"",Inputs!$C$14,"Child 1"),"")&IF('Child 2'!$Q$100=1,", "&IF(Inputs!$D$14<>"",Inputs!$D$14,"Child 2"),"")&IF('Child 3'!$Q$100=1,", "&IF(Inputs!$E$14<>"",Inputs!$E$14,"Child 3"),"")&IF('Child 4'!$Q$100=1,", "&IF(Inputs!$F$14<>"",Inputs!$F$14,"Child 4"),""),3,200),"") | D67: =IF(36<=$C$8,ROUND('Child 1'!$M$100+'Child 2'!$M$100+'Child 3'!$M$100+'Child 4'!$M$100,2),"") | E67: =IF(36<=$C$8,ROUND('Child 1'!$N$100+'Child 2'!$N$100+'Child 3'!$N$100+'Child 4'!$N$100,2),"") | F67: =IF(36<=$C$8,ROUND('Child 1'!$O$100+'Child 2'!$O$100+'Child 3'!$O$100+'Child 4'!$O$100,2),"") | G67: =IF(36<=$C$8,ROUND('Child 1'!$D$100+'Child 2'!$D$100+'Child 3'!$D$100+'Child 4'!$D$100,2),"") | H67: =IF(36<=$C$8,ROUND('Child 1'!$P$100+'Child 2'!$P$100+'Child 3'!$P$100+'Child 4'!$P$100,2),"")
B68: =IF(37<=$C$8,(PlanYear+36)&"/"&RIGHT(PlanYear+37,2),"") | C68: =IF(37<=$C$8,MID(IF('Child 1'!$Q$101=1,", "&IF(Inputs!$C$14<>"",Inputs!$C$14,"Child 1"),"")&IF('Child 2'!$Q$101=1,", "&IF(Inputs!$D$14<>"",Inputs!$D$14,"Child 2"),"")&IF('Child 3'!$Q$101=1,", "&IF(Inputs!$E$14<>"",Inputs!$E$14,"Child 3"),"")&IF('Child 4'!$Q$101=1,", "&IF(Inputs!$F$14<>"",Inputs!$F$14,"Child 4"),""),3,200),"") | D68: =IF(37<=$C$8,ROUND('Child 1'!$M$101+'Child 2'!$M$101+'Child 3'!$M$101+'Child 4'!$M$101,2),"") | E68: =IF(37<=$C$8,ROUND('Child 1'!$N$101+'Child 2'!$N$101+'Child 3'!$N$101+'Child 4'!$N$101,2),"") | F68: =IF(37<=$C$8,ROUND('Child 1'!$O$101+'Child 2'!$O$101+'Child 3'!$O$101+'Child 4'!$O$101,2),"") | G68: =IF(37<=$C$8,ROUND('Child 1'!$D$101+'Child 2'!$D$101+'Child 3'!$D$101+'Child 4'!$D$101,2),"") | H68: =IF(37<=$C$8,ROUND('Child 1'!$P$101+'Child 2'!$P$101+'Child 3'!$P$101+'Child 4'!$P$101,2),"")
B69: =IF(38<=$C$8,(PlanYear+37)&"/"&RIGHT(PlanYear+38,2),"") | C69: =IF(38<=$C$8,MID(IF('Child 1'!$Q$102=1,", "&IF(Inputs!$C$14<>"",Inputs!$C$14,"Child 1"),"")&IF('Child 2'!$Q$102=1,", "&IF(Inputs!$D$14<>"",Inputs!$D$14,"Child 2"),"")&IF('Child 3'!$Q$102=1,", "&IF(Inputs!$E$14<>"",Inputs!$E$14,"Child 3"),"")&IF('Child 4'!$Q$102=1,", "&IF(Inputs!$F$14<>"",Inputs!$F$14,"Child 4"),""),3,200),"") | D69: =IF(38<=$C$8,ROUND('Child 1'!$M$102+'Child 2'!$M$102+'Child 3'!$M$102+'Child 4'!$M$102,2),"") | E69: =IF(38<=$C$8,ROUND('Child 1'!$N$102+'Child 2'!$N$102+'Child 3'!$N$102+'Child 4'!$N$102,2),"") | F69: =IF(38<=$C$8,ROUND('Child 1'!$O$102+'Child 2'!$O$102+'Child 3'!$O$102+'Child 4'!$O$102,2),"") | G69: =IF(38<=$C$8,ROUND('Child 1'!$D$102+'Child 2'!$D$102+'Child 3'!$D$102+'Child 4'!$D$102,2),"") | H69: =IF(38<=$C$8,ROUND('Child 1'!$P$102+'Child 2'!$P$102+'Child 3'!$P$102+'Child 4'!$P$102,2),"")
B70: =IF(39<=$C$8,(PlanYear+38)&"/"&RIGHT(PlanYear+39,2),"") | C70: =IF(39<=$C$8,MID(IF('Child 1'!$Q$103=1,", "&IF(Inputs!$C$14<>"",Inputs!$C$14,"Child 1"),"")&IF('Child 2'!$Q$103=1,", "&IF(Inputs!$D$14<>"",Inputs!$D$14,"Child 2"),"")&IF('Child 3'!$Q$103=1,", "&IF(Inputs!$E$14<>"",Inputs!$E$14,"Child 3"),"")&IF('Child 4'!$Q$103=1,", "&IF(Inputs!$F$14<>"",Inputs!$F$14,"Child 4"),""),3,200),"") | D70: =IF(39<=$C$8,ROUND('Child 1'!$M$103+'Child 2'!$M$103+'Child 3'!$M$103+'Child 4'!$M$103,2),"") | E70: =IF(39<=$C$8,ROUND('Child 1'!$N$103+'Child 2'!$N$103+'Child 3'!$N$103+'Child 4'!$N$103,2),"") | F70: =IF(39<=$C$8,ROUND('Child 1'!$O$103+'Child 2'!$O$103+'Child 3'!$O$103+'Child 4'!$O$103,2),"") | G70: =IF(39<=$C$8,ROUND('Child 1'!$D$103+'Child 2'!$D$103+'Child 3'!$D$103+'Child 4'!$D$103,2),"") | H70: =IF(39<=$C$8,ROUND('Child 1'!$P$103+'Child 2'!$P$103+'Child 3'!$P$103+'Child 4'!$P$103,2),"")
B71: =IF(40<=$C$8,(PlanYear+39)&"/"&RIGHT(PlanYear+40,2),"") | C71: =IF(40<=$C$8,MID(IF('Child 1'!$Q$104=1,", "&IF(Inputs!$C$14<>"",Inputs!$C$14,"Child 1"),"")&IF('Child 2'!$Q$104=1,", "&IF(Inputs!$D$14<>"",Inputs!$D$14,"Child 2"),"")&IF('Child 3'!$Q$104=1,", "&IF(Inputs!$E$14<>"",Inputs!$E$14,"Child 3"),"")&IF('Child 4'!$Q$104=1,", "&IF(Inputs!$F$14<>"",Inputs!$F$14,"Child 4"),""),3,200),"") | D71: =IF(40<=$C$8,ROUND('Child 1'!$M$104+'Child 2'!$M$104+'Child 3'!$M$104+'Child 4'!$M$104,2),"") | E71: =IF(40<=$C$8,ROUND('Child 1'!$N$104+'Child 2'!$N$104+'Child 3'!$N$104+'Child 4'!$N$104,2),"") | F71: =IF(40<=$C$8,ROUND('Child 1'!$O$104+'Child 2'!$O$104+'Child 3'!$O$104+'Child 4'!$O$104,2),"") | G71: =IF(40<=$C$8,ROUND('Child 1'!$D$104+'Child 2'!$D$104+'Child 3'!$D$104+'Child 4'!$D$104,2),"") | H71: =IF(40<=$C$8,ROUND('Child 1'!$P$104+'Child 2'!$P$104+'Child 3'!$P$104+'Child 4'!$P$104,2),"")
B72: =IF(41<=$C$8,(PlanYear+40)&"/"&RIGHT(PlanYear+41,2),"") | C72: =IF(41<=$C$8,MID(IF('Child 1'!$Q$105=1,", "&IF(Inputs!$C$14<>"",Inputs!$C$14,"Child 1"),"")&IF('Child 2'!$Q$105=1,", "&IF(Inputs!$D$14<>"",Inputs!$D$14,"Child 2"),"")&IF('Child 3'!$Q$105=1,", "&IF(Inputs!$E$14<>"",Inputs!$E$14,"Child 3"),"")&IF('Child 4'!$Q$105=1,", "&IF(Inputs!$F$14<>"",Inputs!$F$14,"Child 4"),""),3,200),"") | D72: =IF(41<=$C$8,ROUND('Child 1'!$M$105+'Child 2'!$M$105+'Child 3'!$M$105+'Child 4'!$M$105,2),"") | E72: =IF(41<=$C$8,ROUND('Child 1'!$N$105+'Child 2'!$N$105+'Child 3'!$N$105+'Child 4'!$N$105,2),"") | F72: =IF(41<=$C$8,ROUND('Child 1'!$O$105+'Child 2'!$O$105+'Child 3'!$O$105+'Child 4'!$O$105,2),"") | G72: =IF(41<=$C$8,ROUND('Child 1'!$D$105+'Child 2'!$D$105+'Child 3'!$D$105+'Child 4'!$D$105,2),"") | H72: =IF(41<=$C$8,ROUND('Child 1'!$P$105+'Child 2'!$P$105+'Child 3'!$P$105+'Child 4'!$P$105,2),"")
B73: =IF(42<=$C$8,(PlanYear+41)&"/"&RIGHT(PlanYear+42,2),"") | C73: =IF(42<=$C$8,MID(IF('Child 1'!$Q$106=1,", "&IF(Inputs!$C$14<>"",Inputs!$C$14,"Child 1"),"")&IF('Child 2'!$Q$106=1,", "&IF(Inputs!$D$14<>"",Inputs!$D$14,"Child 2"),"")&IF('Child 3'!$Q$106=1,", "&IF(Inputs!$E$14<>"",Inputs!$E$14,"Child 3"),"")&IF('Child 4'!$Q$106=1,", "&IF(Inputs!$F$14<>"",Inputs!$F$14,"Child 4"),""),3,200),"") | D73: =IF(42<=$C$8,ROUND('Child 1'!$M$106+'Child 2'!$M$106+'Child 3'!$M$106+'Child 4'!$M$106,2),"") | E73: =IF(42<=$C$8,ROUND('Child 1'!$N$106+'Child 2'!$N$106+'Child 3'!$N$106+'Child 4'!$N$106,2),"") | F73: =IF(42<=$C$8,ROUND('Child 1'!$O$106+'Child 2'!$O$106+'Child 3'!$O$106+'Child 4'!$O$106,2),"") | G73: =IF(42<=$C$8,ROUND('Child 1'!$D$106+'Child 2'!$D$106+'Child 3'!$D$106+'Child 4'!$D$106,2),"") | H73: =IF(42<=$C$8,ROUND('Child 1'!$P$106+'Child 2'!$P$106+'Child 3'!$P$106+'Child 4'!$P$106,2),"")
B74: =IF(43<=$C$8,(PlanYear+42)&"/"&RIGHT(PlanYear+43,2),"") | C74: =IF(43<=$C$8,MID(IF('Child 1'!$Q$107=1,", "&IF(Inputs!$C$14<>"",Inputs!$C$14,"Child 1"),"")&IF('Child 2'!$Q$107=1,", "&IF(Inputs!$D$14<>"",Inputs!$D$14,"Child 2"),"")&IF('Child 3'!$Q$107=1,", "&IF(Inputs!$E$14<>"",Inputs!$E$14,"Child 3"),"")&IF('Child 4'!$Q$107=1,", "&IF(Inputs!$F$14<>"",Inputs!$F$14,"Child 4"),""),3,200),"") | D74: =IF(43<=$C$8,ROUND('Child 1'!$M$107+'Child 2'!$M$107+'Child 3'!$M$107+'Child 4'!$M$107,2),"") | E74: =IF(43<=$C$8,ROUND('Child 1'!$N$107+'Child 2'!$N$107+'Child 3'!$N$107+'Child 4'!$N$107,2),"") | F74: =IF(43<=$C$8,ROUND('Child 1'!$O$107+'Child 2'!$O$107+'Child 3'!$O$107+'Child 4'!$O$107,2),"") | G74: =IF(43<=$C$8,ROUND('Child 1'!$D$107+'Child 2'!$D$107+'Child 3'!$D$107+'Child 4'!$D$107,2),"") | H74: =IF(43<=$C$8,ROUND('Child 1'!$P$107+'Child 2'!$P$107+'Child 3'!$P$107+'Child 4'!$P$107,2),"")
B75: =IF(44<=$C$8,(PlanYear+43)&"/"&RIGHT(PlanYear+44,2),"") | C75: =IF(44<=$C$8,MID(IF('Child 1'!$Q$108=1,", "&IF(Inputs!$C$14<>"",Inputs!$C$14,"Child 1"),"")&IF('Child 2'!$Q$108=1,", "&IF(Inputs!$D$14<>"",Inputs!$D$14,"Child 2"),"")&IF('Child 3'!$Q$108=1,", "&IF(Inputs!$E$14<>"",Inputs!$E$14,"Child 3"),"")&IF('Child 4'!$Q$108=1,", "&IF(Inputs!$F$14<>"",Inputs!$F$14,"Child 4"),""),3,200),"") | D75: =IF(44<=$C$8,ROUND('Child 1'!$M$108+'Child 2'!$M$108+'Child 3'!$M$108+'Child 4'!$M$108,2),"") | E75: =IF(44<=$C$8,ROUND('Child 1'!$N$108+'Child 2'!$N$108+'Child 3'!$N$108+'Child 4'!$N$108,2),"") | F75: =IF(44<=$C$8,ROUND('Child 1'!$O$108+'Child 2'!$O$108+'Child 3'!$O$108+'Child 4'!$O$108,2),"") | G75: =IF(44<=$C$8,ROUND('Child 1'!$D$108+'Child 2'!$D$108+'Child 3'!$D$108+'Child 4'!$D$108,2),"") | H75: =IF(44<=$C$8,ROUND('Child 1'!$P$108+'Child 2'!$P$108+'Child 3'!$P$108+'Child 4'!$P$108,2),"")
B76: =IF(45<=$C$8,(PlanYear+44)&"/"&RIGHT(PlanYear+45,2),"") | C76: =IF(45<=$C$8,MID(IF('Child 1'!$Q$109=1,", "&IF(Inputs!$C$14<>"",Inputs!$C$14,"Child 1"),"")&IF('Child 2'!$Q$109=1,", "&IF(Inputs!$D$14<>"",Inputs!$D$14,"Child 2"),"")&IF('Child 3'!$Q$109=1,", "&IF(Inputs!$E$14<>"",Inputs!$E$14,"Child 3"),"")&IF('Child 4'!$Q$109=1,", "&IF(Inputs!$F$14<>"",Inputs!$F$14,"Child 4"),""),3,200),"") | D76: =IF(45<=$C$8,ROUND('Child 1'!$M$109+'Child 2'!$M$109+'Child 3'!$M$109+'Child 4'!$M$109,2),"") | E76: =IF(45<=$C$8,ROUND('Child 1'!$N$109+'Child 2'!$N$109+'Child 3'!$N$109+'Child 4'!$N$109,2),"") | F76: =IF(45<=$C$8,ROUND('Child 1'!$O$109+'Child 2'!$O$109+'Child 3'!$O$109+'Child 4'!$O$109,2),"") | G76: =IF(45<=$C$8,ROUND('Child 1'!$D$109+'Child 2'!$D$109+'Child 3'!$D$109+'Child 4'!$D$109,2),"") | H76: =IF(45<=$C$8,ROUND('Child 1'!$P$109+'Child 2'!$P$109+'Child 3'!$P$109+'Child 4'!$P$109,2),"")
B77: =IF(46<=$C$8,(PlanYear+45)&"/"&RIGHT(PlanYear+46,2),"") | C77: =IF(46<=$C$8,MID(IF('Child 1'!$Q$110=1,", "&IF(Inputs!$C$14<>"",Inputs!$C$14,"Child 1"),"")&IF('Child 2'!$Q$110=1,", "&IF(Inputs!$D$14<>"",Inputs!$D$14,"Child 2"),"")&IF('Child 3'!$Q$110=1,", "&IF(Inputs!$E$14<>"",Inputs!$E$14,"Child 3"),"")&IF('Child 4'!$Q$110=1,", "&IF(Inputs!$F$14<>"",Inputs!$F$14,"Child 4"),""),3,200),"") | D77: =IF(46<=$C$8,ROUND('Child 1'!$M$110+'Child 2'!$M$110+'Child 3'!$M$110+'Child 4'!$M$110,2),"") | E77: =IF(46<=$C$8,ROUND('Child 1'!$N$110+'Child 2'!$N$110+'Child 3'!$N$110+'Child 4'!$N$110,2),"") | F77: =IF(46<=$C$8,ROUND('Child 1'!$O$110+'Child 2'!$O$110+'Child 3'!$O$110+'Child 4'!$O$110,2),"") | G77: =IF(46<=$C$8,ROUND('Child 1'!$D$110+'Child 2'!$D$110+'Child 3'!$D$110+'Child 4'!$D$110,2),"") | H77: =IF(46<=$C$8,ROUND('Child 1'!$P$110+'Child 2'!$P$110+'Child 3'!$P$110+'Child 4'!$P$110,2),"")
B78: =IF(47<=$C$8,(PlanYear+46)&"/"&RIGHT(PlanYear+47,2),"") | C78: =IF(47<=$C$8,MID(IF('Child 1'!$Q$111=1,", "&IF(Inputs!$C$14<>"",Inputs!$C$14,"Child 1"),"")&IF('Child 2'!$Q$111=1,", "&IF(Inputs!$D$14<>"",Inputs!$D$14,"Child 2"),"")&IF('Child 3'!$Q$111=1,", "&IF(Inputs!$E$14<>"",Inputs!$E$14,"Child 3"),"")&IF('Child 4'!$Q$111=1,", "&IF(Inputs!$F$14<>"",Inputs!$F$14,"Child 4"),""),3,200),"") | D78: =IF(47<=$C$8,ROUND('Child 1'!$M$111+'Child 2'!$M$111+'Child 3'!$M$111+'Child 4'!$M$111,2),"") | E78: =IF(47<=$C$8,ROUND('Child 1'!$N$111+'Child 2'!$N$111+'Child 3'!$N$111+'Child 4'!$N$111,2),"") | F78: =IF(47<=$C$8,ROUND('Child 1'!$O$111+'Child 2'!$O$111+'Child 3'!$O$111+'Child 4'!$O$111,2),"") | G78: =IF(47<=$C$8,ROUND('Child 1'!$D$111+'Child 2'!$D$111+'Child 3'!$D$111+'Child 4'!$D$111,2),"") | H78: =IF(47<=$C$8,ROUND('Child 1'!$P$111+'Child 2'!$P$111+'Child 3'!$P$111+'Child 4'!$P$111,2),"")
B79: =IF(48<=$C$8,(PlanYear+47)&"/"&RIGHT(PlanYear+48,2),"") | C79: =IF(48<=$C$8,MID(IF('Child 1'!$Q$112=1,", "&IF(Inputs!$C$14<>"",Inputs!$C$14,"Child 1"),"")&IF('Child 2'!$Q$112=1,", "&IF(Inputs!$D$14<>"",Inputs!$D$14,"Child 2"),"")&IF('Child 3'!$Q$112=1,", "&IF(Inputs!$E$14<>"",Inputs!$E$14,"Child 3"),"")&IF('Child 4'!$Q$112=1,", "&IF(Inputs!$F$14<>"",Inputs!$F$14,"Child 4"),""),3,200),"") | D79: =IF(48<=$C$8,ROUND('Child 1'!$M$112+'Child 2'!$M$112+'Child 3'!$M$112+'Child 4'!$M$112,2),"") | E79: =IF(48<=$C$8,ROUND('Child 1'!$N$112+'Child 2'!$N$112+'Child 3'!$N$112+'Child 4'!$N$112,2),"") | F79: =IF(48<=$C$8,ROUND('Child 1'!$O$112+'Child 2'!$O$112+'Child 3'!$O$112+'Child 4'!$O$112,2),"") | G79: =IF(48<=$C$8,ROUND('Child 1'!$D$112+'Child 2'!$D$112+'Child 3'!$D$112+'Child 4'!$D$112,2),"") | H79: =IF(48<=$C$8,ROUND('Child 1'!$P$112+'Child 2'!$P$112+'Child 3'!$P$112+'Child 4'!$P$112,2),"")
B80: =IF(49<=$C$8,(PlanYear+48)&"/"&RIGHT(PlanYear+49,2),"") | C80: =IF(49<=$C$8,MID(IF('Child 1'!$Q$113=1,", "&IF(Inputs!$C$14<>"",Inputs!$C$14,"Child 1"),"")&IF('Child 2'!$Q$113=1,", "&IF(Inputs!$D$14<>"",Inputs!$D$14,"Child 2"),"")&IF('Child 3'!$Q$113=1,", "&IF(Inputs!$E$14<>"",Inputs!$E$14,"Child 3"),"")&IF('Child 4'!$Q$113=1,", "&IF(Inputs!$F$14<>"",Inputs!$F$14,"Child 4"),""),3,200),"") | D80: =IF(49<=$C$8,ROUND('Child 1'!$M$113+'Child 2'!$M$113+'Child 3'!$M$113+'Child 4'!$M$113,2),"") | E80: =IF(49<=$C$8,ROUND('Child 1'!$N$113+'Child 2'!$N$113+'Child 3'!$N$113+'Child 4'!$N$113,2),"") | F80: =IF(49<=$C$8,ROUND('Child 1'!$O$113+'Child 2'!$O$113+'Child 3'!$O$113+'Child 4'!$O$113,2),"") | G80: =IF(49<=$C$8,ROUND('Child 1'!$D$113+'Child 2'!$D$113+'Child 3'!$D$113+'Child 4'!$D$113,2),"") | H80: =IF(49<=$C$8,ROUND('Child 1'!$P$113+'Child 2'!$P$113+'Child 3'!$P$113+'Child 4'!$P$113,2),"")
B81: =IF(50<=$C$8,(PlanYear+49)&"/"&RIGHT(PlanYear+50,2),"") | C81: =IF(50<=$C$8,MID(IF('Child 1'!$Q$114=1,", "&IF(Inputs!$C$14<>"",Inputs!$C$14,"Child 1"),"")&IF('Child 2'!$Q$114=1,", "&IF(Inputs!$D$14<>"",Inputs!$D$14,"Child 2"),"")&IF('Child 3'!$Q$114=1,", "&IF(Inputs!$E$14<>"",Inputs!$E$14,"Child 3"),"")&IF('Child 4'!$Q$114=1,", "&IF(Inputs!$F$14<>"",Inputs!$F$14,"Child 4"),""),3,200),"") | D81: =IF(50<=$C$8,ROUND('Child 1'!$M$114+'Child 2'!$M$114+'Child 3'!$M$114+'Child 4'!$M$114,2),"") | E81: =IF(50<=$C$8,ROUND('Child 1'!$N$114+'Child 2'!$N$114+'Child 3'!$N$114+'Child 4'!$N$114,2),"") | F81: =IF(50<=$C$8,ROUND('Child 1'!$O$114+'Child 2'!$O$114+'Child 3'!$O$114+'Child 4'!$O$114,2),"") | G81: =IF(50<=$C$8,ROUND('Child 1'!$D$114+'Child 2'!$D$114+'Child 3'!$D$114+'Child 4'!$D$114,2),"") | H81: =IF(50<=$C$8,ROUND('Child 1'!$P$114+'Child 2'!$P$114+'Child 3'!$P$114+'Child 4'!$P$114,2),"")
B82: =IF(51<=$C$8,(PlanYear+50)&"/"&RIGHT(PlanYear+51,2),"") | C82: =IF(51<=$C$8,MID(IF('Child 1'!$Q$115=1,", "&IF(Inputs!$C$14<>"",Inputs!$C$14,"Child 1"),"")&IF('Child 2'!$Q$115=1,", "&IF(Inputs!$D$14<>"",Inputs!$D$14,"Child 2"),"")&IF('Child 3'!$Q$115=1,", "&IF(Inputs!$E$14<>"",Inputs!$E$14,"Child 3"),"")&IF('Child 4'!$Q$115=1,", "&IF(Inputs!$F$14<>"",Inputs!$F$14,"Child 4"),""),3,200),"") | D82: =IF(51<=$C$8,ROUND('Child 1'!$M$115+'Child 2'!$M$115+'Child 3'!$M$115+'Child 4'!$M$115,2),"") | E82: =IF(51<=$C$8,ROUND('Child 1'!$N$115+'Child 2'!$N$115+'Child 3'!$N$115+'Child 4'!$N$115,2),"") | F82: =IF(51<=$C$8,ROUND('Child 1'!$O$115+'Child 2'!$O$115+'Child 3'!$O$115+'Child 4'!$O$115,2),"") | G82: =IF(51<=$C$8,ROUND('Child 1'!$D$115+'Child 2'!$D$115+'Child 3'!$D$115+'Child 4'!$D$115,2),"") | H82: =IF(51<=$C$8,ROUND('Child 1'!$P$115+'Child 2'!$P$115+'Child 3'!$P$115+'Child 4'!$P$115,2),"")
B83: =IF(52<=$C$8,(PlanYear+51)&"/"&RIGHT(PlanYear+52,2),"") | C83: =IF(52<=$C$8,MID(IF('Child 1'!$Q$116=1,", "&IF(Inputs!$C$14<>"",Inputs!$C$14,"Child 1"),"")&IF('Child 2'!$Q$116=1,", "&IF(Inputs!$D$14<>"",Inputs!$D$14,"Child 2"),"")&IF('Child 3'!$Q$116=1,", "&IF(Inputs!$E$14<>"",Inputs!$E$14,"Child 3"),"")&IF('Child 4'!$Q$116=1,", "&IF(Inputs!$F$14<>"",Inputs!$F$14,"Child 4"),""),3,200),"") | D83: =IF(52<=$C$8,ROUND('Child 1'!$M$116+'Child 2'!$M$116+'Child 3'!$M$116+'Child 4'!$M$116,2),"") | E83: =IF(52<=$C$8,ROUND('Child 1'!$N$116+'Child 2'!$N$116+'Child 3'!$N$116+'Child 4'!$N$116,2),"") | F83: =IF(52<=$C$8,ROUND('Child 1'!$O$116+'Child 2'!$O$116+'Child 3'!$O$116+'Child 4'!$O$116,2),"") | G83: =IF(52<=$C$8,ROUND('Child 1'!$D$116+'Child 2'!$D$116+'Child 3'!$D$116+'Child 4'!$D$116,2),"") | H83: =IF(52<=$C$8,ROUND('Child 1'!$P$116+'Child 2'!$P$116+'Child 3'!$P$116+'Child 4'!$P$116,2),"")
B84: =IF(53<=$C$8,(PlanYear+52)&"/"&RIGHT(PlanYear+53,2),"") | C84: =IF(53<=$C$8,MID(IF('Child 1'!$Q$117=1,", "&IF(Inputs!$C$14<>"",Inputs!$C$14,"Child 1"),"")&IF('Child 2'!$Q$117=1,", "&IF(Inputs!$D$14<>"",Inputs!$D$14,"Child 2"),"")&IF('Child 3'!$Q$117=1,", "&IF(Inputs!$E$14<>"",Inputs!$E$14,"Child 3"),"")&IF('Child 4'!$Q$117=1,", "&IF(Inputs!$F$14<>"",Inputs!$F$14,"Child 4"),""),3,200),"") | D84: =IF(53<=$C$8,ROUND('Child 1'!$M$117+'Child 2'!$M$117+'Child 3'!$M$117+'Child 4'!$M$117,2),"") | E84: =IF(53<=$C$8,ROUND('Child 1'!$N$117+'Child 2'!$N$117+'Child 3'!$N$117+'Child 4'!$N$117,2),"") | F84: =IF(53<=$C$8,ROUND('Child 1'!$O$117+'Child 2'!$O$117+'Child 3'!$O$117+'Child 4'!$O$117,2),"") | G84: =IF(53<=$C$8,ROUND('Child 1'!$D$117+'Child 2'!$D$117+'Child 3'!$D$117+'Child 4'!$D$117,2),"") | H84: =IF(53<=$C$8,ROUND('Child 1'!$P$117+'Child 2'!$P$117+'Child 3'!$P$117+'Child 4'!$P$117,2),"")
B85: =IF(54<=$C$8,(PlanYear+53)&"/"&RIGHT(PlanYear+54,2),"") | C85: =IF(54<=$C$8,MID(IF('Child 1'!$Q$118=1,", "&IF(Inputs!$C$14<>"",Inputs!$C$14,"Child 1"),"")&IF('Child 2'!$Q$118=1,", "&IF(Inputs!$D$14<>"",Inputs!$D$14,"Child 2"),"")&IF('Child 3'!$Q$118=1,", "&IF(Inputs!$E$14<>"",Inputs!$E$14,"Child 3"),"")&IF('Child 4'!$Q$118=1,", "&IF(Inputs!$F$14<>"",Inputs!$F$14,"Child 4"),""),3,200),"") | D85: =IF(54<=$C$8,ROUND('Child 1'!$M$118+'Child 2'!$M$118+'Child 3'!$M$118+'Child 4'!$M$118,2),"") | E85: =IF(54<=$C$8,ROUND('Child 1'!$N$118+'Child 2'!$N$118+'Child 3'!$N$118+'Child 4'!$N$118,2),"") | F85: =IF(54<=$C$8,ROUND('Child 1'!$O$118+'Child 2'!$O$118+'Child 3'!$O$118+'Child 4'!$O$118,2),"") | G85: =IF(54<=$C$8,ROUND('Child 1'!$D$118+'Child 2'!$D$118+'Child 3'!$D$118+'Child 4'!$D$118,2),"") | H85: =IF(54<=$C$8,ROUND('Child 1'!$P$118+'Child 2'!$P$118+'Child 3'!$P$118+'Child 4'!$P$118,2),"")
B86: =IF(55<=$C$8,(PlanYear+54)&"/"&RIGHT(PlanYear+55,2),"") | C86: =IF(55<=$C$8,MID(IF('Child 1'!$Q$119=1,", "&IF(Inputs!$C$14<>"",Inputs!$C$14,"Child 1"),"")&IF('Child 2'!$Q$119=1,", "&IF(Inputs!$D$14<>"",Inputs!$D$14,"Child 2"),"")&IF('Child 3'!$Q$119=1,", "&IF(Inputs!$E$14<>"",Inputs!$E$14,"Child 3"),"")&IF('Child 4'!$Q$119=1,", "&IF(Inputs!$F$14<>"",Inputs!$F$14,"Child 4"),""),3,200),"") | D86: =IF(55<=$C$8,ROUND('Child 1'!$M$119+'Child 2'!$M$119+'Child 3'!$M$119+'Child 4'!$M$119,2),"") | E86: =IF(55<=$C$8,ROUND('Child 1'!$N$119+'Child 2'!$N$119+'Child 3'!$N$119+'Child 4'!$N$119,2),"") | F86: =IF(55<=$C$8,ROUND('Child 1'!$O$119+'Child 2'!$O$119+'Child 3'!$O$119+'Child 4'!$O$119,2),"") | G86: =IF(55<=$C$8,ROUND('Child 1'!$D$119+'Child 2'!$D$119+'Child 3'!$D$119+'Child 4'!$D$119,2),"") | H86: =IF(55<=$C$8,ROUND('Child 1'!$P$119+'Child 2'!$P$119+'Child 3'!$P$119+'Child 4'!$P$119,2),"")
B87: =IF(56<=$C$8,(PlanYear+55)&"/"&RIGHT(PlanYear+56,2),"") | C87: =IF(56<=$C$8,MID(IF('Child 1'!$Q$120=1,", "&IF(Inputs!$C$14<>"",Inputs!$C$14,"Child 1"),"")&IF('Child 2'!$Q$120=1,", "&IF(Inputs!$D$14<>"",Inputs!$D$14,"Child 2"),"")&IF('Child 3'!$Q$120=1,", "&IF(Inputs!$E$14<>"",Inputs!$E$14,"Child 3"),"")&IF('Child 4'!$Q$120=1,", "&IF(Inputs!$F$14<>"",Inputs!$F$14,"Child 4"),""),3,200),"") | D87: =IF(56<=$C$8,ROUND('Child 1'!$M$120+'Child 2'!$M$120+'Child 3'!$M$120+'Child 4'!$M$120,2),"") | E87: =IF(56<=$C$8,ROUND('Child 1'!$N$120+'Child 2'!$N$120+'Child 3'!$N$120+'Child 4'!$N$120,2),"") | F87: =IF(56<=$C$8,ROUND('Child 1'!$O$120+'Child 2'!$O$120+'Child 3'!$O$120+'Child 4'!$O$120,2),"") | G87: =IF(56<=$C$8,ROUND('Child 1'!$D$120+'Child 2'!$D$120+'Child 3'!$D$120+'Child 4'!$D$120,2),"") | H87: =IF(56<=$C$8,ROUND('Child 1'!$P$120+'Child 2'!$P$120+'Child 3'!$P$120+'Child 4'!$P$120,2),"")
B88: =IF(57<=$C$8,(PlanYear+56)&"/"&RIGHT(PlanYear+57,2),"") | C88: =IF(57<=$C$8,MID(IF('Child 1'!$Q$121=1,", "&IF(Inputs!$C$14<>"",Inputs!$C$14,"Child 1"),"")&IF('Child 2'!$Q$121=1,", "&IF(Inputs!$D$14<>"",Inputs!$D$14,"Child 2"),"")&IF('Child 3'!$Q$121=1,", "&IF(Inputs!$E$14<>"",Inputs!$E$14,"Child 3"),"")&IF('Child 4'!$Q$121=1,", "&IF(Inputs!$F$14<>"",Inputs!$F$14,"Child 4"),""),3,200),"") | D88: =IF(57<=$C$8,ROUND('Child 1'!$M$121+'Child 2'!$M$121+'Child 3'!$M$121+'Child 4'!$M$121,2),"") | E88: =IF(57<=$C$8,ROUND('Child 1'!$N$121+'Child 2'!$N$121+'Child 3'!$N$121+'Child 4'!$N$121,2),"") | F88: =IF(57<=$C$8,ROUND('Child 1'!$O$121+'Child 2'!$O$121+'Child 3'!$O$121+'Child 4'!$O$121,2),"") | G88: =IF(57<=$C$8,ROUND('Child 1'!$D$121+'Child 2'!$D$121+'Child 3'!$D$121+'Child 4'!$D$121,2),"") | H88: =IF(57<=$C$8,ROUND('Child 1'!$P$121+'Child 2'!$P$121+'Child 3'!$P$121+'Child 4'!$P$121,2),"")
B89: =IF(58<=$C$8,(PlanYear+57)&"/"&RIGHT(PlanYear+58,2),"") | C89: =IF(58<=$C$8,MID(IF('Child 1'!$Q$122=1,", "&IF(Inputs!$C$14<>"",Inputs!$C$14,"Child 1"),"")&IF('Child 2'!$Q$122=1,", "&IF(Inputs!$D$14<>"",Inputs!$D$14,"Child 2"),"")&IF('Child 3'!$Q$122=1,", "&IF(Inputs!$E$14<>"",Inputs!$E$14,"Child 3"),"")&IF('Child 4'!$Q$122=1,", "&IF(Inputs!$F$14<>"",Inputs!$F$14,"Child 4"),""),3,200),"") | D89: =IF(58<=$C$8,ROUND('Child 1'!$M$122+'Child 2'!$M$122+'Child 3'!$M$122+'Child 4'!$M$122,2),"") | E89: =IF(58<=$C$8,ROUND('Child 1'!$N$122+'Child 2'!$N$122+'Child 3'!$N$122+'Child 4'!$N$122,2),"") | F89: =IF(58<=$C$8,ROUND('Child 1'!$O$122+'Child 2'!$O$122+'Child 3'!$O$122+'Child 4'!$O$122,2),"") | G89: =IF(58<=$C$8,ROUND('Child 1'!$D$122+'Child 2'!$D$122+'Child 3'!$D$122+'Child 4'!$D$122,2),"") | H89: =IF(58<=$C$8,ROUND('Child 1'!$P$122+'Child 2'!$P$122+'Child 3'!$P$122+'Child 4'!$P$122,2),"")
B90: =IF(59<=$C$8,(PlanYear+58)&"/"&RIGHT(PlanYear+59,2),"") | C90: =IF(59<=$C$8,MID(IF('Child 1'!$Q$123=1,", "&IF(Inputs!$C$14<>"",Inputs!$C$14,"Child 1"),"")&IF('Child 2'!$Q$123=1,", "&IF(Inputs!$D$14<>"",Inputs!$D$14,"Child 2"),"")&IF('Child 3'!$Q$123=1,", "&IF(Inputs!$E$14<>"",Inputs!$E$14,"Child 3"),"")&IF('Child 4'!$Q$123=1,", "&IF(Inputs!$F$14<>"",Inputs!$F$14,"Child 4"),""),3,200),"") | D90: =IF(59<=$C$8,ROUND('Child 1'!$M$123+'Child 2'!$M$123+'Child 3'!$M$123+'Child 4'!$M$123,2),"") | E90: =IF(59<=$C$8,ROUND('Child 1'!$N$123+'Child 2'!$N$123+'Child 3'!$N$123+'Child 4'!$N$123,2),"") | F90: =IF(59<=$C$8,ROUND('Child 1'!$O$123+'Child 2'!$O$123+'Child 3'!$O$123+'Child 4'!$O$123,2),"") | G90: =IF(59<=$C$8,ROUND('Child 1'!$D$123+'Child 2'!$D$123+'Child 3'!$D$123+'Child 4'!$D$123,2),"") | H90: =IF(59<=$C$8,ROUND('Child 1'!$P$123+'Child 2'!$P$123+'Child 3'!$P$123+'Child 4'!$P$123,2),"")
B91: =IF(60<=$C$8,(PlanYear+59)&"/"&RIGHT(PlanYear+60,2),"") | C91: =IF(60<=$C$8,MID(IF('Child 1'!$Q$124=1,", "&IF(Inputs!$C$14<>"",Inputs!$C$14,"Child 1"),"")&IF('Child 2'!$Q$124=1,", "&IF(Inputs!$D$14<>"",Inputs!$D$14,"Child 2"),"")&IF('Child 3'!$Q$124=1,", "&IF(Inputs!$E$14<>"",Inputs!$E$14,"Child 3"),"")&IF('Child 4'!$Q$124=1,", "&IF(Inputs!$F$14<>"",Inputs!$F$14,"Child 4"),""),3,200),"") | D91: =IF(60<=$C$8,ROUND('Child 1'!$M$124+'Child 2'!$M$124+'Child 3'!$M$124+'Child 4'!$M$124,2),"") | E91: =IF(60<=$C$8,ROUND('Child 1'!$N$124+'Child 2'!$N$124+'Child 3'!$N$124+'Child 4'!$N$124,2),"") | F91: =IF(60<=$C$8,ROUND('Child 1'!$O$124+'Child 2'!$O$124+'Child 3'!$O$124+'Child 4'!$O$124,2),"") | G91: =IF(60<=$C$8,ROUND('Child 1'!$D$124+'Child 2'!$D$124+'Child 3'!$D$124+'Child 4'!$D$124,2),"") | H91: =IF(60<=$C$8,ROUND('Child 1'!$P$124+'Child 2'!$P$124+'Child 3'!$P$124+'Child 4'!$P$124,2),"")
B93: =IF($C$6>0.5,"The opening fund in "&PlanYear&"/"&RIGHT(PlanYear+1,2)&" is the amount needed now ("&RepCcy&" "&TEXT($C$6,"#,##0")&"): costs that start before any yearly saving can be made. The plan assumes no existing savings.","The plan assumes no existing savings, so the fund starts at zero.") -> The plan assumes no existing savings, so the fund starts at zero.
B94: Each year: opening fund - education expenses (paid at the start of the year) + investment growth + family savings (added at the end of the year) = closing fund, which becomes the next year's opening fund.
B95: ="Adds up: "&RepCcy&" "&TEXT($C$6,"#,##0")&" needed now + "&RepCcy&" "&TEXT(SUM(E32:E91),"#,##0")&" family savings + "&RepCcy&" "&TEXT(SUM(F32:F91),"#,##0")&" investment growth - "&RepCcy&" "&TEXT($C$4,"#,##0")&" education expenses = "&RepCcy&" "&TEXT(IF(ABS(IF($C$8>0,INDEX(H32:H91,$C$8),0))<0.5,0,IF($C$8>0,INDEX(H32:H91,$C$8),0)),"#,##0")&" left at the end." -> Adds up: USD 0 needed now + USD 0 family savings + USD 0 investment growth - USD 0 education expenses = USD 0 left at the end.

Sheet Compare Countries
B1: Compare countries
B2: ="The same child and qualification in each country, in "&RepCcy&". Choose the child on the Inputs sheet (Compare countries for child number)." -> The same child and qualification in each country, in USD. Choose the child on the Inputs sheet (Compare countries for child number).
B4: Child | C4: =CHOOSE(CmpChild,IF(Inputs!$C$14<>"",Inputs!$C$14,"Child 1"),IF(Inputs!$D$14<>"",Inputs!$D$14,"Child 2"),IF(Inputs!$E$14<>"",Inputs!$E$14,"Child 3"),IF(Inputs!$F$14<>"",Inputs!$F$14,"Child 4")) -> Child 1
B5: Qualification | C5: =CHOOSE(CmpChild,'Child 1'!$B$6,'Child 2'!$B$6,'Child 3'!$B$6,'Child 4'!$B$6)
B6: Current plan | C6: =IF(CHOOSE(CmpChild,'Child 1'!$B$22,'Child 2'!$B$22,'Child 3'!$B$22,'Child 4'!$B$22)=1,CHOOSE(CmpChild,'Child 1'!$B$5,'Child 2'!$B$5,'Child 3'!$B$5,'Child 4'!$B$5),"Enter this child's details on the Inputs sheet first.") -> Enter this child's details on the Inputs sheet first.
B8: Country | C8: ="Total ("&RepCcy&")" -> Total (USD) | D8: Note | E8: Current plan
B9: Pakistan | C9: =IF(CHOOSE(CmpChild,'Child 1'!$B$22,'Child 2'!$B$22,'Child 3'!$B$22,'Child 4'!$B$22)<>1,"",IF(CHOOSE(CmpChild,'Child 1'!$B$5,'Child 2'!$B$5,'Child 3'!$B$5,'Child 4'!$B$5)="Pakistan",CHOOSE(CmpChild,'Child 1'!$Z$56,'Child 2'!$Z$56,'Child 3'!$Z$56,'Child 4'!$Z$56),IF('Compare Calc'!$B$21=1,'Compare Calc'!$Z$55,"Not available"))) | D9: =IF(CHOOSE(CmpChild,'Child 1'!$B$22,'Child 2'!$B$22,'Child 3'!$B$22,'Child 4'!$B$22)<>1,"",IF(AND(NOT(CHOOSE(CmpChild,'Child 1'!$B$5,'Child 2'!$B$5,'Child 3'!$B$5,'Child 4'!$B$5)="Pakistan"),'Compare Calc'!$B$21<>1),'Compare Calc'!$B$22,IF(IF(CHOOSE(CmpChild,'Child 1'!$B$5,'Child 2'!$B$5,'Child 3'!$B$5,'Child 4'!$B$5)="Pakistan",CHOOSE(CmpChild,'Child 1'!$B$60,'Child 2'!$B$60,'Child 3'!$B$60,'Child 4'!$B$60),'Compare Calc'!$B$59)="estimated","Estimate — no published fee for this course",IF(IF(CHOOSE(CmpChild,'Child 1'!$B$5,'Child 2'!$B$5,'Child 3'!$B$5,'Child 4'!$B$5)="Pakistan",CHOOSE(CmpChild,'Child 1'!$B$61,'Child 2'!$B$61,'Child 3'!$B$61,'Child 4'!$B$61),'Compare Calc'!$B$60)=1,"Some costs have no figure yet","")))) | E9: =IF(AND(CHOOSE(CmpChild,'Child 1'!$B$22,'Child 2'!$B$22,'Child 3'!$B$22,'Child 4'!$B$22)=1,CHOOSE(CmpChild,'Child 1'!$B$5,'Child 2'!$B$5,'Child 3'!$B$5,'Child 4'!$B$5)="Pakistan"),"Current plan","")
B10: India | C10: =IF(CHOOSE(CmpChild,'Child 1'!$B$22,'Child 2'!$B$22,'Child 3'!$B$22,'Child 4'!$B$22)<>1,"",IF(CHOOSE(CmpChild,'Child 1'!$B$5,'Child 2'!$B$5,'Child 3'!$B$5,'Child 4'!$B$5)="India",CHOOSE(CmpChild,'Child 1'!$Z$56,'Child 2'!$Z$56,'Child 3'!$Z$56,'Child 4'!$Z$56),IF('Compare Calc'!$B$82=1,'Compare Calc'!$Z$116,"Not available"))) | D10: =IF(CHOOSE(CmpChild,'Child 1'!$B$22,'Child 2'!$B$22,'Child 3'!$B$22,'Child 4'!$B$22)<>1,"",IF(AND(NOT(CHOOSE(CmpChild,'Child 1'!$B$5,'Child 2'!$B$5,'Child 3'!$B$5,'Child 4'!$B$5)="India"),'Compare Calc'!$B$82<>1),'Compare Calc'!$B$83,IF(IF(CHOOSE(CmpChild,'Child 1'!$B$5,'Child 2'!$B$5,'Child 3'!$B$5,'Child 4'!$B$5)="India",CHOOSE(CmpChild,'Child 1'!$B$60,'Child 2'!$B$60,'Child 3'!$B$60,'Child 4'!$B$60),'Compare Calc'!$B$120)="estimated","Estimate — no published fee for this course",IF(IF(CHOOSE(CmpChild,'Child 1'!$B$5,'Child 2'!$B$5,'Child 3'!$B$5,'Child 4'!$B$5)="India",CHOOSE(CmpChild,'Child 1'!$B$61,'Child 2'!$B$61,'Child 3'!$B$61,'Child 4'!$B$61),'Compare Calc'!$B$121)=1,"Some costs have no figure yet","")))) | E10: =IF(AND(CHOOSE(CmpChild,'Child 1'!$B$22,'Child 2'!$B$22,'Child 3'!$B$22,'Child 4'!$B$22)=1,CHOOSE(CmpChild,'Child 1'!$B$5,'Child 2'!$B$5,'Child 3'!$B$5,'Child 4'!$B$5)="India"),"Current plan","")
B11: USA | C11: =IF(CHOOSE(CmpChild,'Child 1'!$B$22,'Child 2'!$B$22,'Child 3'!$B$22,'Child 4'!$B$22)<>1,"",IF(CHOOSE(CmpChild,'Child 1'!$B$5,'Child 2'!$B$5,'Child 3'!$B$5,'Child 4'!$B$5)="USA",CHOOSE(CmpChild,'Child 1'!$Z$56,'Child 2'!$Z$56,'Child 3'!$Z$56,'Child 4'!$Z$56),IF('Compare Calc'!$B$143=1,'Compare Calc'!$Z$177,"Not available"))) | D11: =IF(CHOOSE(CmpChild,'Child 1'!$B$22,'Child 2'!$B$22,'Child 3'!$B$22,'Child 4'!$B$22)<>1,"",IF(AND(NOT(CHOOSE(CmpChild,'Child 1'!$B$5,'Child 2'!$B$5,'Child 3'!$B$5,'Child 4'!$B$5)="USA"),'Compare Calc'!$B$143<>1),'Compare Calc'!$B$144,IF(IF(CHOOSE(CmpChild,'Child 1'!$B$5,'Child 2'!$B$5,'Child 3'!$B$5,'Child 4'!$B$5)="USA",CHOOSE(CmpChild,'Child 1'!$B$60,'Child 2'!$B$60,'Child 3'!$B$60,'Child 4'!$B$60),'Compare Calc'!$B$181)="estimated","Estimate — no published fee for this course",IF(IF(CHOOSE(CmpChild,'Child 1'!$B$5,'Child 2'!$B$5,'Child 3'!$B$5,'Child 4'!$B$5)="USA",CHOOSE(CmpChild,'Child 1'!$B$61,'Child 2'!$B$61,'Child 3'!$B$61,'Child 4'!$B$61),'Compare Calc'!$B$182)=1,"Some costs have no figure yet","")))) | E11: =IF(AND(CHOOSE(CmpChild,'Child 1'!$B$22,'Child 2'!$B$22,'Child 3'!$B$22,'Child 4'!$B$22)=1,CHOOSE(CmpChild,'Child 1'!$B$5,'Child 2'!$B$5,'Child 3'!$B$5,'Child 4'!$B$5)="USA"),"Current plan","")
B12: UK | C12: =IF(CHOOSE(CmpChild,'Child 1'!$B$22,'Child 2'!$B$22,'Child 3'!$B$22,'Child 4'!$B$22)<>1,"",IF(CHOOSE(CmpChild,'Child 1'!$B$5,'Child 2'!$B$5,'Child 3'!$B$5,'Child 4'!$B$5)="UK",CHOOSE(CmpChild,'Child 1'!$Z$56,'Child 2'!$Z$56,'Child 3'!$Z$56,'Child 4'!$Z$56),IF('Compare Calc'!$B$204=1,'Compare Calc'!$Z$238,"Not available"))) | D12: =IF(CHOOSE(CmpChild,'Child 1'!$B$22,'Child 2'!$B$22,'Child 3'!$B$22,'Child 4'!$B$22)<>1,"",IF(AND(NOT(CHOOSE(CmpChild,'Child 1'!$B$5,'Child 2'!$B$5,'Child 3'!$B$5,'Child 4'!$B$5)="UK"),'Compare Calc'!$B$204<>1),'Compare Calc'!$B$205,IF(IF(CHOOSE(CmpChild,'Child 1'!$B$5,'Child 2'!$B$5,'Child 3'!$B$5,'Child 4'!$B$5)="UK",CHOOSE(CmpChild,'Child 1'!$B$60,'Child 2'!$B$60,'Child 3'!$B$60,'Child 4'!$B$60),'Compare Calc'!$B$242)="estimated","Estimate — no published fee for this course",IF(IF(CHOOSE(CmpChild,'Child 1'!$B$5,'Child 2'!$B$5,'Child 3'!$B$5,'Child 4'!$B$5)="UK",CHOOSE(CmpChild,'Child 1'!$B$61,'Child 2'!$B$61,'Child 3'!$B$61,'Child 4'!$B$61),'Compare Calc'!$B$243)=1,"Some costs have no figure yet","")))) | E12: =IF(AND(CHOOSE(CmpChild,'Child 1'!$B$22,'Child 2'!$B$22,'Child 3'!$B$22,'Child 4'!$B$22)=1,CHOOSE(CmpChild,'Child 1'!$B$5,'Child 2'!$B$5,'Child 3'!$B$5,'Child 4'!$B$5)="UK"),"Current plan","")
B13: Australia | C13: =IF(CHOOSE(CmpChild,'Child 1'!$B$22,'Child 2'!$B$22,'Child 3'!$B$22,'Child 4'!$B$22)<>1,"",IF(CHOOSE(CmpChild,'Child 1'!$B$5,'Child 2'!$B$5,'Child 3'!$B$5,'Child 4'!$B$5)="Australia",CHOOSE(CmpChild,'Child 1'!$Z$56,'Child 2'!$Z$56,'Child 3'!$Z$56,'Child 4'!$Z$56),IF('Compare Calc'!$B$265=1,'Compare Calc'!$Z$299,"Not available"))) | D13: =IF(CHOOSE(CmpChild,'Child 1'!$B$22,'Child 2'!$B$22,'Child 3'!$B$22,'Child 4'!$B$22)<>1,"",IF(AND(NOT(CHOOSE(CmpChild,'Child 1'!$B$5,'Child 2'!$B$5,'Child 3'!$B$5,'Child 4'!$B$5)="Australia"),'Compare Calc'!$B$265<>1),'Compare Calc'!$B$266,IF(IF(CHOOSE(CmpChild,'Child 1'!$B$5,'Child 2'!$B$5,'Child 3'!$B$5,'Child 4'!$B$5)="Australia",CHOOSE(CmpChild,'Child 1'!$B$60,'Child 2'!$B$60,'Child 3'!$B$60,'Child 4'!$B$60),'Compare Calc'!$B$303)="estimated","Estimate — no published fee for this course",IF(IF(CHOOSE(CmpChild,'Child 1'!$B$5,'Child 2'!$B$5,'Child 3'!$B$5,'Child 4'!$B$5)="Australia",CHOOSE(CmpChild,'Child 1'!$B$61,'Child 2'!$B$61,'Child 3'!$B$61,'Child 4'!$B$61),'Compare Calc'!$B$304)=1,"Some costs have no figure yet","")))) | E13: =IF(AND(CHOOSE(CmpChild,'Child 1'!$B$22,'Child 2'!$B$22,'Child 3'!$B$22,'Child 4'!$B$22)=1,CHOOSE(CmpChild,'Child 1'!$B$5,'Child 2'!$B$5,'Child 3'!$B$5,'Child 4'!$B$5)="Australia"),"Current plan","")
B14: Germany | C14: =IF(CHOOSE(CmpChild,'Child 1'!$B$22,'Child 2'!$B$22,'Child 3'!$B$22,'Child 4'!$B$22)<>1,"",IF(CHOOSE(CmpChild,'Child 1'!$B$5,'Child 2'!$B$5,'Child 3'!$B$5,'Child 4'!$B$5)="Germany",CHOOSE(CmpChild,'Child 1'!$Z$56,'Child 2'!$Z$56,'Child 3'!$Z$56,'Child 4'!$Z$56),IF('Compare Calc'!$B$326=1,'Compare Calc'!$Z$360,"Not available"))) | D14: =IF(CHOOSE(CmpChild,'Child 1'!$B$22,'Child 2'!$B$22,'Child 3'!$B$22,'Child 4'!$B$22)<>1,"",IF(AND(NOT(CHOOSE(CmpChild,'Child 1'!$B$5,'Child 2'!$B$5,'Child 3'!$B$5,'Child 4'!$B$5)="Germany"),'Compare Calc'!$B$326<>1),'Compare Calc'!$B$327,IF(IF(CHOOSE(CmpChild,'Child 1'!$B$5,'Child 2'!$B$5,'Child 3'!$B$5,'Child 4'!$B$5)="Germany",CHOOSE(CmpChild,'Child 1'!$B$60,'Child 2'!$B$60,'Child 3'!$B$60,'Child 4'!$B$60),'Compare Calc'!$B$364)="estimated","Estimate — no published fee for this course",IF(IF(CHOOSE(CmpChild,'Child 1'!$B$5,'Child 2'!$B$5,'Child 3'!$B$5,'Child 4'!$B$5)="Germany",CHOOSE(CmpChild,'Child 1'!$B$61,'Child 2'!$B$61,'Child 3'!$B$61,'Child 4'!$B$61),'Compare Calc'!$B$365)=1,"Some costs have no figure yet","")))) | E14: =IF(AND(CHOOSE(CmpChild,'Child 1'!$B$22,'Child 2'!$B$22,'Child 3'!$B$22,'Child 4'!$B$22)=1,CHOOSE(CmpChild,'Child 1'!$B$5,'Child 2'!$B$5,'Child 3'!$B$5,'Child 4'!$B$5)="Germany"),"Current plan","")
B15: Singapore | C15: =IF(CHOOSE(CmpChild,'Child 1'!$B$22,'Child 2'!$B$22,'Child 3'!$B$22,'Child 4'!$B$22)<>1,"",IF(CHOOSE(CmpChild,'Child 1'!$B$5,'Child 2'!$B$5,'Child 3'!$B$5,'Child 4'!$B$5)="Singapore",CHOOSE(CmpChild,'Child 1'!$Z$56,'Child 2'!$Z$56,'Child 3'!$Z$56,'Child 4'!$Z$56),IF('Compare Calc'!$B$387=1,'Compare Calc'!$Z$421,"Not available"))) | D15: =IF(CHOOSE(CmpChild,'Child 1'!$B$22,'Child 2'!$B$22,'Child 3'!$B$22,'Child 4'!$B$22)<>1,"",IF(AND(NOT(CHOOSE(CmpChild,'Child 1'!$B$5,'Child 2'!$B$5,'Child 3'!$B$5,'Child 4'!$B$5)="Singapore"),'Compare Calc'!$B$387<>1),'Compare Calc'!$B$388,IF(IF(CHOOSE(CmpChild,'Child 1'!$B$5,'Child 2'!$B$5,'Child 3'!$B$5,'Child 4'!$B$5)="Singapore",CHOOSE(CmpChild,'Child 1'!$B$60,'Child 2'!$B$60,'Child 3'!$B$60,'Child 4'!$B$60),'Compare Calc'!$B$425)="estimated","Estimate — no published fee for this course",IF(IF(CHOOSE(CmpChild,'Child 1'!$B$5,'Child 2'!$B$5,'Child 3'!$B$5,'Child 4'!$B$5)="Singapore",CHOOSE(CmpChild,'Child 1'!$B$61,'Child 2'!$B$61,'Child 3'!$B$61,'Child 4'!$B$61),'Compare Calc'!$B$426)=1,"Some costs have no figure yet","")))) | E15: =IF(AND(CHOOSE(CmpChild,'Child 1'!$B$22,'Child 2'!$B$22,'Child 3'!$B$22,'Child 4'!$B$22)=1,CHOOSE(CmpChild,'Child 1'!$B$5,'Child 2'!$B$5,'Child 3'!$B$5,'Child 4'!$B$5)="Singapore"),"Current plan","")
B16: Malaysia | C16: =IF(CHOOSE(CmpChild,'Child 1'!$B$22,'Child 2'!$B$22,'Child 3'!$B$22,'Child 4'!$B$22)<>1,"",IF(CHOOSE(CmpChild,'Child 1'!$B$5,'Child 2'!$B$5,'Child 3'!$B$5,'Child 4'!$B$5)="Malaysia",CHOOSE(CmpChild,'Child 1'!$Z$56,'Child 2'!$Z$56,'Child 3'!$Z$56,'Child 4'!$Z$56),IF('Compare Calc'!$B$448=1,'Compare Calc'!$Z$482,"Not available"))) | D16: =IF(CHOOSE(CmpChild,'Child 1'!$B$22,'Child 2'!$B$22,'Child 3'!$B$22,'Child 4'!$B$22)<>1,"",IF(AND(NOT(CHOOSE(CmpChild,'Child 1'!$B$5,'Child 2'!$B$5,'Child 3'!$B$5,'Child 4'!$B$5)="Malaysia"),'Compare Calc'!$B$448<>1),'Compare Calc'!$B$449,IF(IF(CHOOSE(CmpChild,'Child 1'!$B$5,'Child 2'!$B$5,'Child 3'!$B$5,'Child 4'!$B$5)="Malaysia",CHOOSE(CmpChild,'Child 1'!$B$60,'Child 2'!$B$60,'Child 3'!$B$60,'Child 4'!$B$60),'Compare Calc'!$B$486)="estimated","Estimate — no published fee for this course",IF(IF(CHOOSE(CmpChild,'Child 1'!$B$5,'Child 2'!$B$5,'Child 3'!$B$5,'Child 4'!$B$5)="Malaysia",CHOOSE(CmpChild,'Child 1'!$B$61,'Child 2'!$B$61,'Child 3'!$B$61,'Child 4'!$B$61),'Compare Calc'!$B$487)=1,"Some costs have no figure yet","")))) | E16: =IF(AND(CHOOSE(CmpChild,'Child 1'!$B$22,'Child 2'!$B$22,'Child 3'!$B$22,'Child 4'!$B$22)=1,CHOOSE(CmpChild,'Child 1'!$B$5,'Child 2'!$B$5,'Child 3'!$B$5,'Child 4'!$B$5)="Malaysia"),"Current plan","")
B17: Ireland | C17: =IF(CHOOSE(CmpChild,'Child 1'!$B$22,'Child 2'!$B$22,'Child 3'!$B$22,'Child 4'!$B$22)<>1,"",IF(CHOOSE(CmpChild,'Child 1'!$B$5,'Child 2'!$B$5,'Child 3'!$B$5,'Child 4'!$B$5)="Ireland",CHOOSE(CmpChild,'Child 1'!$Z$56,'Child 2'!$Z$56,'Child 3'!$Z$56,'Child 4'!$Z$56),IF('Compare Calc'!$B$509=1,'Compare Calc'!$Z$543,"Not available"))) | D17: =IF(CHOOSE(CmpChild,'Child 1'!$B$22,'Child 2'!$B$22,'Child 3'!$B$22,'Child 4'!$B$22)<>1,"",IF(AND(NOT(CHOOSE(CmpChild,'Child 1'!$B$5,'Child 2'!$B$5,'Child 3'!$B$5,'Child 4'!$B$5)="Ireland"),'Compare Calc'!$B$509<>1),'Compare Calc'!$B$510,IF(IF(CHOOSE(CmpChild,'Child 1'!$B$5,'Child 2'!$B$5,'Child 3'!$B$5,'Child 4'!$B$5)="Ireland",CHOOSE(CmpChild,'Child 1'!$B$60,'Child 2'!$B$60,'Child 3'!$B$60,'Child 4'!$B$60),'Compare Calc'!$B$547)="estimated","Estimate — no published fee for this course",IF(IF(CHOOSE(CmpChild,'Child 1'!$B$5,'Child 2'!$B$5,'Child 3'!$B$5,'Child 4'!$B$5)="Ireland",CHOOSE(CmpChild,'Child 1'!$B$61,'Child 2'!$B$61,'Child 3'!$B$61,'Child 4'!$B$61),'Compare Calc'!$B$548)=1,"Some costs have no figure yet","")))) | E17: =IF(AND(CHOOSE(CmpChild,'Child 1'!$B$22,'Child 2'!$B$22,'Child 3'!$B$22,'Child 4'!$B$22)=1,CHOOSE(CmpChild,'Child 1'!$B$5,'Child 2'!$B$5,'Child 3'!$B$5,'Child 4'!$B$5)="Ireland"),"Current plan","")
B18: Qatar | C18: =IF(CHOOSE(CmpChild,'Child 1'!$B$22,'Child 2'!$B$22,'Child 3'!$B$22,'Child 4'!$B$22)<>1,"",IF(CHOOSE(CmpChild,'Child 1'!$B$5,'Child 2'!$B$5,'Child 3'!$B$5,'Child 4'!$B$5)="Qatar",CHOOSE(CmpChild,'Child 1'!$Z$56,'Child 2'!$Z$56,'Child 3'!$Z$56,'Child 4'!$Z$56),IF('Compare Calc'!$B$570=1,'Compare Calc'!$Z$604,"Not available"))) | D18: =IF(CHOOSE(CmpChild,'Child 1'!$B$22,'Child 2'!$B$22,'Child 3'!$B$22,'Child 4'!$B$22)<>1,"",IF(AND(NOT(CHOOSE(CmpChild,'Child 1'!$B$5,'Child 2'!$B$5,'Child 3'!$B$5,'Child 4'!$B$5)="Qatar"),'Compare Calc'!$B$570<>1),'Compare Calc'!$B$571,IF(IF(CHOOSE(CmpChild,'Child 1'!$B$5,'Child 2'!$B$5,'Child 3'!$B$5,'Child 4'!$B$5)="Qatar",CHOOSE(CmpChild,'Child 1'!$B$60,'Child 2'!$B$60,'Child 3'!$B$60,'Child 4'!$B$60),'Compare Calc'!$B$608)="estimated","Estimate — no published fee for this course",IF(IF(CHOOSE(CmpChild,'Child 1'!$B$5,'Child 2'!$B$5,'Child 3'!$B$5,'Child 4'!$B$5)="Qatar",CHOOSE(CmpChild,'Child 1'!$B$61,'Child 2'!$B$61,'Child 3'!$B$61,'Child 4'!$B$61),'Compare Calc'!$B$609)=1,"Some costs have no figure yet","")))) | E18: =IF(AND(CHOOSE(CmpChild,'Child 1'!$B$22,'Child 2'!$B$22,'Child 3'!$B$22,'Child 4'!$B$22)=1,CHOOSE(CmpChild,'Child 1'!$B$5,'Child 2'!$B$5,'Child 3'!$B$5,'Child 4'!$B$5)="Qatar"),"Current plan","")
B19: United Arab Emirates | C19: =IF(CHOOSE(CmpChild,'Child 1'!$B$22,'Child 2'!$B$22,'Child 3'!$B$22,'Child 4'!$B$22)<>1,"",IF(CHOOSE(CmpChild,'Child 1'!$B$5,'Child 2'!$B$5,'Child 3'!$B$5,'Child 4'!$B$5)="United Arab Emirates",CHOOSE(CmpChild,'Child 1'!$Z$56,'Child 2'!$Z$56,'Child 3'!$Z$56,'Child 4'!$Z$56),IF('Compare Calc'!$B$631=1,'Compare Calc'!$Z$665,"Not available"))) | D19: =IF(CHOOSE(CmpChild,'Child 1'!$B$22,'Child 2'!$B$22,'Child 3'!$B$22,'Child 4'!$B$22)<>1,"",IF(AND(NOT(CHOOSE(CmpChild,'Child 1'!$B$5,'Child 2'!$B$5,'Child 3'!$B$5,'Child 4'!$B$5)="United Arab Emirates"),'Compare Calc'!$B$631<>1),'Compare Calc'!$B$632,IF(IF(CHOOSE(CmpChild,'Child 1'!$B$5,'Child 2'!$B$5,'Child 3'!$B$5,'Child 4'!$B$5)="United Arab Emirates",CHOOSE(CmpChild,'Child 1'!$B$60,'Child 2'!$B$60,'Child 3'!$B$60,'Child 4'!$B$60),'Compare Calc'!$B$669)="estimated","Estimate — no published fee for this course",IF(IF(CHOOSE(CmpChild,'Child 1'!$B$5,'Child 2'!$B$5,'Child 3'!$B$5,'Child 4'!$B$5)="United Arab Emirates",CHOOSE(CmpChild,'Child 1'!$B$61,'Child 2'!$B$61,'Child 3'!$B$61,'Child 4'!$B$61),'Compare Calc'!$B$670)=1,"Some costs have no figure yet","")))) | E19: =IF(AND(CHOOSE(CmpChild,'Child 1'!$B$22,'Child 2'!$B$22,'Child 3'!$B$22,'Child 4'!$B$22)=1,CHOOSE(CmpChild,'Child 1'!$B$5,'Child 2'!$B$5,'Child 3'!$B$5,'Child 4'!$B$5)="United Arab Emirates"),"Current plan","")
B21: Each total covers the full course in that country (its usual length), at future prices, after your scholarship / part-time-work percentage. The current plan's row is your plan exactly. For other countries your own fee and living-cost increases are used, but your own cost figures are not carried over, because they are in another country's currency.

Sheet Child 1
A1: Child 1 - cost and savings calculation
A2: All formulas. Change inputs on the Inputs sheet. Amounts in the cost lines table are in the education country's currency; everything else is in the results currency.
A4: Included (1 = yes) | B4: =IF(1<=NumChildren,1,0) -> 1
A5: Education country | B5: =IF(Inputs!$C$17="","",Inputs!$C$17)
A6: Qualification | B6: =IF(Inputs!$C$18="","",Inputs!$C$18)
A7: Current age | B7: =IF(Inputs!$C$15="","",Inputs!$C$15)
A8: College-entry age | B8: =IF(Inputs!$C$19="","",Inputs!$C$19) -> 18
A9: Fee status | B9: =IF($B$5="","",IF(COUNTIF(DomKey,$B$5&"|"&Nationality)>0,"domestic","international"))
A10: Lookup key | B10: =$B$5&"|"&$B$6&"|"&$B$9 -> ||
A11: Cost database row | B11: =IFERROR(MATCH($B$10,DB_Key,0),0) -> 0
A12: Education currency | B12: =IFERROR(INDEX(Ctry_Ccy,MATCH($B$5,Ctry_Name,0)),"USD") -> USD
A13: Course length (years) | B13: =IF($B$11>0,INDEX(DB_Dur,$B$11),0) -> 0
A14: Offered in this country (1/0) | B14: =IF($B$11>0,INDEX(DB_Avail,$B$11),0) -> 0
A15: Pre-stage years | B15: =IF($B$11>0,INDEX(DB_PreYears,$B$11),0) -> 0
A16: Fee increase used | B16: =IF(ISNUMBER(Inputs!$C$20),Inputs!$C$20,IF($B$11>0,INDEX(DB_TInf,$B$11),0)) -> 0
A17: Living-cost increase used | B17: =IF(ISNUMBER(Inputs!$C$21),Inputs!$C$21,IFERROR(INDEX(Ctry_LInf,MATCH($B$5,Ctry_Name,0)),0)) -> 0
A18: Years until college | B18: =IF($B$22=1,MAX(0,$B$8-$B$7),0) -> 0
A19: Study years | B19: =ROUNDUP($B$13,0) -> 0
A20: Plan years | B20: =IF($B$22=1,$B$18+$B$19,0) -> 0
A21: Saving years | B21: =MAX(0,$B$20-1) -> 0
A22: Calculated (1 = yes) | B22: =IF(IFERROR(AND($B$4=1,$B$5<>"",$B$6<>"",$B$14=1,IFERROR(AND(ISNUMBER($B$7),$B$7>=0,$B$7<=18,INT($B$7)=$B$7),FALSE),IFERROR(AND(ISNUMBER($B$8),$B$8>=14,$B$8<=45,INT($B$8)=$B$8),FALSE)),FALSE),1,0) -> 0
A23: Message | B23: =IF($B$4<>1,"",IF(AND($B$7="",$B$5="",$B$6=""),"Enter this child's details on the Inputs sheet.",IF(NOT(IFERROR(AND(ISNUMBER($B$7),$B$7>=0,$B$7<=18,INT($B$7)=$B$7),FALSE)),"Choose the child's current age (0 to 18).",IF(NOT(IFERROR(AND(ISNUMBER($B$8),$B$8>=14,$B$8<=45,INT($B$8)=$B$8),FALSE)),"College-entry age must be a whole number from 14 to 45.",IF($B$5="","Choose the education country.",IF($B$6="","Choose the qualification.",IF($B$14<>1,"This qualification is not offered (or has no typical duration) in the selected country.",""))))))) -> Enter this child's details on the Inputs sheet.
A24: Exchange rate (education to results currency) | B24: =INDEX(FxUsed,MATCH(RepCcy,FxCodes,0))/INDEX(FxUsed,MATCH($B$12,FxCodes,0)) -> 1
A25: Published fee records used | B25: =IF($B$11=0,0,COUNTIF(RecKey,$B$10)) -> 0
A26: Fee records currency | B26: =IF($B$25>0,INDEX(DB_RecCcy,$B$11),IF($B$11>0,INDEX(DB_EstCcy,$B$11),$B$12)) -> USD
A27: Living costs row | B27: =IFERROR(MATCH($B$5&"|"&$B$9,LivKey,0),0) -> 0
A28: Visa row | B28: =IFERROR(MATCH($B$5&"|"&Nationality,VisaKey,0),0) -> 0
A29: Travel row | B29: =IFERROR(MATCH($B$5&"|"&Residence,TravKey,0),0) -> 0
A31: Cost line | B31: Researched (education currency) | C31: Your figure | D31: Amount used | E31: Price year | F31: Status code | G31: Status | H31: Increase | I31: Timing | J31: Scholarship applies
A32: Tuition | B32: =IF($B$11=0,0,(IF($B$25>0,SUMPRODUCT((RecKey=$B$10)*RecTuition*(1+$B$16)^(PlanYear-RecYear))/$B$25,INDEX(DB_EstTuition,$B$11)))/INDEX(FxUsed,MATCH($B$26,FxCodes,0))*INDEX(FxUsed,MATCH($B$12,FxCodes,0))) -> 0 | C32: =IF(ISNUMBER(Inputs!$C$23),Inputs!$C$23,"") | D32: =IF(ISNUMBER(C32),IF(C32>=0,C32,B32),B32) -> 0 | E32: =IF(ISNUMBER(C32),PlanYear,IF($B$25>0,PlanYear,IF($B$11>0,INDEX(DB_EstBase,$B$11),PlanYear))) -> 2026 | F32: =IF(ISNUMBER(C32),"override",IF($B$11=0,"missing",IF($B$25>0,"verified",INDEX(DB_EstStatus,$B$11)))) -> missing | G32: =IF(F32="verified","Published figure",IF(F32="estimated","Estimated — please review",IF(F32="notNeeded","Not needed",IF(F32="override","Your figure",IF(F32="missing","No figure yet — enter your own",""))))) -> No figure yet — enter your own | H32: tuition | I32: annual | J32: Yes
A33: Accommodation | B33: =IF($B$27=0,0,(INDEX(Liv_accommodation_Amt,$B$27))/INDEX(FxUsed,MATCH(INDEX(Liv_accommodation_Ccy,$B$27),FxCodes,0))*INDEX(FxUsed,MATCH($B$12,FxCodes,0))) -> 0 | C33: =IF(ISNUMBER(Inputs!$C$24),Inputs!$C$24,"") | D33: =IF(ISNUMBER(C33),IF(C33>=0,C33,B33),B33) -> 0 | E33: =IF(ISNUMBER(C33),PlanYear,IF($B$27=0,PlanYear,INDEX(Liv_accommodation_Base,$B$27))) -> 2026 | F33: =IF(ISNUMBER(C33),"override",IF($B$27=0,"missing",INDEX(Liv_accommodation_Status,$B$27))) -> missing | G33: =IF(F33="verified","Published figure",IF(F33="estimated","Estimated — please review",IF(F33="notNeeded","Not needed",IF(F33="override","Your figure",IF(F33="missing","No figure yet — enter your own",""))))) -> No figure yet — enter your own | H33: living | I33: annual | J33: Yes
A34: Food | B34: =IF($B$27=0,0,(INDEX(Liv_food_Amt,$B$27))/INDEX(FxUsed,MATCH(INDEX(Liv_food_Ccy,$B$27),FxCodes,0))*INDEX(FxUsed,MATCH($B$12,FxCodes,0))) -> 0 | C34: =IF(ISNUMBER(Inputs!$C$25),Inputs!$C$25,"") | D34: =IF(ISNUMBER(C34),IF(C34>=0,C34,B34),B34) -> 0 | E34: =IF(ISNUMBER(C34),PlanYear,IF($B$27=0,PlanYear,INDEX(Liv_food_Base,$B$27))) -> 2026 | F34: =IF(ISNUMBER(C34),"override",IF($B$27=0,"missing",INDEX(Liv_food_Status,$B$27))) -> missing | G34: =IF(F34="verified","Published figure",IF(F34="estimated","Estimated — please review",IF(F34="notNeeded","Not needed",IF(F34="override","Your figure",IF(F34="missing","No figure yet — enter your own",""))))) -> No figure yet — enter your own | H34: living | I34: annual | J34: Yes
A35: Local transport | B35: =IF($B$27=0,0,(INDEX(Liv_transport_Amt,$B$27))/INDEX(FxUsed,MATCH(INDEX(Liv_transport_Ccy,$B$27),FxCodes,0))*INDEX(FxUsed,MATCH($B$12,FxCodes,0))) -> 0 | C35: =IF(ISNUMBER(Inputs!$C$26),Inputs!$C$26,"") | D35: =IF(ISNUMBER(C35),IF(C35>=0,C35,B35),B35) -> 0 | E35: =IF(ISNUMBER(C35),PlanYear,IF($B$27=0,PlanYear,INDEX(Liv_transport_Base,$B$27))) -> 2026 | F35: =IF(ISNUMBER(C35),"override",IF($B$27=0,"missing",INDEX(Liv_transport_Status,$B$27))) -> missing | G35: =IF(F35="verified","Published figure",IF(F35="estimated","Estimated — please review",IF(F35="notNeeded","Not needed",IF(F35="override","Your figure",IF(F35="missing","No figure yet — enter your own",""))))) -> No figure yet — enter your own | H35: living | I35: annual | J35: Yes
A36: Health insurance | B36: =IF($B$27=0,0,(INDEX(Liv_healthInsurance_Amt,$B$27))/INDEX(FxUsed,MATCH(INDEX(Liv_healthInsurance_Ccy,$B$27),FxCodes,0))*INDEX(FxUsed,MATCH($B$12,FxCodes,0))) -> 0 | C36: =IF(ISNUMBER(Inputs!$C$27),Inputs!$C$27,"") | D36: =IF(ISNUMBER(C36),IF(C36>=0,C36,B36),B36) -> 0 | E36: =IF(ISNUMBER(C36),PlanYear,IF($B$27=0,PlanYear,INDEX(Liv_healthInsurance_Base,$B$27))) -> 2026 | F36: =IF(ISNUMBER(C36),"override",IF($B$27=0,"missing",INDEX(Liv_healthInsurance_Status,$B$27))) -> missing | G36: =IF(F36="verified","Published figure",IF(F36="estimated","Estimated — please review",IF(F36="notNeeded","Not needed",IF(F36="override","Your figure",IF(F36="missing","No figure yet — enter your own",""))))) -> No figure yet — enter your own | H36: living | I36: annual | J36: Yes
A37: Books and supplies | B37: =IF($B$27=0,0,(INDEX(Liv_books_Amt,$B$27))/INDEX(FxUsed,MATCH(INDEX(Liv_books_Ccy,$B$27),FxCodes,0))*INDEX(FxUsed,MATCH($B$12,FxCodes,0))) -> 0 | C37: =IF(ISNUMBER(Inputs!$C$28),Inputs!$C$28,"") | D37: =IF(ISNUMBER(C37),IF(C37>=0,C37,B37),B37) -> 0 | E37: =IF(ISNUMBER(C37),PlanYear,IF($B$27=0,PlanYear,INDEX(Liv_books_Base,$B$27))) -> 2026 | F37: =IF(ISNUMBER(C37),"override",IF($B$27=0,"missing",INDEX(Liv_books_Status,$B$27))) -> missing | G37: =IF(F37="verified","Published figure",IF(F37="estimated","Estimated — please review",IF(F37="notNeeded","Not needed",IF(F37="override","Your figure",IF(F37="missing","No figure yet — enter your own",""))))) -> No figure yet — enter your own | H37: living | I37: annual | J37: Yes
A38: Other university and course fees | B38: =IF($B$11=0,0,(IF($B$25>0,SUMPRODUCT((RecKey=$B$10)*RecOther*(1+$B$16)^(PlanYear-RecYear))/$B$25,INDEX(DB_EstOther,$B$11)))/INDEX(FxUsed,MATCH($B$26,FxCodes,0))*INDEX(FxUsed,MATCH($B$12,FxCodes,0))) -> 0 | C38: =IF(ISNUMBER(Inputs!$C$29),Inputs!$C$29,"") | D38: =IF(ISNUMBER(C38),IF(C38>=0,C38,B38),B38) -> 0 | E38: =IF(ISNUMBER(C38),PlanYear,IF($B$25>0,PlanYear,IF($B$11>0,INDEX(DB_EstBase,$B$11),PlanYear))) -> 2026 | F38: =IF(ISNUMBER(C38),"override",IF($B$11=0,"missing",IF($B$25>0,"verified",INDEX(DB_EstStatus,$B$11)))) -> missing | G38: =IF(F38="verified","Published figure",IF(F38="estimated","Estimated — please review",IF(F38="notNeeded","Not needed",IF(F38="override","Your figure",IF(F38="missing","No figure yet — enter your own",""))))) -> No figure yet — enter your own | H38: tuition | I38: annual | J38: Yes
A39: Admission and one-time fees | B39: =IF($B$15>0,IF($B$15>0,(INDEX(DB_PreAdm,$B$11))/INDEX(FxUsed,MATCH(INDEX(DB_PreCcy,$B$11),FxCodes,0))*INDEX(FxUsed,MATCH($B$12,FxCodes,0)),0),IF($B$11=0,0,(IF($B$25>0,SUMPRODUCT((RecKey=$B$10)*RecAdm*(1+$B$16)^(PlanYear-RecYear))/$B$25,INDEX(DB_EstAdm,$B$11)))/INDEX(FxUsed,MATCH($B$26,FxCodes,0))*INDEX(FxUsed,MATCH($B$12,FxCodes,0)))) -> 0 | C39: =IF(ISNUMBER(Inputs!$C$30),Inputs!$C$30,"") | D39: =IF(ISNUMBER(C39),IF(C39>=0,C39,B39),B39) -> 0 | E39: =IF(ISNUMBER(C39),PlanYear,IF($B$15>0,INDEX(DB_PreBase,$B$11),IF($B$25>0,PlanYear,IF($B$11>0,INDEX(DB_EstBase,$B$11),PlanYear)))) -> 2026 | F39: =IF(ISNUMBER(C39),"override",IF($B$15>0,INDEX(DB_PreStatus,$B$11),IF($B$11=0,"missing",IF($B$25>0,"verified",INDEX(DB_EstStatus,$B$11))))) -> missing | G39: =IF(F39="verified","Published figure",IF(F39="estimated","Estimated — please review",IF(F39="notNeeded","Not needed",IF(F39="override","Your figure",IF(F39="missing","No figure yet — enter your own",""))))) -> No figure yet — enter your own | H39: tuition | I39: once | J39: Yes
A40: Visa and application | B40: =IF(OR($B$28=0,AND($B$9<>"domestic",Residence=$B$5,COUNTIF(ResNoVisa,$B$5)>0)),0,(INDEX(VisaAmt,$B$28))/INDEX(FxUsed,MATCH(INDEX(VisaCcy,$B$28),FxCodes,0))*INDEX(FxUsed,MATCH($B$12,FxCodes,0))) -> 0 | C40: =IF(ISNUMBER(Inputs!$C$31),Inputs!$C$31,"") | D40: =IF(ISNUMBER(C40),IF(C40>=0,C40,B40),B40) -> 0 | E40: =IF(ISNUMBER(C40),PlanYear,IF(OR($B$28=0,AND($B$9<>"domestic",Residence=$B$5,COUNTIF(ResNoVisa,$B$5)>0)),PlanYear,INDEX(VisaBase,$B$28))) -> 2026 | F40: =IF(ISNUMBER(C40),"override",IF(AND($B$9<>"domestic",Residence=$B$5,COUNTIF(ResNoVisa,$B$5)>0),"notNeeded",IF($B$28=0,"missing",INDEX(VisaStatus,$B$28)))) -> missing | G40: =IF(F40="verified","Published figure",IF(F40="estimated","Estimated — please review",IF(F40="notNeeded","Not needed",IF(F40="override","Your figure",IF(F40="missing","No figure yet — enter your own",""))))) -> No figure yet — enter your own | H40: living | I40: once | J40: No
A41: Travel and relocation | B41: =IF($B$29=0,0,(INDEX(TravAmt,$B$29))/INDEX(FxUsed,MATCH(INDEX(TravCcy,$B$29),FxCodes,0))*INDEX(FxUsed,MATCH($B$12,FxCodes,0))) -> 0 | C41: =IF(ISNUMBER(Inputs!$C$32),Inputs!$C$32,"") | D41: =IF(ISNUMBER(C41),IF(C41>=0,C41,B41),B41) -> 0 | E41: =IF(ISNUMBER(C41),PlanYear,IF($B$29=0,PlanYear,INDEX(TravBase,$B$29))) -> 2026 | F41: =IF(ISNUMBER(C41),"override",IF($B$29=0,"missing",INDEX(TravStatus,$B$29))) -> missing | G41: =IF(F41="verified","Published figure",IF(F41="estimated","Estimated — please review",IF(F41="notNeeded","Not needed",IF(F41="override","Your figure",IF(F41="missing","No figure yet — enter your own",""))))) -> No figure yet — enter your own | H41: living | I41: once | J41: No
A42: Pre-stage tuition (e.g. pre-medical degree) | B42: =IF($B$15>0,(INDEX(DB_PreTuition,$B$11))/INDEX(FxUsed,MATCH(INDEX(DB_PreCcy,$B$11),FxCodes,0))*INDEX(FxUsed,MATCH($B$12,FxCodes,0)),0) -> 0 | C42: =IF(ISNUMBER(Inputs!$C$33),Inputs!$C$33,"") | D42: =IF(ISNUMBER(C42),IF(C42>=0,C42,B42),B42) -> 0 | E42: =IF(ISNUMBER(C42),PlanYear,IF($B$15>0,INDEX(DB_PreBase,$B$11),PlanYear)) -> 2026 | F42: =IF(ISNUMBER(C42),"override",IF($B$15>0,INDEX(DB_PreStatus,$B$11),"")) | G42: =IF(F42="verified","Published figure",IF(F42="estimated","Estimated — please review",IF(F42="notNeeded","Not needed",IF(F42="override","Your figure",IF(F42="missing","No figure yet — enter your own",""))))) | H42: tuition | I42: annual | J42: Yes
A43: Pre-stage other fees | B43: =IF($B$15>0,(INDEX(DB_PreOther,$B$11))/INDEX(FxUsed,MATCH(INDEX(DB_PreCcy,$B$11),FxCodes,0))*INDEX(FxUsed,MATCH($B$12,FxCodes,0)),0) -> 0 | C43: =IF(ISNUMBER(Inputs!$C$34),Inputs!$C$34,"") | D43: =IF(ISNUMBER(C43),IF(C43>=0,C43,B43),B43) -> 0 | E43: =IF(ISNUMBER(C43),PlanYear,IF($B$15>0,INDEX(DB_PreBase,$B$11),PlanYear)) -> 2026 | F43: =IF(ISNUMBER(C43),"override",IF($B$15>0,INDEX(DB_PreStatus,$B$11),"")) | G43: =IF(F43="verified","Published figure",IF(F43="estimated","Estimated — please review",IF(F43="notNeeded","Not needed",IF(F43="override","Your figure",IF(F43="missing","No figure yet — enter your own",""))))) | H43: tuition | I43: annual | J43: Yes
A45: Study year (0 = first) | B45: Calendar year | C45: Fraction of year | D45: In pre-stage (1/0) | E45: In course (1/0) | F45: Tuition (gross) | G45: Accommodation (gross) | H45: Food (gross) | I45: Local transport (gross) | J45: Health insurance (gross) | K45: Books and supplies (gross) | L45: Other university and course fees (gross) | M45: Admission and one-time fees (gross) | N45: Visa and application (gross) | O45: Travel and relocation (gross) | P45: Tuition | Q45: Accommodation | R45: Food | S45: Local transport | T45: Health insurance | U45: Books and supplies | V45: Other university and course fees | W45: Admission and one-time fees | X45: Visa and application | Y45: Travel and relocation | Z45: Education expenses | AA45: Before scholarship
A46: 0 | B46: =PlanYear+$B$18+A46 -> 2026 | C46: =MAX(0,MIN(1,$B$13-A46)) -> 0 | D46: =IF(A46<$B$15,1,0) -> 0 | E46: =IF(AND($B$22=1,A46<$B$19),1,0) -> 0 | F46: =IF(AND(E46=1),IF(D46=1,$D$42,$D$32)*(1+$B$16)^(B46-IF(D46=1,$E$42,$E$32))*C46*$B$24,0) -> 0 | G46: =IF(AND(E46=1),$D$33*(1+$B$17)^(B46-$E$33)*C46*$B$24,0) -> 0 | H46: =IF(AND(E46=1),$D$34*(1+$B$17)^(B46-$E$34)*C46*$B$24,0) -> 0 | I46: =IF(AND(E46=1),$D$35*(1+$B$17)^(B46-$E$35)*C46*$B$24,0) -> 0 | J46: =IF(AND(E46=1),$D$36*(1+$B$17)^(B46-$E$36)*C46*$B$24,0) -> 0 | K46: =IF(AND(E46=1),$D$37*(1+$B$17)^(B46-$E$37)*C46*$B$24,0) -> 0 | L46: =IF(AND(E46=1),IF(D46=1,$D$43,$D$38)*(1+$B$16)^(B46-IF(D46=1,$E$43,$E$38))*C46*$B$24,0) -> 0 | M46: =IF(AND(E46=1,A46=0),$D$39*(1+$B$16)^(B46-$E$39)*$B$24,0) -> 0 | N46: =IF(AND(E46=1,A46=0),$D$40*(1+$B$17)^(B46-$E$40)*$B$24,0) -> 0 | O46: =IF(AND(E46=1,A46=0),$D$41*(1+$B$17)^(B46-$E$41)*$B$24,0) -> 0 | P46: =F46*(1-Coverage) -> 0 | Q46: =G46*(1-Coverage) -> 0 | R46: =H46*(1-Coverage) -> 0 | S46: =I46*(1-Coverage) -> 0 | T46: =J46*(1-Coverage) -> 0 | U46: =K46*(1-Coverage) -> 0 | V46: =L46*(1-Coverage) -> 0 | W46: =M46*(1-Coverage) -> 0 | X46: =N46*1 -> 0 | Y46: =O46*1 -> 0 | Z46: =SUM(P46:Y46) -> 0 | AA46: =SUM(F46:O46) -> 0
A47: 1 | B47: =PlanYear+$B$18+A47 -> 2027 | C47: =MAX(0,MIN(1,$B$13-A47)) -> 0 | D47: =IF(A47<$B$15,1,0) -> 0 | E47: =IF(AND($B$22=1,A47<$B$19),1,0) -> 0 | F47: =IF(AND(E47=1),IF(D47=1,$D$42,$D$32)*(1+$B$16)^(B47-IF(D47=1,$E$42,$E$32))*C47*$B$24,0) -> 0 | G47: =IF(AND(E47=1),$D$33*(1+$B$17)^(B47-$E$33)*C47*$B$24,0) -> 0 | H47: =IF(AND(E47=1),$D$34*(1+$B$17)^(B47-$E$34)*C47*$B$24,0) -> 0 | I47: =IF(AND(E47=1),$D$35*(1+$B$17)^(B47-$E$35)*C47*$B$24,0) -> 0 | J47: =IF(AND(E47=1),$D$36*(1+$B$17)^(B47-$E$36)*C47*$B$24,0) -> 0 | K47: =IF(AND(E47=1),$D$37*(1+$B$17)^(B47-$E$37)*C47*$B$24,0) -> 0 | L47: =IF(AND(E47=1),IF(D47=1,$D$43,$D$38)*(1+$B$16)^(B47-IF(D47=1,$E$43,$E$38))*C47*$B$24,0) -> 0 | M47: =IF(AND(E47=1,A47=0),$D$39*(1+$B$16)^(B47-$E$39)*$B$24,0) -> 0 | N47: =IF(AND(E47=1,A47=0),$D$40*(1+$B$17)^(B47-$E$40)*$B$24,0) -> 0 | O47: =IF(AND(E47=1,A47=0),$D$41*(1+$B$17)^(B47-$E$41)*$B$24,0) -> 0 | P47: =F47*(1-Coverage) -> 0 | Q47: =G47*(1-Coverage) -> 0 | R47: =H47*(1-Coverage) -> 0 | S47: =I47*(1-Coverage) -> 0 | T47: =J47*(1-Coverage) -> 0 | U47: =K47*(1-Coverage) -> 0 | V47: =L47*(1-Coverage) -> 0 | W47: =M47*(1-Coverage) -> 0 | X47: =N47*1 -> 0 | Y47: =O47*1 -> 0 | Z47: =SUM(P47:Y47) -> 0 | AA47: =SUM(F47:O47) -> 0
A48: 2 | B48: =PlanYear+$B$18+A48 -> 2028 | C48: =MAX(0,MIN(1,$B$13-A48)) -> 0 | D48: =IF(A48<$B$15,1,0) -> 0 | E48: =IF(AND($B$22=1,A48<$B$19),1,0) -> 0 | F48: =IF(AND(E48=1),IF(D48=1,$D$42,$D$32)*(1+$B$16)^(B48-IF(D48=1,$E$42,$E$32))*C48*$B$24,0) -> 0 | G48: =IF(AND(E48=1),$D$33*(1+$B$17)^(B48-$E$33)*C48*$B$24,0) -> 0 | H48: =IF(AND(E48=1),$D$34*(1+$B$17)^(B48-$E$34)*C48*$B$24,0) -> 0 | I48: =IF(AND(E48=1),$D$35*(1+$B$17)^(B48-$E$35)*C48*$B$24,0) -> 0 | J48: =IF(AND(E48=1),$D$36*(1+$B$17)^(B48-$E$36)*C48*$B$24,0) -> 0 | K48: =IF(AND(E48=1),$D$37*(1+$B$17)^(B48-$E$37)*C48*$B$24,0) -> 0 | L48: =IF(AND(E48=1),IF(D48=1,$D$43,$D$38)*(1+$B$16)^(B48-IF(D48=1,$E$43,$E$38))*C48*$B$24,0) -> 0 | M48: =IF(AND(E48=1,A48=0),$D$39*(1+$B$16)^(B48-$E$39)*$B$24,0) -> 0 | N48: =IF(AND(E48=1,A48=0),$D$40*(1+$B$17)^(B48-$E$40)*$B$24,0) -> 0 | O48: =IF(AND(E48=1,A48=0),$D$41*(1+$B$17)^(B48-$E$41)*$B$24,0) -> 0 | P48: =F48*(1-Coverage) -> 0 | Q48: =G48*(1-Coverage) -> 0 | R48: =H48*(1-Coverage) -> 0 | S48: =I48*(1-Coverage) -> 0 | T48: =J48*(1-Coverage) -> 0 | U48: =K48*(1-Coverage) -> 0 | V48: =L48*(1-Coverage) -> 0 | W48: =M48*(1-Coverage) -> 0 | X48: =N48*1 -> 0 | Y48: =O48*1 -> 0 | Z48: =SUM(P48:Y48) -> 0 | AA48: =SUM(F48:O48) -> 0
A49: 3 | B49: =PlanYear+$B$18+A49 -> 2029 | C49: =MAX(0,MIN(1,$B$13-A49)) -> 0 | D49: =IF(A49<$B$15,1,0) -> 0 | E49: =IF(AND($B$22=1,A49<$B$19),1,0) -> 0 | F49: =IF(AND(E49=1),IF(D49=1,$D$42,$D$32)*(1+$B$16)^(B49-IF(D49=1,$E$42,$E$32))*C49*$B$24,0) -> 0 | G49: =IF(AND(E49=1),$D$33*(1+$B$17)^(B49-$E$33)*C49*$B$24,0) -> 0 | H49: =IF(AND(E49=1),$D$34*(1+$B$17)^(B49-$E$34)*C49*$B$24,0) -> 0 | I49: =IF(AND(E49=1),$D$35*(1+$B$17)^(B49-$E$35)*C49*$B$24,0) -> 0 | J49: =IF(AND(E49=1),$D$36*(1+$B$17)^(B49-$E$36)*C49*$B$24,0) -> 0 | K49: =IF(AND(E49=1),$D$37*(1+$B$17)^(B49-$E$37)*C49*$B$24,0) -> 0 | L49: =IF(AND(E49=1),IF(D49=1,$D$43,$D$38)*(1+$B$16)^(B49-IF(D49=1,$E$43,$E$38))*C49*$B$24,0) -> 0 | M49: =IF(AND(E49=1,A49=0),$D$39*(1+$B$16)^(B49-$E$39)*$B$24,0) -> 0 | N49: =IF(AND(E49=1,A49=0),$D$40*(1+$B$17)^(B49-$E$40)*$B$24,0) -> 0 | O49: =IF(AND(E49=1,A49=0),$D$41*(1+$B$17)^(B49-$E$41)*$B$24,0) -> 0 | P49: =F49*(1-Coverage) -> 0 | Q49: =G49*(1-Coverage) -> 0 | R49: =H49*(1-Coverage) -> 0 | S49: =I49*(1-Coverage) -> 0 | T49: =J49*(1-Coverage) -> 0 | U49: =K49*(1-Coverage) -> 0 | V49: =L49*(1-Coverage) -> 0 | W49: =M49*(1-Coverage) -> 0 | X49: =N49*1 -> 0 | Y49: =O49*1 -> 0 | Z49: =SUM(P49:Y49) -> 0 | AA49: =SUM(F49:O49) -> 0
A50: 4 | B50: =PlanYear+$B$18+A50 -> 2030 | C50: =MAX(0,MIN(1,$B$13-A50)) -> 0 | D50: =IF(A50<$B$15,1,0) -> 0 | E50: =IF(AND($B$22=1,A50<$B$19),1,0) -> 0 | F50: =IF(AND(E50=1),IF(D50=1,$D$42,$D$32)*(1+$B$16)^(B50-IF(D50=1,$E$42,$E$32))*C50*$B$24,0) -> 0 | G50: =IF(AND(E50=1),$D$33*(1+$B$17)^(B50-$E$33)*C50*$B$24,0) -> 0 | H50: =IF(AND(E50=1),$D$34*(1+$B$17)^(B50-$E$34)*C50*$B$24,0) -> 0 | I50: =IF(AND(E50=1),$D$35*(1+$B$17)^(B50-$E$35)*C50*$B$24,0) -> 0 | J50: =IF(AND(E50=1),$D$36*(1+$B$17)^(B50-$E$36)*C50*$B$24,0) -> 0 | K50: =IF(AND(E50=1),$D$37*(1+$B$17)^(B50-$E$37)*C50*$B$24,0) -> 0 | L50: =IF(AND(E50=1),IF(D50=1,$D$43,$D$38)*(1+$B$16)^(B50-IF(D50=1,$E$43,$E$38))*C50*$B$24,0) -> 0 | M50: =IF(AND(E50=1,A50=0),$D$39*(1+$B$16)^(B50-$E$39)*$B$24,0) -> 0 | N50: =IF(AND(E50=1,A50=0),$D$40*(1+$B$17)^(B50-$E$40)*$B$24,0) -> 0 | O50: =IF(AND(E50=1,A50=0),$D$41*(1+$B$17)^(B50-$E$41)*$B$24,0) -> 0 | P50: =F50*(1-Coverage) -> 0 | Q50: =G50*(1-Coverage) -> 0 | R50: =H50*(1-Coverage) -> 0 | S50: =I50*(1-Coverage) -> 0 | T50: =J50*(1-Coverage) -> 0 | U50: =K50*(1-Coverage) -> 0 | V50: =L50*(1-Coverage) -> 0 | W50: =M50*(1-Coverage) -> 0 | X50: =N50*1 -> 0 | Y50: =O50*1 -> 0 | Z50: =SUM(P50:Y50) -> 0 | AA50: =SUM(F50:O50) -> 0
A51: 5 | B51: =PlanYear+$B$18+A51 -> 2031 | C51: =MAX(0,MIN(1,$B$13-A51)) -> 0 | D51: =IF(A51<$B$15,1,0) -> 0 | E51: =IF(AND($B$22=1,A51<$B$19),1,0) -> 0 | F51: =IF(AND(E51=1),IF(D51=1,$D$42,$D$32)*(1+$B$16)^(B51-IF(D51=1,$E$42,$E$32))*C51*$B$24,0) -> 0 | G51: =IF(AND(E51=1),$D$33*(1+$B$17)^(B51-$E$33)*C51*$B$24,0) -> 0 | H51: =IF(AND(E51=1),$D$34*(1+$B$17)^(B51-$E$34)*C51*$B$24,0) -> 0 | I51: =IF(AND(E51=1),$D$35*(1+$B$17)^(B51-$E$35)*C51*$B$24,0) -> 0 | J51: =IF(AND(E51=1),$D$36*(1+$B$17)^(B51-$E$36)*C51*$B$24,0) -> 0 | K51: =IF(AND(E51=1),$D$37*(1+$B$17)^(B51-$E$37)*C51*$B$24,0) -> 0 | L51: =IF(AND(E51=1),IF(D51=1,$D$43,$D$38)*(1+$B$16)^(B51-IF(D51=1,$E$43,$E$38))*C51*$B$24,0) -> 0 | M51: =IF(AND(E51=1,A51=0),$D$39*(1+$B$16)^(B51-$E$39)*$B$24,0) -> 0 | N51: =IF(AND(E51=1,A51=0),$D$40*(1+$B$17)^(B51-$E$40)*$B$24,0) -> 0 | O51: =IF(AND(E51=1,A51=0),$D$41*(1+$B$17)^(B51-$E$41)*$B$24,0) -> 0 | P51: =F51*(1-Coverage) -> 0 | Q51: =G51*(1-Coverage) -> 0 | R51: =H51*(1-Coverage) -> 0 | S51: =I51*(1-Coverage) -> 0 | T51: =J51*(1-Coverage) -> 0 | U51: =K51*(1-Coverage) -> 0 | V51: =L51*(1-Coverage) -> 0 | W51: =M51*(1-Coverage) -> 0 | X51: =N51*1 -> 0 | Y51: =O51*1 -> 0 | Z51: =SUM(P51:Y51) -> 0 | AA51: =SUM(F51:O51) -> 0
A52: 6 | B52: =PlanYear+$B$18+A52 -> 2032 | C52: =MAX(0,MIN(1,$B$13-A52)) -> 0 | D52: =IF(A52<$B$15,1,0) -> 0 | E52: =IF(AND($B$22=1,A52<$B$19),1,0) -> 0 | F52: =IF(AND(E52=1),IF(D52=1,$D$42,$D$32)*(1+$B$16)^(B52-IF(D52=1,$E$42,$E$32))*C52*$B$24,0) -> 0 | G52: =IF(AND(E52=1),$D$33*(1+$B$17)^(B52-$E$33)*C52*$B$24,0) -> 0 | H52: =IF(AND(E52=1),$D$34*(1+$B$17)^(B52-$E$34)*C52*$B$24,0) -> 0 | I52: =IF(AND(E52=1),$D$35*(1+$B$17)^(B52-$E$35)*C52*$B$24,0) -> 0 | J52: =IF(AND(E52=1),$D$36*(1+$B$17)^(B52-$E$36)*C52*$B$24,0) -> 0 | K52: =IF(AND(E52=1),$D$37*(1+$B$17)^(B52-$E$37)*C52*$B$24,0) -> 0 | L52: =IF(AND(E52=1),IF(D52=1,$D$43,$D$38)*(1+$B$16)^(B52-IF(D52=1,$E$43,$E$38))*C52*$B$24,0) -> 0 | M52: =IF(AND(E52=1,A52=0),$D$39*(1+$B$16)^(B52-$E$39)*$B$24,0) -> 0 | N52: =IF(AND(E52=1,A52=0),$D$40*(1+$B$17)^(B52-$E$40)*$B$24,0) -> 0 | O52: =IF(AND(E52=1,A52=0),$D$41*(1+$B$17)^(B52-$E$41)*$B$24,0) -> 0 | P52: =F52*(1-Coverage) -> 0 | Q52: =G52*(1-Coverage) -> 0 | R52: =H52*(1-Coverage) -> 0 | S52: =I52*(1-Coverage) -> 0 | T52: =J52*(1-Coverage) -> 0 | U52: =K52*(1-Coverage) -> 0 | V52: =L52*(1-Coverage) -> 0 | W52: =M52*(1-Coverage) -> 0 | X52: =N52*1 -> 0 | Y52: =O52*1 -> 0 | Z52: =SUM(P52:Y52) -> 0 | AA52: =SUM(F52:O52) -> 0
A53: 7 | B53: =PlanYear+$B$18+A53 -> 2033 | C53: =MAX(0,MIN(1,$B$13-A53)) -> 0 | D53: =IF(A53<$B$15,1,0) -> 0 | E53: =IF(AND($B$22=1,A53<$B$19),1,0) -> 0 | F53: =IF(AND(E53=1),IF(D53=1,$D$42,$D$32)*(1+$B$16)^(B53-IF(D53=1,$E$42,$E$32))*C53*$B$24,0) -> 0 | G53: =IF(AND(E53=1),$D$33*(1+$B$17)^(B53-$E$33)*C53*$B$24,0) -> 0 | H53: =IF(AND(E53=1),$D$34*(1+$B$17)^(B53-$E$34)*C53*$B$24,0) -> 0 | I53: =IF(AND(E53=1),$D$35*(1+$B$17)^(B53-$E$35)*C53*$B$24,0) -> 0 | J53: =IF(AND(E53=1),$D$36*(1+$B$17)^(B53-$E$36)*C53*$B$24,0) -> 0 | K53: =IF(AND(E53=1),$D$37*(1+$B$17)^(B53-$E$37)*C53*$B$24,0) -> 0 | L53: =IF(AND(E53=1),IF(D53=1,$D$43,$D$38)*(1+$B$16)^(B53-IF(D53=1,$E$43,$E$38))*C53*$B$24,0) -> 0 | M53: =IF(AND(E53=1,A53=0),$D$39*(1+$B$16)^(B53-$E$39)*$B$24,0) -> 0 | N53: =IF(AND(E53=1,A53=0),$D$40*(1+$B$17)^(B53-$E$40)*$B$24,0) -> 0 | O53: =IF(AND(E53=1,A53=0),$D$41*(1+$B$17)^(B53-$E$41)*$B$24,0) -> 0 | P53: =F53*(1-Coverage) -> 0 | Q53: =G53*(1-Coverage) -> 0 | R53: =H53*(1-Coverage) -> 0 | S53: =I53*(1-Coverage) -> 0 | T53: =J53*(1-Coverage) -> 0 | U53: =K53*(1-Coverage) -> 0 | V53: =L53*(1-Coverage) -> 0 | W53: =M53*(1-Coverage) -> 0 | X53: =N53*1 -> 0 | Y53: =O53*1 -> 0 | Z53: =SUM(P53:Y53) -> 0 | AA53: =SUM(F53:O53) -> 0
A54: 8 | B54: =PlanYear+$B$18+A54 -> 2034 | C54: =MAX(0,MIN(1,$B$13-A54)) -> 0 | D54: =IF(A54<$B$15,1,0) -> 0 | E54: =IF(AND($B$22=1,A54<$B$19),1,0) -> 0 | F54: =IF(AND(E54=1),IF(D54=1,$D$42,$D$32)*(1+$B$16)^(B54-IF(D54=1,$E$42,$E$32))*C54*$B$24,0) -> 0 | G54: =IF(AND(E54=1),$D$33*(1+$B$17)^(B54-$E$33)*C54*$B$24,0) -> 0 | H54: =IF(AND(E54=1),$D$34*(1+$B$17)^(B54-$E$34)*C54*$B$24,0) -> 0 | I54: =IF(AND(E54=1),$D$35*(1+$B$17)^(B54-$E$35)*C54*$B$24,0) -> 0 | J54: =IF(AND(E54=1),$D$36*(1+$B$17)^(B54-$E$36)*C54*$B$24,0) -> 0 | K54: =IF(AND(E54=1),$D$37*(1+$B$17)^(B54-$E$37)*C54*$B$24,0) -> 0 | L54: =IF(AND(E54=1),IF(D54=1,$D$43,$D$38)*(1+$B$16)^(B54-IF(D54=1,$E$43,$E$38))*C54*$B$24,0) -> 0 | M54: =IF(AND(E54=1,A54=0),$D$39*(1+$B$16)^(B54-$E$39)*$B$24,0) -> 0 | N54: =IF(AND(E54=1,A54=0),$D$40*(1+$B$17)^(B54-$E$40)*$B$24,0) -> 0 | O54: =IF(AND(E54=1,A54=0),$D$41*(1+$B$17)^(B54-$E$41)*$B$24,0) -> 0 | P54: =F54*(1-Coverage) -> 0 | Q54: =G54*(1-Coverage) -> 0 | R54: =H54*(1-Coverage) -> 0 | S54: =I54*(1-Coverage) -> 0 | T54: =J54*(1-Coverage) -> 0 | U54: =K54*(1-Coverage) -> 0 | V54: =L54*(1-Coverage) -> 0 | W54: =M54*(1-Coverage) -> 0 | X54: =N54*1 -> 0 | Y54: =O54*1 -> 0 | Z54: =SUM(P54:Y54) -> 0 | AA54: =SUM(F54:O54) -> 0
A55: 9 | B55: =PlanYear+$B$18+A55 -> 2035 | C55: =MAX(0,MIN(1,$B$13-A55)) -> 0 | D55: =IF(A55<$B$15,1,0) -> 0 | E55: =IF(AND($B$22=1,A55<$B$19),1,0) -> 0 | F55: =IF(AND(E55=1),IF(D55=1,$D$42,$D$32)*(1+$B$16)^(B55-IF(D55=1,$E$42,$E$32))*C55*$B$24,0) -> 0 | G55: =IF(AND(E55=1),$D$33*(1+$B$17)^(B55-$E$33)*C55*$B$24,0) -> 0 | H55: =IF(AND(E55=1),$D$34*(1+$B$17)^(B55-$E$34)*C55*$B$24,0) -> 0 | I55: =IF(AND(E55=1),$D$35*(1+$B$17)^(B55-$E$35)*C55*$B$24,0) -> 0 | J55: =IF(AND(E55=1),$D$36*(1+$B$17)^(B55-$E$36)*C55*$B$24,0) -> 0 | K55: =IF(AND(E55=1),$D$37*(1+$B$17)^(B55-$E$37)*C55*$B$24,0) -> 0 | L55: =IF(AND(E55=1),IF(D55=1,$D$43,$D$38)*(1+$B$16)^(B55-IF(D55=1,$E$43,$E$38))*C55*$B$24,0) -> 0 | M55: =IF(AND(E55=1,A55=0),$D$39*(1+$B$16)^(B55-$E$39)*$B$24,0) -> 0 | N55: =IF(AND(E55=1,A55=0),$D$40*(1+$B$17)^(B55-$E$40)*$B$24,0) -> 0 | O55: =IF(AND(E55=1,A55=0),$D$41*(1+$B$17)^(B55-$E$41)*$B$24,0) -> 0 | P55: =F55*(1-Coverage) -> 0 | Q55: =G55*(1-Coverage) -> 0 | R55: =H55*(1-Coverage) -> 0 | S55: =I55*(1-Coverage) -> 0 | T55: =J55*(1-Coverage) -> 0 | U55: =K55*(1-Coverage) -> 0 | V55: =L55*(1-Coverage) -> 0 | W55: =M55*(1-Coverage) -> 0 | X55: =N55*1 -> 0 | Y55: =O55*1 -> 0 | Z55: =SUM(P55:Y55) -> 0 | AA55: =SUM(F55:O55) -> 0
A56: Total | F56: =SUM(F46:F55) -> 0 | G56: =SUM(G46:G55) -> 0 | H56: =SUM(H46:H55) -> 0 | I56: =SUM(I46:I55) -> 0 | J56: =SUM(J46:J55) -> 0 | K56: =SUM(K46:K55) -> 0 | L56: =SUM(L46:L55) -> 0 | M56: =SUM(M46:M55) -> 0 | ... AA56: =SUM(AA46:AA55) -> 0
A58: Total estimated education cost (results currency) | B58: =$Z$56 -> 0
A59: Covered by scholarship / part-time work | B59: =$AA$56-$Z$56 -> 0
A60: Tuition figure status | B60: =IF(OR($F$32="missing",AND($B$15>0,$F$42="missing")),"missing",IF(OR($F$32="estimated",AND($B$15>0,$F$42="estimated")),"estimated",IF($B$15>0,$F$42,$F$32))) -> missing
A61: Some costs have no figure (1/0) | B61: =IF(OR($F$32="missing",AND($B$15>0,$F$42="missing"),$F$33="missing"),1,0) -> 1
A63: Savings and yearly fund (results currency). Costs are paid at the start of each year, savings added at the end.
A64: Plan year | B64: Calendar year | C64: Study year | D64: Education expenses | E64: Saving factor | F64: Growth factor | G64: a (no saving) | H64: b (per 1 saved) | I64: A carried | J64: B carried | K64: Needed-now candidate | L64: Saving candidate | M64: Opening fund | N64: Family savings added | O64: Investment growth | P64: Closing fund | Q64: Studying (1/0)
A65: 1 | B65: =PlanYear+A65-1 -> 2026 | C65: =A65-1-$B$18 -> 0 | D65: =IF(AND($B$22=1,C65>=0,C65<$B$19),INDEX($Z$46:$Z$55,C65+1),0) -> 0 | E65: =IF(AND($B$22=1,A65<=$B$21),(1+SavInc)^(A65-1),0) -> 0 | F65: =(1+ReturnRate)^(A65-1) -> 1 | G65: =-D65 -> 0 | H65: =0 -> 0 | I65: =G65*(1+ReturnRate) -> 0 | J65: =H65*(1+ReturnRate)+E65 -> 0 | K65: =IF(AND(D65>0,H65<=0.000000000001,G65<0),-G65/F65,0) -> 0 | L65: =IF(AND(D65>0,H65>0.000000000001),-(G65+$B$126*F65)/H65,0) -> 0 | M65: =$B$126 -> 0 | N65: =E65*$B$127 -> 0 | O65: =IF(AND($B$22=1,A65<=$B$20),(M65-D65)*ReturnRate,0) -> 0 | P65: =M65-D65+O65+N65 -> 0 | Q65: =IF(AND($B$22=1,C65>=0,C65<$B$19),1,0) -> 0
A66: 2 | B66: =PlanYear+A66-1 -> 2027 | C66: =A66-1-$B$18 -> 1 | D66: =IF(AND($B$22=1,C66>=0,C66<$B$19),INDEX($Z$46:$Z$55,C66+1),0) -> 0 | E66: =IF(AND($B$22=1,A66<=$B$21),(1+SavInc)^(A66-1),0) -> 0 | F66: =(1+ReturnRate)^(A66-1) -> 1.06 | G66: =I65-D66 -> 0 | H66: =J65 -> 0 | I66: =G66*(1+ReturnRate) -> 0 | J66: =H66*(1+ReturnRate)+E66 -> 0 | K66: =IF(AND(D66>0,H66<=0.000000000001,G66<0),-G66/F66,0) -> 0 | L66: =IF(AND(D66>0,H66>0.000000000001),-(G66+$B$126*F66)/H66,0) -> 0 | M66: =P65 -> 0 | N66: =E66*$B$127 -> 0 | O66: =IF(AND($B$22=1,A66<=$B$20),(M66-D66)*ReturnRate,0) -> 0 | P66: =M66-D66+O66+N66 -> 0 | Q66: =IF(AND($B$22=1,C66>=0,C66<$B$19),1,0) -> 0
A67: 3 | B67: =PlanYear+A67-1 -> 2028 | C67: =A67-1-$B$18 -> 2 | D67: =IF(AND($B$22=1,C67>=0,C67<$B$19),INDEX($Z$46:$Z$55,C67+1),0) -> 0 | E67: =IF(AND($B$22=1,A67<=$B$21),(1+SavInc)^(A67-1),0) -> 0 | F67: =(1+ReturnRate)^(A67-1) -> 1.1236 | G67: =I66-D67 -> 0 | H67: =J66 -> 0 | I67: =G67*(1+ReturnRate) -> 0 | J67: =H67*(1+ReturnRate)+E67 -> 0 | K67: =IF(AND(D67>0,H67<=0.000000000001,G67<0),-G67/F67,0) -> 0 | L67: =IF(AND(D67>0,H67>0.000000000001),-(G67+$B$126*F67)/H67,0) -> 0 | M67: =P66 -> 0 | N67: =E67*$B$127 -> 0 | O67: =IF(AND($B$22=1,A67<=$B$20),(M67-D67)*ReturnRate,0) -> 0 | P67: =M67-D67+O67+N67 -> 0 | Q67: =IF(AND($B$22=1,C67>=0,C67<$B$19),1,0) -> 0
A68: 4 | B68: =PlanYear+A68-1 -> 2029 | C68: =A68-1-$B$18 -> 3 | D68: =IF(AND($B$22=1,C68>=0,C68<$B$19),INDEX($Z$46:$Z$55,C68+1),0) -> 0 | E68: =IF(AND($B$22=1,A68<=$B$21),(1+SavInc)^(A68-1),0) -> 0 | F68: =(1+ReturnRate)^(A68-1) -> 1.191016 | G68: =I67-D68 -> 0 | H68: =J67 -> 0 | I68: =G68*(1+ReturnRate) -> 0 | J68: =H68*(1+ReturnRate)+E68 -> 0 | K68: =IF(AND(D68>0,H68<=0.000000000001,G68<0),-G68/F68,0) -> 0 | L68: =IF(AND(D68>0,H68>0.000000000001),-(G68+$B$126*F68)/H68,0) -> 0 | M68: =P67 -> 0 | N68: =E68*$B$127 -> 0 | O68: =IF(AND($B$22=1,A68<=$B$20),(M68-D68)*ReturnRate,0) -> 0 | P68: =M68-D68+O68+N68 -> 0 | Q68: =IF(AND($B$22=1,C68>=0,C68<$B$19),1,0) -> 0
A69: 5 | B69: =PlanYear+A69-1 -> 2030 | C69: =A69-1-$B$18 -> 4 | D69: =IF(AND($B$22=1,C69>=0,C69<$B$19),INDEX($Z$46:$Z$55,C69+1),0) -> 0 | E69: =IF(AND($B$22=1,A69<=$B$21),(1+SavInc)^(A69-1),0) -> 0 | F69: =(1+ReturnRate)^(A69-1) -> 1.262477 | G69: =I68-D69 -> 0 | H69: =J68 -> 0 | I69: =G69*(1+ReturnRate) -> 0 | J69: =H69*(1+ReturnRate)+E69 -> 0 | K69: =IF(AND(D69>0,H69<=0.000000000001,G69<0),-G69/F69,0) -> 0 | L69: =IF(AND(D69>0,H69>0.000000000001),-(G69+$B$126*F69)/H69,0) -> 0 | M69: =P68 -> 0 | N69: =E69*$B$127 -> 0 | O69: =IF(AND($B$22=1,A69<=$B$20),(M69-D69)*ReturnRate,0) -> 0 | P69: =M69-D69+O69+N69 -> 0 | Q69: =IF(AND($B$22=1,C69>=0,C69<$B$19),1,0) -> 0
A70: 6 | B70: =PlanYear+A70-1 -> 2031 | C70: =A70-1-$B$18 -> 5 | D70: =IF(AND($B$22=1,C70>=0,C70<$B$19),INDEX($Z$46:$Z$55,C70+1),0) -> 0 | E70: =IF(AND($B$22=1,A70<=$B$21),(1+SavInc)^(A70-1),0) -> 0 | F70: =(1+ReturnRate)^(A70-1) -> 1.3382256 | G70: =I69-D70 -> 0 | H70: =J69 -> 0 | I70: =G70*(1+ReturnRate) -> 0 | J70: =H70*(1+ReturnRate)+E70 -> 0 | K70: =IF(AND(D70>0,H70<=0.000000000001,G70<0),-G70/F70,0) -> 0 | L70: =IF(AND(D70>0,H70>0.000000000001),-(G70+$B$126*F70)/H70,0) -> 0 | M70: =P69 -> 0 | N70: =E70*$B$127 -> 0 | O70: =IF(AND($B$22=1,A70<=$B$20),(M70-D70)*ReturnRate,0) -> 0 | P70: =M70-D70+O70+N70 -> 0 | Q70: =IF(AND($B$22=1,C70>=0,C70<$B$19),1,0) -> 0
A71: 7 | B71: =PlanYear+A71-1 -> 2032 | C71: =A71-1-$B$18 -> 6 | D71: =IF(AND($B$22=1,C71>=0,C71<$B$19),INDEX($Z$46:$Z$55,C71+1),0) -> 0 | E71: =IF(AND($B$22=1,A71<=$B$21),(1+SavInc)^(A71-1),0) -> 0 | F71: =(1+ReturnRate)^(A71-1) -> 1.4185191 | G71: =I70-D71 -> 0 | H71: =J70 -> 0 | I71: =G71*(1+ReturnRate) -> 0 | J71: =H71*(1+ReturnRate)+E71 -> 0 | K71: =IF(AND(D71>0,H71<=0.000000000001,G71<0),-G71/F71,0) -> 0 | L71: =IF(AND(D71>0,H71>0.000000000001),-(G71+$B$126*F71)/H71,0) -> 0 | M71: =P70 -> 0 | N71: =E71*$B$127 -> 0 | O71: =IF(AND($B$22=1,A71<=$B$20),(M71-D71)*ReturnRate,0) -> 0 | P71: =M71-D71+O71+N71 -> 0 | Q71: =IF(AND($B$22=1,C71>=0,C71<$B$19),1,0) -> 0
A72: 8 | B72: =PlanYear+A72-1 -> 2033 | C72: =A72-1-$B$18 -> 7 | D72: =IF(AND($B$22=1,C72>=0,C72<$B$19),INDEX($Z$46:$Z$55,C72+1),0) -> 0 | E72: =IF(AND($B$22=1,A72<=$B$21),(1+SavInc)^(A72-1),0) -> 0 | F72: =(1+ReturnRate)^(A72-1) -> 1.5036303 | G72: =I71-D72 -> 0 | H72: =J71 -> 0 | I72: =G72*(1+ReturnRate) -> 0 | J72: =H72*(1+ReturnRate)+E72 -> 0 | K72: =IF(AND(D72>0,H72<=0.000000000001,G72<0),-G72/F72,0) -> 0 | L72: =IF(AND(D72>0,H72>0.000000000001),-(G72+$B$126*F72)/H72,0) -> 0 | M72: =P71 -> 0 | N72: =E72*$B$127 -> 0 | O72: =IF(AND($B$22=1,A72<=$B$20),(M72-D72)*ReturnRate,0) -> 0 | P72: =M72-D72+O72+N72 -> 0 | Q72: =IF(AND($B$22=1,C72>=0,C72<$B$19),1,0) -> 0
A73: 9 | B73: =PlanYear+A73-1 -> 2034 | C73: =A73-1-$B$18 -> 8 | D73: =IF(AND($B$22=1,C73>=0,C73<$B$19),INDEX($Z$46:$Z$55,C73+1),0) -> 0 | E73: =IF(AND($B$22=1,A73<=$B$21),(1+SavInc)^(A73-1),0) -> 0 | F73: =(1+ReturnRate)^(A73-1) -> 1.5938481 | G73: =I72-D73 -> 0 | H73: =J72 -> 0 | I73: =G73*(1+ReturnRate) -> 0 | J73: =H73*(1+ReturnRate)+E73 -> 0 | K73: =IF(AND(D73>0,H73<=0.000000000001,G73<0),-G73/F73,0) -> 0 | L73: =IF(AND(D73>0,H73>0.000000000001),-(G73+$B$126*F73)/H73,0) -> 0 | M73: =P72 -> 0 | N73: =E73*$B$127 -> 0 | O73: =IF(AND($B$22=1,A73<=$B$20),(M73-D73)*ReturnRate,0) -> 0 | P73: =M73-D73+O73+N73 -> 0 | Q73: =IF(AND($B$22=1,C73>=0,C73<$B$19),1,0) -> 0
A74: 10 | B74: =PlanYear+A74-1 -> 2035 | C74: =A74-1-$B$18 -> 9 | D74: =IF(AND($B$22=1,C74>=0,C74<$B$19),INDEX($Z$46:$Z$55,C74+1),0) -> 0 | E74: =IF(AND($B$22=1,A74<=$B$21),(1+SavInc)^(A74-1),0) -> 0 | F74: =(1+ReturnRate)^(A74-1) -> 1.689479 | G74: =I73-D74 -> 0 | H74: =J73 -> 0 | I74: =G74*(1+ReturnRate) -> 0 | J74: =H74*(1+ReturnRate)+E74 -> 0 | K74: =IF(AND(D74>0,H74<=0.000000000001,G74<0),-G74/F74,0) -> 0 | L74: =IF(AND(D74>0,H74>0.000000000001),-(G74+$B$126*F74)/H74,0) -> 0 | M74: =P73 -> 0 | N74: =E74*$B$127 -> 0 | O74: =IF(AND($B$22=1,A74<=$B$20),(M74-D74)*ReturnRate,0) -> 0 | P74: =M74-D74+O74+N74 -> 0 | Q74: =IF(AND($B$22=1,C74>=0,C74<$B$19),1,0) -> 0
A75: 11 | B75: =PlanYear+A75-1 -> 2036 | C75: =A75-1-$B$18 -> 10 | D75: =IF(AND($B$22=1,C75>=0,C75<$B$19),INDEX($Z$46:$Z$55,C75+1),0) -> 0 | E75: =IF(AND($B$22=1,A75<=$B$21),(1+SavInc)^(A75-1),0) -> 0 | F75: =(1+ReturnRate)^(A75-1) -> 1.7908477 | G75: =I74-D75 -> 0 | H75: =J74 -> 0 | I75: =G75*(1+ReturnRate) -> 0 | J75: =H75*(1+ReturnRate)+E75 -> 0 | K75: =IF(AND(D75>0,H75<=0.000000000001,G75<0),-G75/F75,0) -> 0 | L75: =IF(AND(D75>0,H75>0.000000000001),-(G75+$B$126*F75)/H75,0) -> 0 | M75: =P74 -> 0 | N75: =E75*$B$127 -> 0 | O75: =IF(AND($B$22=1,A75<=$B$20),(M75-D75)*ReturnRate,0) -> 0 | P75: =M75-D75+O75+N75 -> 0 | Q75: =IF(AND($B$22=1,C75>=0,C75<$B$19),1,0) -> 0
A76: 12 | B76: =PlanYear+A76-1 -> 2037 | C76: =A76-1-$B$18 -> 11 | D76: =IF(AND($B$22=1,C76>=0,C76<$B$19),INDEX($Z$46:$Z$55,C76+1),0) -> 0 | E76: =IF(AND($B$22=1,A76<=$B$21),(1+SavInc)^(A76-1),0) -> 0 | F76: =(1+ReturnRate)^(A76-1) -> 1.8982986 | G76: =I75-D76 -> 0 | H76: =J75 -> 0 | I76: =G76*(1+ReturnRate) -> 0 | J76: =H76*(1+ReturnRate)+E76 -> 0 | K76: =IF(AND(D76>0,H76<=0.000000000001,G76<0),-G76/F76,0) -> 0 | L76: =IF(AND(D76>0,H76>0.000000000001),-(G76+$B$126*F76)/H76,0) -> 0 | M76: =P75 -> 0 | N76: =E76*$B$127 -> 0 | O76: =IF(AND($B$22=1,A76<=$B$20),(M76-D76)*ReturnRate,0) -> 0 | P76: =M76-D76+O76+N76 -> 0 | Q76: =IF(AND($B$22=1,C76>=0,C76<$B$19),1,0) -> 0
A77: 13 | B77: =PlanYear+A77-1 -> 2038 | C77: =A77-1-$B$18 -> 12 | D77: =IF(AND($B$22=1,C77>=0,C77<$B$19),INDEX($Z$46:$Z$55,C77+1),0) -> 0 | E77: =IF(AND($B$22=1,A77<=$B$21),(1+SavInc)^(A77-1),0) -> 0 | F77: =(1+ReturnRate)^(A77-1) -> 2.0121965 | G77: =I76-D77 -> 0 | H77: =J76 -> 0 | I77: =G77*(1+ReturnRate) -> 0 | J77: =H77*(1+ReturnRate)+E77 -> 0 | K77: =IF(AND(D77>0,H77<=0.000000000001,G77<0),-G77/F77,0) -> 0 | L77: =IF(AND(D77>0,H77>0.000000000001),-(G77+$B$126*F77)/H77,0) -> 0 | M77: =P76 -> 0 | N77: =E77*$B$127 -> 0 | O77: =IF(AND($B$22=1,A77<=$B$20),(M77-D77)*ReturnRate,0) -> 0 | P77: =M77-D77+O77+N77 -> 0 | Q77: =IF(AND($B$22=1,C77>=0,C77<$B$19),1,0) -> 0
... A124: 60 | B124: =PlanYear+A124-1 -> 2085 | C124: =A124-1-$B$18 -> 59 | D124: =IF(AND($B$22=1,C124>=0,C124<$B$19),INDEX($Z$46:$Z$55,C124+1),0) -> 0 | E124: =IF(AND($B$22=1,A124<=$B$21),(1+SavInc)^(A124-1),0) -> 0 | F124: =(1+ReturnRate)^(A124-1) -> 31.120463 | G124: =I123-D124 -> 0 | H124: =J123 -> 0 | I124: =G124*(1+ReturnRate) -> 0 | J124: =H124*(1+ReturnRate)+E124 -> 0 | K124: =IF(AND(D124>0,H124<=0.000000000001,G124<0),-G124/F124,0) -> 0 | L124: =IF(AND(D124>0,H124>0.000000000001),-(G124+$B$126*F124)/H124,0) -> 0 | M124: =P123 -> 0 | N124: =E124*$B$127 -> 0 | O124: =IF(AND($B$22=1,A124<=$B$20),(M124-D124)*ReturnRate,0) -> 0 | P124: =M124-D124+O124+N124 -> 0 | Q124: =IF(AND($B$22=1,C124>=0,C124<$B$19),1,0) -> 0
A126: Amount needed now | B126: =IF($B$22=1,MAX(K65:K124),0) -> 0
A127: Required yearly saving (first year) | B127: =IF($B$22=1,IF(MAX(0,MAX(L65:L124))<0.000000001,0,MAX(0,MAX(L65:L124))),0) -> 0

Sheet Child 2
A1: Child 2 - cost and savings calculation
A2: All formulas. Change inputs on the Inputs sheet. Amounts in the cost lines table are in the education country's currency; everything else is in the results currency.
A4: Included (1 = yes) | B4: =IF(2<=NumChildren,1,0) -> 0
A5: Education country | B5: =IF(Inputs!$D$17="","",Inputs!$D$17)
A6: Qualification | B6: =IF(Inputs!$D$18="","",Inputs!$D$18)
A7: Current age | B7: =IF(Inputs!$D$15="","",Inputs!$D$15)
A8: College-entry age | B8: =IF(Inputs!$D$19="","",Inputs!$D$19) -> 18
A9: Fee status | B9: =IF($B$5="","",IF(COUNTIF(DomKey,$B$5&"|"&Nationality)>0,"domestic","international"))
A10: Lookup key | B10: =$B$5&"|"&$B$6&"|"&$B$9 -> ||
A11: Cost database row | B11: =IFERROR(MATCH($B$10,DB_Key,0),0) -> 0
A12: Education currency | B12: =IFERROR(INDEX(Ctry_Ccy,MATCH($B$5,Ctry_Name,0)),"USD") -> USD
A13: Course length (years) | B13: =IF($B$11>0,INDEX(DB_Dur,$B$11),0) -> 0
A14: Offered in this country (1/0) | B14: =IF($B$11>0,INDEX(DB_Avail,$B$11),0) -> 0
A15: Pre-stage years | B15: =IF($B$11>0,INDEX(DB_PreYears,$B$11),0) -> 0
A16: Fee increase used | B16: =IF(ISNUMBER(Inputs!$D$20),Inputs!$D$20,IF($B$11>0,INDEX(DB_TInf,$B$11),0)) -> 0
A17: Living-cost increase used | B17: =IF(ISNUMBER(Inputs!$D$21),Inputs!$D$21,IFERROR(INDEX(Ctry_LInf,MATCH($B$5,Ctry_Name,0)),0)) -> 0
A18: Years until college | B18: =IF($B$22=1,MAX(0,$B$8-$B$7),0) -> 0
A19: Study years | B19: =ROUNDUP($B$13,0) -> 0
A20: Plan years | B20: =IF($B$22=1,$B$18+$B$19,0) -> 0
A21: Saving years | B21: =MAX(0,$B$20-1) -> 0
A22: Calculated (1 = yes) | B22: =IF(IFERROR(AND($B$4=1,$B$5<>"",$B$6<>"",$B$14=1,IFERROR(AND(ISNUMBER($B$7),$B$7>=0,$B$7<=18,INT($B$7)=$B$7),FALSE),IFERROR(AND(ISNUMBER($B$8),$B$8>=14,$B$8<=45,INT($B$8)=$B$8),FALSE)),FALSE),1,0) -> 0
A23: Message | B23: =IF($B$4<>1,"",IF(AND($B$7="",$B$5="",$B$6=""),"Enter this child's details on the Inputs sheet.",IF(NOT(IFERROR(AND(ISNUMBER($B$7),$B$7>=0,$B$7<=18,INT($B$7)=$B$7),FALSE)),"Choose the child's current age (0 to 18).",IF(NOT(IFERROR(AND(ISNUMBER($B$8),$B$8>=14,$B$8<=45,INT($B$8)=$B$8),FALSE)),"College-entry age must be a whole number from 14 to 45.",IF($B$5="","Choose the education country.",IF($B$6="","Choose the qualification.",IF($B$14<>1,"This qualification is not offered (or has no typical duration) in the selected country.","")))))))
A24: Exchange rate (education to results currency) | B24: =INDEX(FxUsed,MATCH(RepCcy,FxCodes,0))/INDEX(FxUsed,MATCH($B$12,FxCodes,0)) -> 1
A25: Published fee records used | B25: =IF($B$11=0,0,COUNTIF(RecKey,$B$10)) -> 0
A26: Fee records currency | B26: =IF($B$25>0,INDEX(DB_RecCcy,$B$11),IF($B$11>0,INDEX(DB_EstCcy,$B$11),$B$12)) -> USD
A27: Living costs row | B27: =IFERROR(MATCH($B$5&"|"&$B$9,LivKey,0),0) -> 0
A28: Visa row | B28: =IFERROR(MATCH($B$5&"|"&Nationality,VisaKey,0),0) -> 0
A29: Travel row | B29: =IFERROR(MATCH($B$5&"|"&Residence,TravKey,0),0) -> 0
A31: Cost line | B31: Researched (education currency) | C31: Your figure | D31: Amount used | E31: Price year | F31: Status code | G31: Status | H31: Increase | I31: Timing | J31: Scholarship applies
A32: Tuition | B32: =IF($B$11=0,0,(IF($B$25>0,SUMPRODUCT((RecKey=$B$10)*RecTuition*(1+$B$16)^(PlanYear-RecYear))/$B$25,INDEX(DB_EstTuition,$B$11)))/INDEX(FxUsed,MATCH($B$26,FxCodes,0))*INDEX(FxUsed,MATCH($B$12,FxCodes,0))) -> 0 | C32: =IF(ISNUMBER(Inputs!$D$23),Inputs!$D$23,"") | D32: =IF(ISNUMBER(C32),IF(C32>=0,C32,B32),B32) -> 0 | E32: =IF(ISNUMBER(C32),PlanYear,IF($B$25>0,PlanYear,IF($B$11>0,INDEX(DB_EstBase,$B$11),PlanYear))) -> 2026 | F32: =IF(ISNUMBER(C32),"override",IF($B$11=0,"missing",IF($B$25>0,"verified",INDEX(DB_EstStatus,$B$11)))) -> missing | G32: =IF(F32="verified","Published figure",IF(F32="estimated","Estimated — please review",IF(F32="notNeeded","Not needed",IF(F32="override","Your figure",IF(F32="missing","No figure yet — enter your own",""))))) -> No figure yet — enter your own | H32: tuition | I32: annual | J32: Yes
A33: Accommodation | B33: =IF($B$27=0,0,(INDEX(Liv_accommodation_Amt,$B$27))/INDEX(FxUsed,MATCH(INDEX(Liv_accommodation_Ccy,$B$27),FxCodes,0))*INDEX(FxUsed,MATCH($B$12,FxCodes,0))) -> 0 | C33: =IF(ISNUMBER(Inputs!$D$24),Inputs!$D$24,"") | D33: =IF(ISNUMBER(C33),IF(C33>=0,C33,B33),B33) -> 0 | E33: =IF(ISNUMBER(C33),PlanYear,IF($B$27=0,PlanYear,INDEX(Liv_accommodation_Base,$B$27))) -> 2026 | F33: =IF(ISNUMBER(C33),"override",IF($B$27=0,"missing",INDEX(Liv_accommodation_Status,$B$27))) -> missing | G33: =IF(F33="verified","Published figure",IF(F33="estimated","Estimated — please review",IF(F33="notNeeded","Not needed",IF(F33="override","Your figure",IF(F33="missing","No figure yet — enter your own",""))))) -> No figure yet — enter your own | H33: living | I33: annual | J33: Yes
A34: Food | B34: =IF($B$27=0,0,(INDEX(Liv_food_Amt,$B$27))/INDEX(FxUsed,MATCH(INDEX(Liv_food_Ccy,$B$27),FxCodes,0))*INDEX(FxUsed,MATCH($B$12,FxCodes,0))) -> 0 | C34: =IF(ISNUMBER(Inputs!$D$25),Inputs!$D$25,"") | D34: =IF(ISNUMBER(C34),IF(C34>=0,C34,B34),B34) -> 0 | E34: =IF(ISNUMBER(C34),PlanYear,IF($B$27=0,PlanYear,INDEX(Liv_food_Base,$B$27))) -> 2026 | F34: =IF(ISNUMBER(C34),"override",IF($B$27=0,"missing",INDEX(Liv_food_Status,$B$27))) -> missing | G34: =IF(F34="verified","Published figure",IF(F34="estimated","Estimated — please review",IF(F34="notNeeded","Not needed",IF(F34="override","Your figure",IF(F34="missing","No figure yet — enter your own",""))))) -> No figure yet — enter your own | H34: living | I34: annual | J34: Yes
A35: Local transport | B35: =IF($B$27=0,0,(INDEX(Liv_transport_Amt,$B$27))/INDEX(FxUsed,MATCH(INDEX(Liv_transport_Ccy,$B$27),FxCodes,0))*INDEX(FxUsed,MATCH($B$12,FxCodes,0))) -> 0 | C35: =IF(ISNUMBER(Inputs!$D$26),Inputs!$D$26,"") | D35: =IF(ISNUMBER(C35),IF(C35>=0,C35,B35),B35) -> 0 | E35: =IF(ISNUMBER(C35),PlanYear,IF($B$27=0,PlanYear,INDEX(Liv_transport_Base,$B$27))) -> 2026 | F35: =IF(ISNUMBER(C35),"override",IF($B$27=0,"missing",INDEX(Liv_transport_Status,$B$27))) -> missing | G35: =IF(F35="verified","Published figure",IF(F35="estimated","Estimated — please review",IF(F35="notNeeded","Not needed",IF(F35="override","Your figure",IF(F35="missing","No figure yet — enter your own",""))))) -> No figure yet — enter your own | H35: living | I35: annual | J35: Yes
A36: Health insurance | B36: =IF($B$27=0,0,(INDEX(Liv_healthInsurance_Amt,$B$27))/INDEX(FxUsed,MATCH(INDEX(Liv_healthInsurance_Ccy,$B$27),FxCodes,0))*INDEX(FxUsed,MATCH($B$12,FxCodes,0))) -> 0 | C36: =IF(ISNUMBER(Inputs!$D$27),Inputs!$D$27,"") | D36: =IF(ISNUMBER(C36),IF(C36>=0,C36,B36),B36) -> 0 | E36: =IF(ISNUMBER(C36),PlanYear,IF($B$27=0,PlanYear,INDEX(Liv_healthInsurance_Base,$B$27))) -> 2026 | F36: =IF(ISNUMBER(C36),"override",IF($B$27=0,"missing",INDEX(Liv_healthInsurance_Status,$B$27))) -> missing | G36: =IF(F36="verified","Published figure",IF(F36="estimated","Estimated — please review",IF(F36="notNeeded","Not needed",IF(F36="override","Your figure",IF(F36="missing","No figure yet — enter your own",""))))) -> No figure yet — enter your own | H36: living | I36: annual | J36: Yes
A37: Books and supplies | B37: =IF($B$27=0,0,(INDEX(Liv_books_Amt,$B$27))/INDEX(FxUsed,MATCH(INDEX(Liv_books_Ccy,$B$27),FxCodes,0))*INDEX(FxUsed,MATCH($B$12,FxCodes,0))) -> 0 | C37: =IF(ISNUMBER(Inputs!$D$28),Inputs!$D$28,"") | D37: =IF(ISNUMBER(C37),IF(C37>=0,C37,B37),B37) -> 0 | E37: =IF(ISNUMBER(C37),PlanYear,IF($B$27=0,PlanYear,INDEX(Liv_books_Base,$B$27))) -> 2026 | F37: =IF(ISNUMBER(C37),"override",IF($B$27=0,"missing",INDEX(Liv_books_Status,$B$27))) -> missing | G37: =IF(F37="verified","Published figure",IF(F37="estimated","Estimated — please review",IF(F37="notNeeded","Not needed",IF(F37="override","Your figure",IF(F37="missing","No figure yet — enter your own",""))))) -> No figure yet — enter your own | H37: living | I37: annual | J37: Yes
A38: Other university and course fees | B38: =IF($B$11=0,0,(IF($B$25>0,SUMPRODUCT((RecKey=$B$10)*RecOther*(1+$B$16)^(PlanYear-RecYear))/$B$25,INDEX(DB_EstOther,$B$11)))/INDEX(FxUsed,MATCH($B$26,FxCodes,0))*INDEX(FxUsed,MATCH($B$12,FxCodes,0))) -> 0 | C38: =IF(ISNUMBER(Inputs!$D$29),Inputs!$D$29,"") | D38: =IF(ISNUMBER(C38),IF(C38>=0,C38,B38),B38) -> 0 | E38: =IF(ISNUMBER(C38),PlanYear,IF($B$25>0,PlanYear,IF($B$11>0,INDEX(DB_EstBase,$B$11),PlanYear))) -> 2026 | F38: =IF(ISNUMBER(C38),"override",IF($B$11=0,"missing",IF($B$25>0,"verified",INDEX(DB_EstStatus,$B$11)))) -> missing | G38: =IF(F38="verified","Published figure",IF(F38="estimated","Estimated — please review",IF(F38="notNeeded","Not needed",IF(F38="override","Your figure",IF(F38="missing","No figure yet — enter your own",""))))) -> No figure yet — enter your own | H38: tuition | I38: annual | J38: Yes
A39: Admission and one-time fees | B39: =IF($B$15>0,IF($B$15>0,(INDEX(DB_PreAdm,$B$11))/INDEX(FxUsed,MATCH(INDEX(DB_PreCcy,$B$11),FxCodes,0))*INDEX(FxUsed,MATCH($B$12,FxCodes,0)),0),IF($B$11=0,0,(IF($B$25>0,SUMPRODUCT((RecKey=$B$10)*RecAdm*(1+$B$16)^(PlanYear-RecYear))/$B$25,INDEX(DB_EstAdm,$B$11)))/INDEX(FxUsed,MATCH($B$26,FxCodes,0))*INDEX(FxUsed,MATCH($B$12,FxCodes,0)))) -> 0 | C39: =IF(ISNUMBER(Inputs!$D$30),Inputs!$D$30,"") | D39: =IF(ISNUMBER(C39),IF(C39>=0,C39,B39),B39) -> 0 | E39: =IF(ISNUMBER(C39),PlanYear,IF($B$15>0,INDEX(DB_PreBase,$B$11),IF($B$25>0,PlanYear,IF($B$11>0,INDEX(DB_EstBase,$B$11),PlanYear)))) -> 2026 | F39: =IF(ISNUMBER(C39),"override",IF($B$15>0,INDEX(DB_PreStatus,$B$11),IF($B$11=0,"missing",IF($B$25>0,"verified",INDEX(DB_EstStatus,$B$11))))) -> missing | G39: =IF(F39="verified","Published figure",IF(F39="estimated","Estimated — please review",IF(F39="notNeeded","Not needed",IF(F39="override","Your figure",IF(F39="missing","No figure yet — enter your own",""))))) -> No figure yet — enter your own | H39: tuition | I39: once | J39: Yes
A40: Visa and application | B40: =IF(OR($B$28=0,AND($B$9<>"domestic",Residence=$B$5,COUNTIF(ResNoVisa,$B$5)>0)),0,(INDEX(VisaAmt,$B$28))/INDEX(FxUsed,MATCH(INDEX(VisaCcy,$B$28),FxCodes,0))*INDEX(FxUsed,MATCH($B$12,FxCodes,0))) -> 0 | C40: =IF(ISNUMBER(Inputs!$D$31),Inputs!$D$31,"") | D40: =IF(ISNUMBER(C40),IF(C40>=0,C40,B40),B40) -> 0 | E40: =IF(ISNUMBER(C40),PlanYear,IF(OR($B$28=0,AND($B$9<>"domestic",Residence=$B$5,COUNTIF(ResNoVisa,$B$5)>0)),PlanYear,INDEX(VisaBase,$B$28))) -> 2026 | F40: =IF(ISNUMBER(C40),"override",IF(AND($B$9<>"domestic",Residence=$B$5,COUNTIF(ResNoVisa,$B$5)>0),"notNeeded",IF($B$28=0,"missing",INDEX(VisaStatus,$B$28)))) -> missing | G40: =IF(F40="verified","Published figure",IF(F40="estimated","Estimated — please review",IF(F40="notNeeded","Not needed",IF(F40="override","Your figure",IF(F40="missing","No figure yet — enter your own",""))))) -> No figure yet — enter your own | H40: living | I40: once | J40: No
A41: Travel and relocation | B41: =IF($B$29=0,0,(INDEX(TravAmt,$B$29))/INDEX(FxUsed,MATCH(INDEX(TravCcy,$B$29),FxCodes,0))*INDEX(FxUsed,MATCH($B$12,FxCodes,0))) -> 0 | C41: =IF(ISNUMBER(Inputs!$D$32),Inputs!$D$32,"") | D41: =IF(ISNUMBER(C41),IF(C41>=0,C41,B41),B41) -> 0 | E41: =IF(ISNUMBER(C41),PlanYear,IF($B$29=0,PlanYear,INDEX(TravBase,$B$29))) -> 2026 | F41: =IF(ISNUMBER(C41),"override",IF($B$29=0,"missing",INDEX(TravStatus,$B$29))) -> missing | G41: =IF(F41="verified","Published figure",IF(F41="estimated","Estimated — please review",IF(F41="notNeeded","Not needed",IF(F41="override","Your figure",IF(F41="missing","No figure yet — enter your own",""))))) -> No figure yet — enter your own | H41: living | I41: once | J41: No
A42: Pre-stage tuition (e.g. pre-medical degree) | B42: =IF($B$15>0,(INDEX(DB_PreTuition,$B$11))/INDEX(FxUsed,MATCH(INDEX(DB_PreCcy,$B$11),FxCodes,0))*INDEX(FxUsed,MATCH($B$12,FxCodes,0)),0) -> 0 | C42: =IF(ISNUMBER(Inputs!$D$33),Inputs!$D$33,"") | D42: =IF(ISNUMBER(C42),IF(C42>=0,C42,B42),B42) -> 0 | E42: =IF(ISNUMBER(C42),PlanYear,IF($B$15>0,INDEX(DB_PreBase,$B$11),PlanYear)) -> 2026 | F42: =IF(ISNUMBER(C42),"override",IF($B$15>0,INDEX(DB_PreStatus,$B$11),"")) | G42: =IF(F42="verified","Published figure",IF(F42="estimated","Estimated — please review",IF(F42="notNeeded","Not needed",IF(F42="override","Your figure",IF(F42="missing","No figure yet — enter your own",""))))) | H42: tuition | I42: annual | J42: Yes
A43: Pre-stage other fees | B43: =IF($B$15>0,(INDEX(DB_PreOther,$B$11))/INDEX(FxUsed,MATCH(INDEX(DB_PreCcy,$B$11),FxCodes,0))*INDEX(FxUsed,MATCH($B$12,FxCodes,0)),0) -> 0 | C43: =IF(ISNUMBER(Inputs!$D$34),Inputs!$D$34,"") | D43: =IF(ISNUMBER(C43),IF(C43>=0,C43,B43),B43) -> 0 | E43: =IF(ISNUMBER(C43),PlanYear,IF($B$15>0,INDEX(DB_PreBase,$B$11),PlanYear)) -> 2026 | F43: =IF(ISNUMBER(C43),"override",IF($B$15>0,INDEX(DB_PreStatus,$B$11),"")) | G43: =IF(F43="verified","Published figure",IF(F43="estimated","Estimated — please review",IF(F43="notNeeded","Not needed",IF(F43="override","Your figure",IF(F43="missing","No figure yet — enter your own",""))))) | H43: tuition | I43: annual | J43: Yes
A45: Study year (0 = first) | B45: Calendar year | C45: Fraction of year | D45: In pre-stage (1/0) | E45: In course (1/0) | F45: Tuition (gross) | G45: Accommodation (gross) | H45: Food (gross) | I45: Local transport (gross) | J45: Health insurance (gross) | K45: Books and supplies (gross) | L45: Other university and course fees (gross) | M45: Admission and one-time fees (gross) | N45: Visa and application (gross) | O45: Travel and relocation (gross) | P45: Tuition | Q45: Accommodation | R45: Food | S45: Local transport | T45: Health insurance | U45: Books and supplies | V45: Other university and course fees | W45: Admission and one-time fees | X45: Visa and application | Y45: Travel and relocation | Z45: Education expenses | AA45: Before scholarship
A46: 0 | B46: =PlanYear+$B$18+A46 -> 2026 | C46: =MAX(0,MIN(1,$B$13-A46)) -> 0 | D46: =IF(A46<$B$15,1,0) -> 0 | E46: =IF(AND($B$22=1,A46<$B$19),1,0) -> 0 | F46: =IF(AND(E46=1),IF(D46=1,$D$42,$D$32)*(1+$B$16)^(B46-IF(D46=1,$E$42,$E$32))*C46*$B$24,0) -> 0 | G46: =IF(AND(E46=1),$D$33*(1+$B$17)^(B46-$E$33)*C46*$B$24,0) -> 0 | H46: =IF(AND(E46=1),$D$34*(1+$B$17)^(B46-$E$34)*C46*$B$24,0) -> 0 | I46: =IF(AND(E46=1),$D$35*(1+$B$17)^(B46-$E$35)*C46*$B$24,0) -> 0 | J46: =IF(AND(E46=1),$D$36*(1+$B$17)^(B46-$E$36)*C46*$B$24,0) -> 0 | K46: =IF(AND(E46=1),$D$37*(1+$B$17)^(B46-$E$37)*C46*$B$24,0) -> 0 | L46: =IF(AND(E46=1),IF(D46=1,$D$43,$D$38)*(1+$B$16)^(B46-IF(D46=1,$E$43,$E$38))*C46*$B$24,0) -> 0 | M46: =IF(AND(E46=1,A46=0),$D$39*(1+$B$16)^(B46-$E$39)*$B$24,0) -> 0 | N46: =IF(AND(E46=1,A46=0),$D$40*(1+$B$17)^(B46-$E$40)*$B$24,0) -> 0 | O46: =IF(AND(E46=1,A46=0),$D$41*(1+$B$17)^(B46-$E$41)*$B$24,0) -> 0 | P46: =F46*(1-Coverage) -> 0 | Q46: =G46*(1-Coverage) -> 0 | R46: =H46*(1-Coverage) -> 0 | S46: =I46*(1-Coverage) -> 0 | T46: =J46*(1-Coverage) -> 0 | U46: =K46*(1-Coverage) -> 0 | V46: =L46*(1-Coverage) -> 0 | W46: =M46*(1-Coverage) -> 0 | X46: =N46*1 -> 0 | Y46: =O46*1 -> 0 | Z46: =SUM(P46:Y46) -> 0 | AA46: =SUM(F46:O46) -> 0
A47: 1 | B47: =PlanYear+$B$18+A47 -> 2027 | C47: =MAX(0,MIN(1,$B$13-A47)) -> 0 | D47: =IF(A47<$B$15,1,0) -> 0 | E47: =IF(AND($B$22=1,A47<$B$19),1,0) -> 0 | F47: =IF(AND(E47=1),IF(D47=1,$D$42,$D$32)*(1+$B$16)^(B47-IF(D47=1,$E$42,$E$32))*C47*$B$24,0) -> 0 | G47: =IF(AND(E47=1),$D$33*(1+$B$17)^(B47-$E$33)*C47*$B$24,0) -> 0 | H47: =IF(AND(E47=1),$D$34*(1+$B$17)^(B47-$E$34)*C47*$B$24,0) -> 0 | I47: =IF(AND(E47=1),$D$35*(1+$B$17)^(B47-$E$35)*C47*$B$24,0) -> 0 | J47: =IF(AND(E47=1),$D$36*(1+$B$17)^(B47-$E$36)*C47*$B$24,0) -> 0 | K47: =IF(AND(E47=1),$D$37*(1+$B$17)^(B47-$E$37)*C47*$B$24,0) -> 0 | L47: =IF(AND(E47=1),IF(D47=1,$D$43,$D$38)*(1+$B$16)^(B47-IF(D47=1,$E$43,$E$38))*C47*$B$24,0) -> 0 | M47: =IF(AND(E47=1,A47=0),$D$39*(1+$B$16)^(B47-$E$39)*$B$24,0) -> 0 | N47: =IF(AND(E47=1,A47=0),$D$40*(1+$B$17)^(B47-$E$40)*$B$24,0) -> 0 | O47: =IF(AND(E47=1,A47=0),$D$41*(1+$B$17)^(B47-$E$41)*$B$24,0) -> 0 | P47: =F47*(1-Coverage) -> 0 | Q47: =G47*(1-Coverage) -> 0 | R47: =H47*(1-Coverage) -> 0 | S47: =I47*(1-Coverage) -> 0 | T47: =J47*(1-Coverage) -> 0 | U47: =K47*(1-Coverage) -> 0 | V47: =L47*(1-Coverage) -> 0 | W47: =M47*(1-Coverage) -> 0 | X47: =N47*1 -> 0 | Y47: =O47*1 -> 0 | Z47: =SUM(P47:Y47) -> 0 | AA47: =SUM(F47:O47) -> 0
A48: 2 | B48: =PlanYear+$B$18+A48 -> 2028 | C48: =MAX(0,MIN(1,$B$13-A48)) -> 0 | D48: =IF(A48<$B$15,1,0) -> 0 | E48: =IF(AND($B$22=1,A48<$B$19),1,0) -> 0 | F48: =IF(AND(E48=1),IF(D48=1,$D$42,$D$32)*(1+$B$16)^(B48-IF(D48=1,$E$42,$E$32))*C48*$B$24,0) -> 0 | G48: =IF(AND(E48=1),$D$33*(1+$B$17)^(B48-$E$33)*C48*$B$24,0) -> 0 | H48: =IF(AND(E48=1),$D$34*(1+$B$17)^(B48-$E$34)*C48*$B$24,0) -> 0 | I48: =IF(AND(E48=1),$D$35*(1+$B$17)^(B48-$E$35)*C48*$B$24,0) -> 0 | J48: =IF(AND(E48=1),$D$36*(1+$B$17)^(B48-$E$36)*C48*$B$24,0) -> 0 | K48: =IF(AND(E48=1),$D$37*(1+$B$17)^(B48-$E$37)*C48*$B$24,0) -> 0 | L48: =IF(AND(E48=1),IF(D48=1,$D$43,$D$38)*(1+$B$16)^(B48-IF(D48=1,$E$43,$E$38))*C48*$B$24,0) -> 0 | M48: =IF(AND(E48=1,A48=0),$D$39*(1+$B$16)^(B48-$E$39)*$B$24,0) -> 0 | N48: =IF(AND(E48=1,A48=0),$D$40*(1+$B$17)^(B48-$E$40)*$B$24,0) -> 0 | O48: =IF(AND(E48=1,A48=0),$D$41*(1+$B$17)^(B48-$E$41)*$B$24,0) -> 0 | P48: =F48*(1-Coverage) -> 0 | Q48: =G48*(1-Coverage) -> 0 | R48: =H48*(1-Coverage) -> 0 | S48: =I48*(1-Coverage) -> 0 | T48: =J48*(1-Coverage) -> 0 | U48: =K48*(1-Coverage) -> 0 | V48: =L48*(1-Coverage) -> 0 | W48: =M48*(1-Coverage) -> 0 | X48: =N48*1 -> 0 | Y48: =O48*1 -> 0 | Z48: =SUM(P48:Y48) -> 0 | AA48: =SUM(F48:O48) -> 0
A49: 3 | B49: =PlanYear+$B$18+A49 -> 2029 | C49: =MAX(0,MIN(1,$B$13-A49)) -> 0 | D49: =IF(A49<$B$15,1,0) -> 0 | E49: =IF(AND($B$22=1,A49<$B$19),1,0) -> 0 | F49: =IF(AND(E49=1),IF(D49=1,$D$42,$D$32)*(1+$B$16)^(B49-IF(D49=1,$E$42,$E$32))*C49*$B$24,0) -> 0 | G49: =IF(AND(E49=1),$D$33*(1+$B$17)^(B49-$E$33)*C49*$B$24,0) -> 0 | H49: =IF(AND(E49=1),$D$34*(1+$B$17)^(B49-$E$34)*C49*$B$24,0) -> 0 | I49: =IF(AND(E49=1),$D$35*(1+$B$17)^(B49-$E$35)*C49*$B$24,0) -> 0 | J49: =IF(AND(E49=1),$D$36*(1+$B$17)^(B49-$E$36)*C49*$B$24,0) -> 0 | K49: =IF(AND(E49=1),$D$37*(1+$B$17)^(B49-$E$37)*C49*$B$24,0) -> 0 | L49: =IF(AND(E49=1),IF(D49=1,$D$43,$D$38)*(1+$B$16)^(B49-IF(D49=1,$E$43,$E$38))*C49*$B$24,0) -> 0 | M49: =IF(AND(E49=1,A49=0),$D$39*(1+$B$16)^(B49-$E$39)*$B$24,0) -> 0 | N49: =IF(AND(E49=1,A49=0),$D$40*(1+$B$17)^(B49-$E$40)*$B$24,0) -> 0 | O49: =IF(AND(E49=1,A49=0),$D$41*(1+$B$17)^(B49-$E$41)*$B$24,0) -> 0 | P49: =F49*(1-Coverage) -> 0 | Q49: =G49*(1-Coverage) -> 0 | R49: =H49*(1-Coverage) -> 0 | S49: =I49*(1-Coverage) -> 0 | T49: =J49*(1-Coverage) -> 0 | U49: =K49*(1-Coverage) -> 0 | V49: =L49*(1-Coverage) -> 0 | W49: =M49*(1-Coverage) -> 0 | X49: =N49*1 -> 0 | Y49: =O49*1 -> 0 | Z49: =SUM(P49:Y49) -> 0 | AA49: =SUM(F49:O49) -> 0
A50: 4 | B50: =PlanYear+$B$18+A50 -> 2030 | C50: =MAX(0,MIN(1,$B$13-A50)) -> 0 | D50: =IF(A50<$B$15,1,0) -> 0 | E50: =IF(AND($B$22=1,A50<$B$19),1,0) -> 0 | F50: =IF(AND(E50=1),IF(D50=1,$D$42,$D$32)*(1+$B$16)^(B50-IF(D50=1,$E$42,$E$32))*C50*$B$24,0) -> 0 | G50: =IF(AND(E50=1),$D$33*(1+$B$17)^(B50-$E$33)*C50*$B$24,0) -> 0 | H50: =IF(AND(E50=1),$D$34*(1+$B$17)^(B50-$E$34)*C50*$B$24,0) -> 0 | I50: =IF(AND(E50=1),$D$35*(1+$B$17)^(B50-$E$35)*C50*$B$24,0) -> 0 | J50: =IF(AND(E50=1),$D$36*(1+$B$17)^(B50-$E$36)*C50*$B$24,0) -> 0 | K50: =IF(AND(E50=1),$D$37*(1+$B$17)^(B50-$E$37)*C50*$B$24,0) -> 0 | L50: =IF(AND(E50=1),IF(D50=1,$D$43,$D$38)*(1+$B$16)^(B50-IF(D50=1,$E$43,$E$38))*C50*$B$24,0) -> 0 | M50: =IF(AND(E50=1,A50=0),$D$39*(1+$B$16)^(B50-$E$39)*$B$24,0) -> 0 | N50: =IF(AND(E50=1,A50=0),$D$40*(1+$B$17)^(B50-$E$40)*$B$24,0) -> 0 | O50: =IF(AND(E50=1,A50=0),$D$41*(1+$B$17)^(B50-$E$41)*$B$24,0) -> 0 | P50: =F50*(1-Coverage) -> 0 | Q50: =G50*(1-Coverage) -> 0 | R50: =H50*(1-Coverage) -> 0 | S50: =I50*(1-Coverage) -> 0 | T50: =J50*(1-Coverage) -> 0 | U50: =K50*(1-Coverage) -> 0 | V50: =L50*(1-Coverage) -> 0 | W50: =M50*(1-Coverage) -> 0 | X50: =N50*1 -> 0 | Y50: =O50*1 -> 0 | Z50: =SUM(P50:Y50) -> 0 | AA50: =SUM(F50:O50) -> 0
A51: 5 | B51: =PlanYear+$B$18+A51 -> 2031 | C51: =MAX(0,MIN(1,$B$13-A51)) -> 0 | D51: =IF(A51<$B$15,1,0) -> 0 | E51: =IF(AND($B$22=1,A51<$B$19),1,0) -> 0 | F51: =IF(AND(E51=1),IF(D51=1,$D$42,$D$32)*(1+$B$16)^(B51-IF(D51=1,$E$42,$E$32))*C51*$B$24,0) -> 0 | G51: =IF(AND(E51=1),$D$33*(1+$B$17)^(B51-$E$33)*C51*$B$24,0) -> 0 | H51: =IF(AND(E51=1),$D$34*(1+$B$17)^(B51-$E$34)*C51*$B$24,0) -> 0 | I51: =IF(AND(E51=1),$D$35*(1+$B$17)^(B51-$E$35)*C51*$B$24,0) -> 0 | J51: =IF(AND(E51=1),$D$36*(1+$B$17)^(B51-$E$36)*C51*$B$24,0) -> 0 | K51: =IF(AND(E51=1),$D$37*(1+$B$17)^(B51-$E$37)*C51*$B$24,0) -> 0 | L51: =IF(AND(E51=1),IF(D51=1,$D$43,$D$38)*(1+$B$16)^(B51-IF(D51=1,$E$43,$E$38))*C51*$B$24,0) -> 0 | M51: =IF(AND(E51=1,A51=0),$D$39*(1+$B$16)^(B51-$E$39)*$B$24,0) -> 0 | N51: =IF(AND(E51=1,A51=0),$D$40*(1+$B$17)^(B51-$E$40)*$B$24,0) -> 0 | O51: =IF(AND(E51=1,A51=0),$D$41*(1+$B$17)^(B51-$E$41)*$B$24,0) -> 0 | P51: =F51*(1-Coverage) -> 0 | Q51: =G51*(1-Coverage) -> 0 | R51: =H51*(1-Coverage) -> 0 | S51: =I51*(1-Coverage) -> 0 | T51: =J51*(1-Coverage) -> 0 | U51: =K51*(1-Coverage) -> 0 | V51: =L51*(1-Coverage) -> 0 | W51: =M51*(1-Coverage) -> 0 | X51: =N51*1 -> 0 | Y51: =O51*1 -> 0 | Z51: =SUM(P51:Y51) -> 0 | AA51: =SUM(F51:O51) -> 0
A52: 6 | B52: =PlanYear+$B$18+A52 -> 2032 | C52: =MAX(0,MIN(1,$B$13-A52)) -> 0 | D52: =IF(A52<$B$15,1,0) -> 0 | E52: =IF(AND($B$22=1,A52<$B$19),1,0) -> 0 | F52: =IF(AND(E52=1),IF(D52=1,$D$42,$D$32)*(1+$B$16)^(B52-IF(D52=1,$E$42,$E$32))*C52*$B$24,0) -> 0 | G52: =IF(AND(E52=1),$D$33*(1+$B$17)^(B52-$E$33)*C52*$B$24,0) -> 0 | H52: =IF(AND(E52=1),$D$34*(1+$B$17)^(B52-$E$34)*C52*$B$24,0) -> 0 | I52: =IF(AND(E52=1),$D$35*(1+$B$17)^(B52-$E$35)*C52*$B$24,0) -> 0 | J52: =IF(AND(E52=1),$D$36*(1+$B$17)^(B52-$E$36)*C52*$B$24,0) -> 0 | K52: =IF(AND(E52=1),$D$37*(1+$B$17)^(B52-$E$37)*C52*$B$24,0) -> 0 | L52: =IF(AND(E52=1),IF(D52=1,$D$43,$D$38)*(1+$B$16)^(B52-IF(D52=1,$E$43,$E$38))*C52*$B$24,0) -> 0 | M52: =IF(AND(E52=1,A52=0),$D$39*(1+$B$16)^(B52-$E$39)*$B$24,0) -> 0 | N52: =IF(AND(E52=1,A52=0),$D$40*(1+$B$17)^(B52-$E$40)*$B$24,0) -> 0 | O52: =IF(AND(E52=1,A52=0),$D$41*(1+$B$17)^(B52-$E$41)*$B$24,0) -> 0 | P52: =F52*(1-Coverage) -> 0 | Q52: =G52*(1-Coverage) -> 0 | R52: =H52*(1-Coverage) -> 0 | S52: =I52*(1-Coverage) -> 0 | T52: =J52*(1-Coverage) -> 0 | U52: =K52*(1-Coverage) -> 0 | V52: =L52*(1-Coverage) -> 0 | W52: =M52*(1-Coverage) -> 0 | X52: =N52*1 -> 0 | Y52: =O52*1 -> 0 | Z52: =SUM(P52:Y52) -> 0 | AA52: =SUM(F52:O52) -> 0
A53: 7 | B53: =PlanYear+$B$18+A53 -> 2033 | C53: =MAX(0,MIN(1,$B$13-A53)) -> 0 | D53: =IF(A53<$B$15,1,0) -> 0 | E53: =IF(AND($B$22=1,A53<$B$19),1,0) -> 0 | F53: =IF(AND(E53=1),IF(D53=1,$D$42,$D$32)*(1+$B$16)^(B53-IF(D53=1,$E$42,$E$32))*C53*$B$24,0) -> 0 | G53: =IF(AND(E53=1),$D$33*(1+$B$17)^(B53-$E$33)*C53*$B$24,0) -> 0 | H53: =IF(AND(E53=1),$D$34*(1+$B$17)^(B53-$E$34)*C53*$B$24,0) -> 0 | I53: =IF(AND(E53=1),$D$35*(1+$B$17)^(B53-$E$35)*C53*$B$24,0) -> 0 | J53: =IF(AND(E53=1),$D$36*(1+$B$17)^(B53-$E$36)*C53*$B$24,0) -> 0 | K53: =IF(AND(E53=1),$D$37*(1+$B$17)^(B53-$E$37)*C53*$B$24,0) -> 0 | L53: =IF(AND(E53=1),IF(D53=1,$D$43,$D$38)*(1+$B$16)^(B53-IF(D53=1,$E$43,$E$38))*C53*$B$24,0) -> 0 | M53: =IF(AND(E53=1,A53=0),$D$39*(1+$B$16)^(B53-$E$39)*$B$24,0) -> 0 | N53: =IF(AND(E53=1,A53=0),$D$40*(1+$B$17)^(B53-$E$40)*$B$24,0) -> 0 | O53: =IF(AND(E53=1,A53=0),$D$41*(1+$B$17)^(B53-$E$41)*$B$24,0) -> 0 | P53: =F53*(1-Coverage) -> 0 | Q53: =G53*(1-Coverage) -> 0 | R53: =H53*(1-Coverage) -> 0 | S53: =I53*(1-Coverage) -> 0 | T53: =J53*(1-Coverage) -> 0 | U53: =K53*(1-Coverage) -> 0 | V53: =L53*(1-Coverage) -> 0 | W53: =M53*(1-Coverage) -> 0 | X53: =N53*1 -> 0 | Y53: =O53*1 -> 0 | Z53: =SUM(P53:Y53) -> 0 | AA53: =SUM(F53:O53) -> 0
A54: 8 | B54: =PlanYear+$B$18+A54 -> 2034 | C54: =MAX(0,MIN(1,$B$13-A54)) -> 0 | D54: =IF(A54<$B$15,1,0) -> 0 | E54: =IF(AND($B$22=1,A54<$B$19),1,0) -> 0 | F54: =IF(AND(E54=1),IF(D54=1,$D$42,$D$32)*(1+$B$16)^(B54-IF(D54=1,$E$42,$E$32))*C54*$B$24,0) -> 0 | G54: =IF(AND(E54=1),$D$33*(1+$B$17)^(B54-$E$33)*C54*$B$24,0) -> 0 | H54: =IF(AND(E54=1),$D$34*(1+$B$17)^(B54-$E$34)*C54*$B$24,0) -> 0 | I54: =IF(AND(E54=1),$D$35*(1+$B$17)^(B54-$E$35)*C54*$B$24,0) -> 0 | J54: =IF(AND(E54=1),$D$36*(1+$B$17)^(B54-$E$36)*C54*$B$24,0) -> 0 | K54: =IF(AND(E54=1),$D$37*(1+$B$17)^(B54-$E$37)*C54*$B$24,0) -> 0 | L54: =IF(AND(E54=1),IF(D54=1,$D$43,$D$38)*(1+$B$16)^(B54-IF(D54=1,$E$43,$E$38))*C54*$B$24,0) -> 0 | M54: =IF(AND(E54=1,A54=0),$D$39*(1+$B$16)^(B54-$E$39)*$B$24,0) -> 0 | N54: =IF(AND(E54=1,A54=0),$D$40*(1+$B$17)^(B54-$E$40)*$B$24,0) -> 0 | O54: =IF(AND(E54=1,A54=0),$D$41*(1+$B$17)^(B54-$E$41)*$B$24,0) -> 0 | P54: =F54*(1-Coverage) -> 0 | Q54: =G54*(1-Coverage) -> 0 | R54: =H54*(1-Coverage) -> 0 | S54: =I54*(1-Coverage) -> 0 | T54: =J54*(1-Coverage) -> 0 | U54: =K54*(1-Coverage) -> 0 | V54: =L54*(1-Coverage) -> 0 | W54: =M54*(1-Coverage) -> 0 | X54: =N54*1 -> 0 | Y54: =O54*1 -> 0 | Z54: =SUM(P54:Y54) -> 0 | AA54: =SUM(F54:O54) -> 0
A55: 9 | B55: =PlanYear+$B$18+A55 -> 2035 | C55: =MAX(0,MIN(1,$B$13-A55)) -> 0 | D55: =IF(A55<$B$15,1,0) -> 0 | E55: =IF(AND($B$22=1,A55<$B$19),1,0) -> 0 | F55: =IF(AND(E55=1),IF(D55=1,$D$42,$D$32)*(1+$B$16)^(B55-IF(D55=1,$E$42,$E$32))*C55*$B$24,0) -> 0 | G55: =IF(AND(E55=1),$D$33*(1+$B$17)^(B55-$E$33)*C55*$B$24,0) -> 0 | H55: =IF(AND(E55=1),$D$34*(1+$B$17)^(B55-$E$34)*C55*$B$24,0) -> 0 | I55: =IF(AND(E55=1),$D$35*(1+$B$17)^(B55-$E$35)*C55*$B$24,0) -> 0 | J55: =IF(AND(E55=1),$D$36*(1+$B$17)^(B55-$E$36)*C55*$B$24,0) -> 0 | K55: =IF(AND(E55=1),$D$37*(1+$B$17)^(B55-$E$37)*C55*$B$24,0) -> 0 | L55: =IF(AND(E55=1),IF(D55=1,$D$43,$D$38)*(1+$B$16)^(B55-IF(D55=1,$E$43,$E$38))*C55*$B$24,0) -> 0 | M55: =IF(AND(E55=1,A55=0),$D$39*(1+$B$16)^(B55-$E$39)*$B$24,0) -> 0 | N55: =IF(AND(E55=1,A55=0),$D$40*(1+$B$17)^(B55-$E$40)*$B$24,0) -> 0 | O55: =IF(AND(E55=1,A55=0),$D$41*(1+$B$17)^(B55-$E$41)*$B$24,0) -> 0 | P55: =F55*(1-Coverage) -> 0 | Q55: =G55*(1-Coverage) -> 0 | R55: =H55*(1-Coverage) -> 0 | S55: =I55*(1-Coverage) -> 0 | T55: =J55*(1-Coverage) -> 0 | U55: =K55*(1-Coverage) -> 0 | V55: =L55*(1-Coverage) -> 0 | W55: =M55*(1-Coverage) -> 0 | X55: =N55*1 -> 0 | Y55: =O55*1 -> 0 | Z55: =SUM(P55:Y55) -> 0 | AA55: =SUM(F55:O55) -> 0
A56: Total | F56: =SUM(F46:F55) -> 0 | G56: =SUM(G46:G55) -> 0 | H56: =SUM(H46:H55) -> 0 | I56: =SUM(I46:I55) -> 0 | J56: =SUM(J46:J55) -> 0 | K56: =SUM(K46:K55) -> 0 | L56: =SUM(L46:L55) -> 0 | M56: =SUM(M46:M55) -> 0 | ... AA56: =SUM(AA46:AA55) -> 0
A58: Total estimated education cost (results currency) | B58: =$Z$56 -> 0
A59: Covered by scholarship / part-time work | B59: =$AA$56-$Z$56 -> 0
A60: Tuition figure status | B60: =IF(OR($F$32="missing",AND($B$15>0,$F$42="missing")),"missing",IF(OR($F$32="estimated",AND($B$15>0,$F$42="estimated")),"estimated",IF($B$15>0,$F$42,$F$32))) -> missing
A61: Some costs have no figure (1/0) | B61: =IF(OR($F$32="missing",AND($B$15>0,$F$42="missing"),$F$33="missing"),1,0) -> 1
A63: Savings and yearly fund (results currency). Costs are paid at the start of each year, savings added at the end.
A64: Plan year | B64: Calendar year | C64: Study year | D64: Education expenses | E64: Saving factor | F64: Growth factor | G64: a (no saving) | H64: b (per 1 saved) | I64: A carried | J64: B carried | K64: Needed-now candidate | L64: Saving candidate | M64: Opening fund | N64: Family savings added | O64: Investment growth | P64: Closing fund | Q64: Studying (1/0)
A65: 1 | B65: =PlanYear+A65-1 -> 2026 | C65: =A65-1-$B$18 -> 0 | D65: =IF(AND($B$22=1,C65>=0,C65<$B$19),INDEX($Z$46:$Z$55,C65+1),0) -> 0 | E65: =IF(AND($B$22=1,A65<=$B$21),(1+SavInc)^(A65-1),0) -> 0 | F65: =(1+ReturnRate)^(A65-1) -> 1 | G65: =-D65 -> 0 | H65: =0 -> 0 | I65: =G65*(1+ReturnRate) -> 0 | J65: =H65*(1+ReturnRate)+E65 -> 0 | K65: =IF(AND(D65>0,H65<=0.000000000001,G65<0),-G65/F65,0) -> 0 | L65: =IF(AND(D65>0,H65>0.000000000001),-(G65+$B$126*F65)/H65,0) -> 0 | M65: =$B$126 -> 0 | N65: =E65*$B$127 -> 0 | O65: =IF(AND($B$22=1,A65<=$B$20),(M65-D65)*ReturnRate,0) -> 0 | P65: =M65-D65+O65+N65 -> 0 | Q65: =IF(AND($B$22=1,C65>=0,C65<$B$19),1,0) -> 0
A66: 2 | B66: =PlanYear+A66-1 -> 2027 | C66: =A66-1-$B$18 -> 1 | D66: =IF(AND($B$22=1,C66>=0,C66<$B$19),INDEX($Z$46:$Z$55,C66+1),0) -> 0 | E66: =IF(AND($B$22=1,A66<=$B$21),(1+SavInc)^(A66-1),0) -> 0 | F66: =(1+ReturnRate)^(A66-1) -> 1.06 | G66: =I65-D66 -> 0 | H66: =J65 -> 0 | I66: =G66*(1+ReturnRate) -> 0 | J66: =H66*(1+ReturnRate)+E66 -> 0 | K66: =IF(AND(D66>0,H66<=0.000000000001,G66<0),-G66/F66,0) -> 0 | L66: =IF(AND(D66>0,H66>0.000000000001),-(G66+$B$126*F66)/H66,0) -> 0 | M66: =P65 -> 0 | N66: =E66*$B$127 -> 0 | O66: =IF(AND($B$22=1,A66<=$B$20),(M66-D66)*ReturnRate,0) -> 0 | P66: =M66-D66+O66+N66 -> 0 | Q66: =IF(AND($B$22=1,C66>=0,C66<$B$19),1,0) -> 0
A67: 3 | B67: =PlanYear+A67-1 -> 2028 | C67: =A67-1-$B$18 -> 2 | D67: =IF(AND($B$22=1,C67>=0,C67<$B$19),INDEX($Z$46:$Z$55,C67+1),0) -> 0 | E67: =IF(AND($B$22=1,A67<=$B$21),(1+SavInc)^(A67-1),0) -> 0 | F67: =(1+ReturnRate)^(A67-1) -> 1.1236 | G67: =I66-D67 -> 0 | H67: =J66 -> 0 | I67: =G67*(1+ReturnRate) -> 0 | J67: =H67*(1+ReturnRate)+E67 -> 0 | K67: =IF(AND(D67>0,H67<=0.000000000001,G67<0),-G67/F67,0) -> 0 | L67: =IF(AND(D67>0,H67>0.000000000001),-(G67+$B$126*F67)/H67,0) -> 0 | M67: =P66 -> 0 | N67: =E67*$B$127 -> 0 | O67: =IF(AND($B$22=1,A67<=$B$20),(M67-D67)*ReturnRate,0) -> 0 | P67: =M67-D67+O67+N67 -> 0 | Q67: =IF(AND($B$22=1,C67>=0,C67<$B$19),1,0) -> 0
A68: 4 | B68: =PlanYear+A68-1 -> 2029 | C68: =A68-1-$B$18 -> 3 | D68: =IF(AND($B$22=1,C68>=0,C68<$B$19),INDEX($Z$46:$Z$55,C68+1),0) -> 0 | E68: =IF(AND($B$22=1,A68<=$B$21),(1+SavInc)^(A68-1),0) -> 0 | F68: =(1+ReturnRate)^(A68-1) -> 1.191016 | G68: =I67-D68 -> 0 | H68: =J67 -> 0 | I68: =G68*(1+ReturnRate) -> 0 | J68: =H68*(1+ReturnRate)+E68 -> 0 | K68: =IF(AND(D68>0,H68<=0.000000000001,G68<0),-G68/F68,0) -> 0 | L68: =IF(AND(D68>0,H68>0.000000000001),-(G68+$B$126*F68)/H68,0) -> 0 | M68: =P67 -> 0 | N68: =E68*$B$127 -> 0 | O68: =IF(AND($B$22=1,A68<=$B$20),(M68-D68)*ReturnRate,0) -> 0 | P68: =M68-D68+O68+N68 -> 0 | Q68: =IF(AND($B$22=1,C68>=0,C68<$B$19),1,0) -> 0
A69: 5 | B69: =PlanYear+A69-1 -> 2030 | C69: =A69-1-$B$18 -> 4 | D69: =IF(AND($B$22=1,C69>=0,C69<$B$19),INDEX($Z$46:$Z$55,C69+1),0) -> 0 | E69: =IF(AND($B$22=1,A69<=$B$21),(1+SavInc)^(A69-1),0) -> 0 | F69: =(1+ReturnRate)^(A69-1) -> 1.262477 | G69: =I68-D69 -> 0 | H69: =J68 -> 0 | I69: =G69*(1+ReturnRate) -> 0 | J69: =H69*(1+ReturnRate)+E69 -> 0 | K69: =IF(AND(D69>0,H69<=0.000000000001,G69<0),-G69/F69,0) -> 0 | L69: =IF(AND(D69>0,H69>0.000000000001),-(G69+$B$126*F69)/H69,0) -> 0 | M69: =P68 -> 0 | N69: =E69*$B$127 -> 0 | O69: =IF(AND($B$22=1,A69<=$B$20),(M69-D69)*ReturnRate,0) -> 0 | P69: =M69-D69+O69+N69 -> 0 | Q69: =IF(AND($B$22=1,C69>=0,C69<$B$19),1,0) -> 0
A70: 6 | B70: =PlanYear+A70-1 -> 2031 | C70: =A70-1-$B$18 -> 5 | D70: =IF(AND($B$22=1,C70>=0,C70<$B$19),INDEX($Z$46:$Z$55,C70+1),0) -> 0 | E70: =IF(AND($B$22=1,A70<=$B$21),(1+SavInc)^(A70-1),0) -> 0 | F70: =(1+ReturnRate)^(A70-1) -> 1.3382256 | G70: =I69-D70 -> 0 | H70: =J69 -> 0 | I70: =G70*(1+ReturnRate) -> 0 | J70: =H70*(1+ReturnRate)+E70 -> 0 | K70: =IF(AND(D70>0,H70<=0.000000000001,G70<0),-G70/F70,0) -> 0 | L70: =IF(AND(D70>0,H70>0.000000000001),-(G70+$B$126*F70)/H70,0) -> 0 | M70: =P69 -> 0 | N70: =E70*$B$127 -> 0 | O70: =IF(AND($B$22=1,A70<=$B$20),(M70-D70)*ReturnRate,0) -> 0 | P70: =M70-D70+O70+N70 -> 0 | Q70: =IF(AND($B$22=1,C70>=0,C70<$B$19),1,0) -> 0
A71: 7 | B71: =PlanYear+A71-1 -> 2032 | C71: =A71-1-$B$18 -> 6 | D71: =IF(AND($B$22=1,C71>=0,C71<$B$19),INDEX($Z$46:$Z$55,C71+1),0) -> 0 | E71: =IF(AND($B$22=1,A71<=$B$21),(1+SavInc)^(A71-1),0) -> 0 | F71: =(1+ReturnRate)^(A71-1) -> 1.4185191 | G71: =I70-D71 -> 0 | H71: =J70 -> 0 | I71: =G71*(1+ReturnRate) -> 0 | J71: =H71*(1+ReturnRate)+E71 -> 0 | K71: =IF(AND(D71>0,H71<=0.000000000001,G71<0),-G71/F71,0) -> 0 | L71: =IF(AND(D71>0,H71>0.000000000001),-(G71+$B$126*F71)/H71,0) -> 0 | M71: =P70 -> 0 | N71: =E71*$B$127 -> 0 | O71: =IF(AND($B$22=1,A71<=$B$20),(M71-D71)*ReturnRate,0) -> 0 | P71: =M71-D71+O71+N71 -> 0 | Q71: =IF(AND($B$22=1,C71>=0,C71<$B$19),1,0) -> 0
A72: 8 | B72: =PlanYear+A72-1 -> 2033 | C72: =A72-1-$B$18 -> 7 | D72: =IF(AND($B$22=1,C72>=0,C72<$B$19),INDEX($Z$46:$Z$55,C72+1),0) -> 0 | E72: =IF(AND($B$22=1,A72<=$B$21),(1+SavInc)^(A72-1),0) -> 0 | F72: =(1+ReturnRate)^(A72-1) -> 1.5036303 | G72: =I71-D72 -> 0 | H72: =J71 -> 0 | I72: =G72*(1+ReturnRate) -> 0 | J72: =H72*(1+ReturnRate)+E72 -> 0 | K72: =IF(AND(D72>0,H72<=0.000000000001,G72<0),-G72/F72,0) -> 0 | L72: =IF(AND(D72>0,H72>0.000000000001),-(G72+$B$126*F72)/H72,0) -> 0 | M72: =P71 -> 0 | N72: =E72*$B$127 -> 0 | O72: =IF(AND($B$22=1,A72<=$B$20),(M72-D72)*ReturnRate,0) -> 0 | P72: =M72-D72+O72+N72 -> 0 | Q72: =IF(AND($B$22=1,C72>=0,C72<$B$19),1,0) -> 0
A73: 9 | B73: =PlanYear+A73-1 -> 2034 | C73: =A73-1-$B$18 -> 8 | D73: =IF(AND($B$22=1,C73>=0,C73<$B$19),INDEX($Z$46:$Z$55,C73+1),0) -> 0 | E73: =IF(AND($B$22=1,A73<=$B$21),(1+SavInc)^(A73-1),0) -> 0 | F73: =(1+ReturnRate)^(A73-1) -> 1.5938481 | G73: =I72-D73 -> 0 | H73: =J72 -> 0 | I73: =G73*(1+ReturnRate) -> 0 | J73: =H73*(1+ReturnRate)+E73 -> 0 | K73: =IF(AND(D73>0,H73<=0.000000000001,G73<0),-G73/F73,0) -> 0 | L73: =IF(AND(D73>0,H73>0.000000000001),-(G73+$B$126*F73)/H73,0) -> 0 | M73: =P72 -> 0 | N73: =E73*$B$127 -> 0 | O73: =IF(AND($B$22=1,A73<=$B$20),(M73-D73)*ReturnRate,0) -> 0 | P73: =M73-D73+O73+N73 -> 0 | Q73: =IF(AND($B$22=1,C73>=0,C73<$B$19),1,0) -> 0
A74: 10 | B74: =PlanYear+A74-1 -> 2035 | C74: =A74-1-$B$18 -> 9 | D74: =IF(AND($B$22=1,C74>=0,C74<$B$19),INDEX($Z$46:$Z$55,C74+1),0) -> 0 | E74: =IF(AND($B$22=1,A74<=$B$21),(1+SavInc)^(A74-1),0) -> 0 | F74: =(1+ReturnRate)^(A74-1) -> 1.689479 | G74: =I73-D74 -> 0 | H74: =J73 -> 0 | I74: =G74*(1+ReturnRate) -> 0 | J74: =H74*(1+ReturnRate)+E74 -> 0 | K74: =IF(AND(D74>0,H74<=0.000000000001,G74<0),-G74/F74,0) -> 0 | L74: =IF(AND(D74>0,H74>0.000000000001),-(G74+$B$126*F74)/H74,0) -> 0 | M74: =P73 -> 0 | N74: =E74*$B$127 -> 0 | O74: =IF(AND($B$22=1,A74<=$B$20),(M74-D74)*ReturnRate,0) -> 0 | P74: =M74-D74+O74+N74 -> 0 | Q74: =IF(AND($B$22=1,C74>=0,C74<$B$19),1,0) -> 0
A75: 11 | B75: =PlanYear+A75-1 -> 2036 | C75: =A75-1-$B$18 -> 10 | D75: =IF(AND($B$22=1,C75>=0,C75<$B$19),INDEX($Z$46:$Z$55,C75+1),0) -> 0 | E75: =IF(AND($B$22=1,A75<=$B$21),(1+SavInc)^(A75-1),0) -> 0 | F75: =(1+ReturnRate)^(A75-1) -> 1.7908477 | G75: =I74-D75 -> 0 | H75: =J74 -> 0 | I75: =G75*(1+ReturnRate) -> 0 | J75: =H75*(1+ReturnRate)+E75 -> 0 | K75: =IF(AND(D75>0,H75<=0.000000000001,G75<0),-G75/F75,0) -> 0 | L75: =IF(AND(D75>0,H75>0.000000000001),-(G75+$B$126*F75)/H75,0) -> 0 | M75: =P74 -> 0 | N75: =E75*$B$127 -> 0 | O75: =IF(AND($B$22=1,A75<=$B$20),(M75-D75)*ReturnRate,0) -> 0 | P75: =M75-D75+O75+N75 -> 0 | Q75: =IF(AND($B$22=1,C75>=0,C75<$B$19),1,0) -> 0
A76: 12 | B76: =PlanYear+A76-1 -> 2037 | C76: =A76-1-$B$18 -> 11 | D76: =IF(AND($B$22=1,C76>=0,C76<$B$19),INDEX($Z$46:$Z$55,C76+1),0) -> 0 | E76: =IF(AND($B$22=1,A76<=$B$21),(1+SavInc)^(A76-1),0) -> 0 | F76: =(1+ReturnRate)^(A76-1) -> 1.8982986 | G76: =I75-D76 -> 0 | H76: =J75 -> 0 | I76: =G76*(1+ReturnRate) -> 0 | J76: =H76*(1+ReturnRate)+E76 -> 0 | K76: =IF(AND(D76>0,H76<=0.000000000001,G76<0),-G76/F76,0) -> 0 | L76: =IF(AND(D76>0,H76>0.000000000001),-(G76+$B$126*F76)/H76,0) -> 0 | M76: =P75 -> 0 | N76: =E76*$B$127 -> 0 | O76: =IF(AND($B$22=1,A76<=$B$20),(M76-D76)*ReturnRate,0) -> 0 | P76: =M76-D76+O76+N76 -> 0 | Q76: =IF(AND($B$22=1,C76>=0,C76<$B$19),1,0) -> 0
A77: 13 | B77: =PlanYear+A77-1 -> 2038 | C77: =A77-1-$B$18 -> 12 | D77: =IF(AND($B$22=1,C77>=0,C77<$B$19),INDEX($Z$46:$Z$55,C77+1),0) -> 0 | E77: =IF(AND($B$22=1,A77<=$B$21),(1+SavInc)^(A77-1),0) -> 0 | F77: =(1+ReturnRate)^(A77-1) -> 2.0121965 | G77: =I76-D77 -> 0 | H77: =J76 -> 0 | I77: =G77*(1+ReturnRate) -> 0 | J77: =H77*(1+ReturnRate)+E77 -> 0 | K77: =IF(AND(D77>0,H77<=0.000000000001,G77<0),-G77/F77,0) -> 0 | L77: =IF(AND(D77>0,H77>0.000000000001),-(G77+$B$126*F77)/H77,0) -> 0 | M77: =P76 -> 0 | N77: =E77*$B$127 -> 0 | O77: =IF(AND($B$22=1,A77<=$B$20),(M77-D77)*ReturnRate,0) -> 0 | P77: =M77-D77+O77+N77 -> 0 | Q77: =IF(AND($B$22=1,C77>=0,C77<$B$19),1,0) -> 0
... A124: 60 | B124: =PlanYear+A124-1 -> 2085 | C124: =A124-1-$B$18 -> 59 | D124: =IF(AND($B$22=1,C124>=0,C124<$B$19),INDEX($Z$46:$Z$55,C124+1),0) -> 0 | E124: =IF(AND($B$22=1,A124<=$B$21),(1+SavInc)^(A124-1),0) -> 0 | F124: =(1+ReturnRate)^(A124-1) -> 31.120463 | G124: =I123-D124 -> 0 | H124: =J123 -> 0 | I124: =G124*(1+ReturnRate) -> 0 | J124: =H124*(1+ReturnRate)+E124 -> 0 | K124: =IF(AND(D124>0,H124<=0.000000000001,G124<0),-G124/F124,0) -> 0 | L124: =IF(AND(D124>0,H124>0.000000000001),-(G124+$B$126*F124)/H124,0) -> 0 | M124: =P123 -> 0 | N124: =E124*$B$127 -> 0 | O124: =IF(AND($B$22=1,A124<=$B$20),(M124-D124)*ReturnRate,0) -> 0 | P124: =M124-D124+O124+N124 -> 0 | Q124: =IF(AND($B$22=1,C124>=0,C124<$B$19),1,0) -> 0
A126: Amount needed now | B126: =IF($B$22=1,MAX(K65:K124),0) -> 0
A127: Required yearly saving (first year) | B127: =IF($B$22=1,IF(MAX(0,MAX(L65:L124))<0.000000001,0,MAX(0,MAX(L65:L124))),0) -> 0

Sheet Child 3
A1: Child 3 - cost and savings calculation
A2: All formulas. Change inputs on the Inputs sheet. Amounts in the cost lines table are in the education country's currency; everything else is in the results currency.
A4: Included (1 = yes) | B4: =IF(3<=NumChildren,1,0) -> 0
A5: Education country | B5: =IF(Inputs!$E$17="","",Inputs!$E$17)
A6: Qualification | B6: =IF(Inputs!$E$18="","",Inputs!$E$18)
A7: Current age | B7: =IF(Inputs!$E$15="","",Inputs!$E$15)
A8: College-entry age | B8: =IF(Inputs!$E$19="","",Inputs!$E$19) -> 18
A9: Fee status | B9: =IF($B$5="","",IF(COUNTIF(DomKey,$B$5&"|"&Nationality)>0,"domestic","international"))
A10: Lookup key | B10: =$B$5&"|"&$B$6&"|"&$B$9 -> ||
A11: Cost database row | B11: =IFERROR(MATCH($B$10,DB_Key,0),0) -> 0
A12: Education currency | B12: =IFERROR(INDEX(Ctry_Ccy,MATCH($B$5,Ctry_Name,0)),"USD") -> USD
A13: Course length (years) | B13: =IF($B$11>0,INDEX(DB_Dur,$B$11),0) -> 0
A14: Offered in this country (1/0) | B14: =IF($B$11>0,INDEX(DB_Avail,$B$11),0) -> 0
A15: Pre-stage years | B15: =IF($B$11>0,INDEX(DB_PreYears,$B$11),0) -> 0
A16: Fee increase used | B16: =IF(ISNUMBER(Inputs!$E$20),Inputs!$E$20,IF($B$11>0,INDEX(DB_TInf,$B$11),0)) -> 0
A17: Living-cost increase used | B17: =IF(ISNUMBER(Inputs!$E$21),Inputs!$E$21,IFERROR(INDEX(Ctry_LInf,MATCH($B$5,Ctry_Name,0)),0)) -> 0
A18: Years until college | B18: =IF($B$22=1,MAX(0,$B$8-$B$7),0) -> 0
A19: Study years | B19: =ROUNDUP($B$13,0) -> 0
A20: Plan years | B20: =IF($B$22=1,$B$18+$B$19,0) -> 0
A21: Saving years | B21: =MAX(0,$B$20-1) -> 0
A22: Calculated (1 = yes) | B22: =IF(IFERROR(AND($B$4=1,$B$5<>"",$B$6<>"",$B$14=1,IFERROR(AND(ISNUMBER($B$7),$B$7>=0,$B$7<=18,INT($B$7)=$B$7),FALSE),IFERROR(AND(ISNUMBER($B$8),$B$8>=14,$B$8<=45,INT($B$8)=$B$8),FALSE)),FALSE),1,0) -> 0
A23: Message | B23: =IF($B$4<>1,"",IF(AND($B$7="",$B$5="",$B$6=""),"Enter this child's details on the Inputs sheet.",IF(NOT(IFERROR(AND(ISNUMBER($B$7),$B$7>=0,$B$7<=18,INT($B$7)=$B$7),FALSE)),"Choose the child's current age (0 to 18).",IF(NOT(IFERROR(AND(ISNUMBER($B$8),$B$8>=14,$B$8<=45,INT($B$8)=$B$8),FALSE)),"College-entry age must be a whole number from 14 to 45.",IF($B$5="","Choose the education country.",IF($B$6="","Choose the qualification.",IF($B$14<>1,"This qualification is not offered (or has no typical duration) in the selected country.","")))))))
A24: Exchange rate (education to results currency) | B24: =INDEX(FxUsed,MATCH(RepCcy,FxCodes,0))/INDEX(FxUsed,MATCH($B$12,FxCodes,0)) -> 1
A25: Published fee records used | B25: =IF($B$11=0,0,COUNTIF(RecKey,$B$10)) -> 0
A26: Fee records currency | B26: =IF($B$25>0,INDEX(DB_RecCcy,$B$11),IF($B$11>0,INDEX(DB_EstCcy,$B$11),$B$12)) -> USD
A27: Living costs row | B27: =IFERROR(MATCH($B$5&"|"&$B$9,LivKey,0),0) -> 0
A28: Visa row | B28: =IFERROR(MATCH($B$5&"|"&Nationality,VisaKey,0),0) -> 0
A29: Travel row | B29: =IFERROR(MATCH($B$5&"|"&Residence,TravKey,0),0) -> 0
A31: Cost line | B31: Researched (education currency) | C31: Your figure | D31: Amount used | E31: Price year | F31: Status code | G31: Status | H31: Increase | I31: Timing | J31: Scholarship applies
A32: Tuition | B32: =IF($B$11=0,0,(IF($B$25>0,SUMPRODUCT((RecKey=$B$10)*RecTuition*(1+$B$16)^(PlanYear-RecYear))/$B$25,INDEX(DB_EstTuition,$B$11)))/INDEX(FxUsed,MATCH($B$26,FxCodes,0))*INDEX(FxUsed,MATCH($B$12,FxCodes,0))) -> 0 | C32: =IF(ISNUMBER(Inputs!$E$23),Inputs!$E$23,"") | D32: =IF(ISNUMBER(C32),IF(C32>=0,C32,B32),B32) -> 0 | E32: =IF(ISNUMBER(C32),PlanYear,IF($B$25>0,PlanYear,IF($B$11>0,INDEX(DB_EstBase,$B$11),PlanYear))) -> 2026 | F32: =IF(ISNUMBER(C32),"override",IF($B$11=0,"missing",IF($B$25>0,"verified",INDEX(DB_EstStatus,$B$11)))) -> missing | G32: =IF(F32="verified","Published figure",IF(F32="estimated","Estimated — please review",IF(F32="notNeeded","Not needed",IF(F32="override","Your figure",IF(F32="missing","No figure yet — enter your own",""))))) -> No figure yet — enter your own | H32: tuition | I32: annual | J32: Yes
A33: Accommodation | B33: =IF($B$27=0,0,(INDEX(Liv_accommodation_Amt,$B$27))/INDEX(FxUsed,MATCH(INDEX(Liv_accommodation_Ccy,$B$27),FxCodes,0))*INDEX(FxUsed,MATCH($B$12,FxCodes,0))) -> 0 | C33: =IF(ISNUMBER(Inputs!$E$24),Inputs!$E$24,"") | D33: =IF(ISNUMBER(C33),IF(C33>=0,C33,B33),B33) -> 0 | E33: =IF(ISNUMBER(C33),PlanYear,IF($B$27=0,PlanYear,INDEX(Liv_accommodation_Base,$B$27))) -> 2026 | F33: =IF(ISNUMBER(C33),"override",IF($B$27=0,"missing",INDEX(Liv_accommodation_Status,$B$27))) -> missing | G33: =IF(F33="verified","Published figure",IF(F33="estimated","Estimated — please review",IF(F33="notNeeded","Not needed",IF(F33="override","Your figure",IF(F33="missing","No figure yet — enter your own",""))))) -> No figure yet — enter your own | H33: living | I33: annual | J33: Yes
A34: Food | B34: =IF($B$27=0,0,(INDEX(Liv_food_Amt,$B$27))/INDEX(FxUsed,MATCH(INDEX(Liv_food_Ccy,$B$27),FxCodes,0))*INDEX(FxUsed,MATCH($B$12,FxCodes,0))) -> 0 | C34: =IF(ISNUMBER(Inputs!$E$25),Inputs!$E$25,"") | D34: =IF(ISNUMBER(C34),IF(C34>=0,C34,B34),B34) -> 0 | E34: =IF(ISNUMBER(C34),PlanYear,IF($B$27=0,PlanYear,INDEX(Liv_food_Base,$B$27))) -> 2026 | F34: =IF(ISNUMBER(C34),"override",IF($B$27=0,"missing",INDEX(Liv_food_Status,$B$27))) -> missing | G34: =IF(F34="verified","Published figure",IF(F34="estimated","Estimated — please review",IF(F34="notNeeded","Not needed",IF(F34="override","Your figure",IF(F34="missing","No figure yet — enter your own",""))))) -> No figure yet — enter your own | H34: living | I34: annual | J34: Yes
A35: Local transport | B35: =IF($B$27=0,0,(INDEX(Liv_transport_Amt,$B$27))/INDEX(FxUsed,MATCH(INDEX(Liv_transport_Ccy,$B$27),FxCodes,0))*INDEX(FxUsed,MATCH($B$12,FxCodes,0))) -> 0 | C35: =IF(ISNUMBER(Inputs!$E$26),Inputs!$E$26,"") | D35: =IF(ISNUMBER(C35),IF(C35>=0,C35,B35),B35) -> 0 | E35: =IF(ISNUMBER(C35),PlanYear,IF($B$27=0,PlanYear,INDEX(Liv_transport_Base,$B$27))) -> 2026 | F35: =IF(ISNUMBER(C35),"override",IF($B$27=0,"missing",INDEX(Liv_transport_Status,$B$27))) -> missing | G35: =IF(F35="verified","Published figure",IF(F35="estimated","Estimated — please review",IF(F35="notNeeded","Not needed",IF(F35="override","Your figure",IF(F35="missing","No figure yet — enter your own",""))))) -> No figure yet — enter your own | H35: living | I35: annual | J35: Yes
A36: Health insurance | B36: =IF($B$27=0,0,(INDEX(Liv_healthInsurance_Amt,$B$27))/INDEX(FxUsed,MATCH(INDEX(Liv_healthInsurance_Ccy,$B$27),FxCodes,0))*INDEX(FxUsed,MATCH($B$12,FxCodes,0))) -> 0 | C36: =IF(ISNUMBER(Inputs!$E$27),Inputs!$E$27,"") | D36: =IF(ISNUMBER(C36),IF(C36>=0,C36,B36),B36) -> 0 | E36: =IF(ISNUMBER(C36),PlanYear,IF($B$27=0,PlanYear,INDEX(Liv_healthInsurance_Base,$B$27))) -> 2026 | F36: =IF(ISNUMBER(C36),"override",IF($B$27=0,"missing",INDEX(Liv_healthInsurance_Status,$B$27))) -> missing | G36: =IF(F36="verified","Published figure",IF(F36="estimated","Estimated — please review",IF(F36="notNeeded","Not needed",IF(F36="override","Your figure",IF(F36="missing","No figure yet — enter your own",""))))) -> No figure yet — enter your own | H36: living | I36: annual | J36: Yes
A37: Books and supplies | B37: =IF($B$27=0,0,(INDEX(Liv_books_Amt,$B$27))/INDEX(FxUsed,MATCH(INDEX(Liv_books_Ccy,$B$27),FxCodes,0))*INDEX(FxUsed,MATCH($B$12,FxCodes,0))) -> 0 | C37: =IF(ISNUMBER(Inputs!$E$28),Inputs!$E$28,"") | D37: =IF(ISNUMBER(C37),IF(C37>=0,C37,B37),B37) -> 0 | E37: =IF(ISNUMBER(C37),PlanYear,IF($B$27=0,PlanYear,INDEX(Liv_books_Base,$B$27))) -> 2026 | F37: =IF(ISNUMBER(C37),"override",IF($B$27=0,"missing",INDEX(Liv_books_Status,$B$27))) -> missing | G37: =IF(F37="verified","Published figure",IF(F37="estimated","Estimated — please review",IF(F37="notNeeded","Not needed",IF(F37="override","Your figure",IF(F37="missing","No figure yet — enter your own",""))))) -> No figure yet — enter your own | H37: living | I37: annual | J37: Yes
A38: Other university and course fees | B38: =IF($B$11=0,0,(IF($B$25>0,SUMPRODUCT((RecKey=$B$10)*RecOther*(1+$B$16)^(PlanYear-RecYear))/$B$25,INDEX(DB_EstOther,$B$11)))/INDEX(FxUsed,MATCH($B$26,FxCodes,0))*INDEX(FxUsed,MATCH($B$12,FxCodes,0))) -> 0 | C38: =IF(ISNUMBER(Inputs!$E$29),Inputs!$E$29,"") | D38: =IF(ISNUMBER(C38),IF(C38>=0,C38,B38),B38) -> 0 | E38: =IF(ISNUMBER(C38),PlanYear,IF($B$25>0,PlanYear,IF($B$11>0,INDEX(DB_EstBase,$B$11),PlanYear))) -> 2026 | F38: =IF(ISNUMBER(C38),"override",IF($B$11=0,"missing",IF($B$25>0,"verified",INDEX(DB_EstStatus,$B$11)))) -> missing | G38: =IF(F38="verified","Published figure",IF(F38="estimated","Estimated — please review",IF(F38="notNeeded","Not needed",IF(F38="override","Your figure",IF(F38="missing","No figure yet — enter your own",""))))) -> No figure yet — enter your own | H38: tuition | I38: annual | J38: Yes
A39: Admission and one-time fees | B39: =IF($B$15>0,IF($B$15>0,(INDEX(DB_PreAdm,$B$11))/INDEX(FxUsed,MATCH(INDEX(DB_PreCcy,$B$11),FxCodes,0))*INDEX(FxUsed,MATCH($B$12,FxCodes,0)),0),IF($B$11=0,0,(IF($B$25>0,SUMPRODUCT((RecKey=$B$10)*RecAdm*(1+$B$16)^(PlanYear-RecYear))/$B$25,INDEX(DB_EstAdm,$B$11)))/INDEX(FxUsed,MATCH($B$26,FxCodes,0))*INDEX(FxUsed,MATCH($B$12,FxCodes,0)))) -> 0 | C39: =IF(ISNUMBER(Inputs!$E$30),Inputs!$E$30,"") | D39: =IF(ISNUMBER(C39),IF(C39>=0,C39,B39),B39) -> 0 | E39: =IF(ISNUMBER(C39),PlanYear,IF($B$15>0,INDEX(DB_PreBase,$B$11),IF($B$25>0,PlanYear,IF($B$11>0,INDEX(DB_EstBase,$B$11),PlanYear)))) -> 2026 | F39: =IF(ISNUMBER(C39),"override",IF($B$15>0,INDEX(DB_PreStatus,$B$11),IF($B$11=0,"missing",IF($B$25>0,"verified",INDEX(DB_EstStatus,$B$11))))) -> missing | G39: =IF(F39="verified","Published figure",IF(F39="estimated","Estimated — please review",IF(F39="notNeeded","Not needed",IF(F39="override","Your figure",IF(F39="missing","No figure yet — enter your own",""))))) -> No figure yet — enter your own | H39: tuition | I39: once | J39: Yes
A40: Visa and application | B40: =IF(OR($B$28=0,AND($B$9<>"domestic",Residence=$B$5,COUNTIF(ResNoVisa,$B$5)>0)),0,(INDEX(VisaAmt,$B$28))/INDEX(FxUsed,MATCH(INDEX(VisaCcy,$B$28),FxCodes,0))*INDEX(FxUsed,MATCH($B$12,FxCodes,0))) -> 0 | C40: =IF(ISNUMBER(Inputs!$E$31),Inputs!$E$31,"") | D40: =IF(ISNUMBER(C40),IF(C40>=0,C40,B40),B40) -> 0 | E40: =IF(ISNUMBER(C40),PlanYear,IF(OR($B$28=0,AND($B$9<>"domestic",Residence=$B$5,COUNTIF(ResNoVisa,$B$5)>0)),PlanYear,INDEX(VisaBase,$B$28))) -> 2026 | F40: =IF(ISNUMBER(C40),"override",IF(AND($B$9<>"domestic",Residence=$B$5,COUNTIF(ResNoVisa,$B$5)>0),"notNeeded",IF($B$28=0,"missing",INDEX(VisaStatus,$B$28)))) -> missing | G40: =IF(F40="verified","Published figure",IF(F40="estimated","Estimated — please review",IF(F40="notNeeded","Not needed",IF(F40="override","Your figure",IF(F40="missing","No figure yet — enter your own",""))))) -> No figure yet — enter your own | H40: living | I40: once | J40: No
A41: Travel and relocation | B41: =IF($B$29=0,0,(INDEX(TravAmt,$B$29))/INDEX(FxUsed,MATCH(INDEX(TravCcy,$B$29),FxCodes,0))*INDEX(FxUsed,MATCH($B$12,FxCodes,0))) -> 0 | C41: =IF(ISNUMBER(Inputs!$E$32),Inputs!$E$32,"") | D41: =IF(ISNUMBER(C41),IF(C41>=0,C41,B41),B41) -> 0 | E41: =IF(ISNUMBER(C41),PlanYear,IF($B$29=0,PlanYear,INDEX(TravBase,$B$29))) -> 2026 | F41: =IF(ISNUMBER(C41),"override",IF($B$29=0,"missing",INDEX(TravStatus,$B$29))) -> missing | G41: =IF(F41="verified","Published figure",IF(F41="estimated","Estimated — please review",IF(F41="notNeeded","Not needed",IF(F41="override","Your figure",IF(F41="missing","No figure yet — enter your own",""))))) -> No figure yet — enter your own | H41: living | I41: once | J41: No
A42: Pre-stage tuition (e.g. pre-medical degree) | B42: =IF($B$15>0,(INDEX(DB_PreTuition,$B$11))/INDEX(FxUsed,MATCH(INDEX(DB_PreCcy,$B$11),FxCodes,0))*INDEX(FxUsed,MATCH($B$12,FxCodes,0)),0) -> 0 | C42: =IF(ISNUMBER(Inputs!$E$33),Inputs!$E$33,"") | D42: =IF(ISNUMBER(C42),IF(C42>=0,C42,B42),B42) -> 0 | E42: =IF(ISNUMBER(C42),PlanYear,IF($B$15>0,INDEX(DB_PreBase,$B$11),PlanYear)) -> 2026 | F42: =IF(ISNUMBER(C42),"override",IF($B$15>0,INDEX(DB_PreStatus,$B$11),"")) | G42: =IF(F42="verified","Published figure",IF(F42="estimated","Estimated — please review",IF(F42="notNeeded","Not needed",IF(F42="override","Your figure",IF(F42="missing","No figure yet — enter your own",""))))) | H42: tuition | I42: annual | J42: Yes
A43: Pre-stage other fees | B43: =IF($B$15>0,(INDEX(DB_PreOther,$B$11))/INDEX(FxUsed,MATCH(INDEX(DB_PreCcy,$B$11),FxCodes,0))*INDEX(FxUsed,MATCH($B$12,FxCodes,0)),0) -> 0 | C43: =IF(ISNUMBER(Inputs!$E$34),Inputs!$E$34,"") | D43: =IF(ISNUMBER(C43),IF(C43>=0,C43,B43),B43) -> 0 | E43: =IF(ISNUMBER(C43),PlanYear,IF($B$15>0,INDEX(DB_PreBase,$B$11),PlanYear)) -> 2026 | F43: =IF(ISNUMBER(C43),"override",IF($B$15>0,INDEX(DB_PreStatus,$B$11),"")) | G43: =IF(F43="verified","Published figure",IF(F43="estimated","Estimated — please review",IF(F43="notNeeded","Not needed",IF(F43="override","Your figure",IF(F43="missing","No figure yet — enter your own",""))))) | H43: tuition | I43: annual | J43: Yes
A45: Study year (0 = first) | B45: Calendar year | C45: Fraction of year | D45: In pre-stage (1/0) | E45: In course (1/0) | F45: Tuition (gross) | G45: Accommodation (gross) | H45: Food (gross) | I45: Local transport (gross) | J45: Health insurance (gross) | K45: Books and supplies (gross) | L45: Other university and course fees (gross) | M45: Admission and one-time fees (gross) | N45: Visa and application (gross) | O45: Travel and relocation (gross) | P45: Tuition | Q45: Accommodation | R45: Food | S45: Local transport | T45: Health insurance | U45: Books and supplies | V45: Other university and course fees | W45: Admission and one-time fees | X45: Visa and application | Y45: Travel and relocation | Z45: Education expenses | AA45: Before scholarship
A46: 0 | B46: =PlanYear+$B$18+A46 -> 2026 | C46: =MAX(0,MIN(1,$B$13-A46)) -> 0 | D46: =IF(A46<$B$15,1,0) -> 0 | E46: =IF(AND($B$22=1,A46<$B$19),1,0) -> 0 | F46: =IF(AND(E46=1),IF(D46=1,$D$42,$D$32)*(1+$B$16)^(B46-IF(D46=1,$E$42,$E$32))*C46*$B$24,0) -> 0 | G46: =IF(AND(E46=1),$D$33*(1+$B$17)^(B46-$E$33)*C46*$B$24,0) -> 0 | H46: =IF(AND(E46=1),$D$34*(1+$B$17)^(B46-$E$34)*C46*$B$24,0) -> 0 | I46: =IF(AND(E46=1),$D$35*(1+$B$17)^(B46-$E$35)*C46*$B$24,0) -> 0 | J46: =IF(AND(E46=1),$D$36*(1+$B$17)^(B46-$E$36)*C46*$B$24,0) -> 0 | K46: =IF(AND(E46=1),$D$37*(1+$B$17)^(B46-$E$37)*C46*$B$24,0) -> 0 | L46: =IF(AND(E46=1),IF(D46=1,$D$43,$D$38)*(1+$B$16)^(B46-IF(D46=1,$E$43,$E$38))*C46*$B$24,0) -> 0 | M46: =IF(AND(E46=1,A46=0),$D$39*(1+$B$16)^(B46-$E$39)*$B$24,0) -> 0 | N46: =IF(AND(E46=1,A46=0),$D$40*(1+$B$17)^(B46-$E$40)*$B$24,0) -> 0 | O46: =IF(AND(E46=1,A46=0),$D$41*(1+$B$17)^(B46-$E$41)*$B$24,0) -> 0 | P46: =F46*(1-Coverage) -> 0 | Q46: =G46*(1-Coverage) -> 0 | R46: =H46*(1-Coverage) -> 0 | S46: =I46*(1-Coverage) -> 0 | T46: =J46*(1-Coverage) -> 0 | U46: =K46*(1-Coverage) -> 0 | V46: =L46*(1-Coverage) -> 0 | W46: =M46*(1-Coverage) -> 0 | X46: =N46*1 -> 0 | Y46: =O46*1 -> 0 | Z46: =SUM(P46:Y46) -> 0 | AA46: =SUM(F46:O46) -> 0
A47: 1 | B47: =PlanYear+$B$18+A47 -> 2027 | C47: =MAX(0,MIN(1,$B$13-A47)) -> 0 | D47: =IF(A47<$B$15,1,0) -> 0 | E47: =IF(AND($B$22=1,A47<$B$19),1,0) -> 0 | F47: =IF(AND(E47=1),IF(D47=1,$D$42,$D$32)*(1+$B$16)^(B47-IF(D47=1,$E$42,$E$32))*C47*$B$24,0) -> 0 | G47: =IF(AND(E47=1),$D$33*(1+$B$17)^(B47-$E$33)*C47*$B$24,0) -> 0 | H47: =IF(AND(E47=1),$D$34*(1+$B$17)^(B47-$E$34)*C47*$B$24,0) -> 0 | I47: =IF(AND(E47=1),$D$35*(1+$B$17)^(B47-$E$35)*C47*$B$24,0) -> 0 | J47: =IF(AND(E47=1),$D$36*(1+$B$17)^(B47-$E$36)*C47*$B$24,0) -> 0 | K47: =IF(AND(E47=1),$D$37*(1+$B$17)^(B47-$E$37)*C47*$B$24,0) -> 0 | L47: =IF(AND(E47=1),IF(D47=1,$D$43,$D$38)*(1+$B$16)^(B47-IF(D47=1,$E$43,$E$38))*C47*$B$24,0) -> 0 | M47: =IF(AND(E47=1,A47=0),$D$39*(1+$B$16)^(B47-$E$39)*$B$24,0) -> 0 | N47: =IF(AND(E47=1,A47=0),$D$40*(1+$B$17)^(B47-$E$40)*$B$24,0) -> 0 | O47: =IF(AND(E47=1,A47=0),$D$41*(1+$B$17)^(B47-$E$41)*$B$24,0) -> 0 | P47: =F47*(1-Coverage) -> 0 | Q47: =G47*(1-Coverage) -> 0 | R47: =H47*(1-Coverage) -> 0 | S47: =I47*(1-Coverage) -> 0 | T47: =J47*(1-Coverage) -> 0 | U47: =K47*(1-Coverage) -> 0 | V47: =L47*(1-Coverage) -> 0 | W47: =M47*(1-Coverage) -> 0 | X47: =N47*1 -> 0 | Y47: =O47*1 -> 0 | Z47: =SUM(P47:Y47) -> 0 | AA47: =SUM(F47:O47) -> 0
A48: 2 | B48: =PlanYear+$B$18+A48 -> 2028 | C48: =MAX(0,MIN(1,$B$13-A48)) -> 0 | D48: =IF(A48<$B$15,1,0) -> 0 | E48: =IF(AND($B$22=1,A48<$B$19),1,0) -> 0 | F48: =IF(AND(E48=1),IF(D48=1,$D$42,$D$32)*(1+$B$16)^(B48-IF(D48=1,$E$42,$E$32))*C48*$B$24,0) -> 0 | G48: =IF(AND(E48=1),$D$33*(1+$B$17)^(B48-$E$33)*C48*$B$24,0) -> 0 | H48: =IF(AND(E48=1),$D$34*(1+$B$17)^(B48-$E$34)*C48*$B$24,0) -> 0 | I48: =IF(AND(E48=1),$D$35*(1+$B$17)^(B48-$E$35)*C48*$B$24,0) -> 0 | J48: =IF(AND(E48=1),$D$36*(1+$B$17)^(B48-$E$36)*C48*$B$24,0) -> 0 | K48: =IF(AND(E48=1),$D$37*(1+$B$17)^(B48-$E$37)*C48*$B$24,0) -> 0 | L48: =IF(AND(E48=1),IF(D48=1,$D$43,$D$38)*(1+$B$16)^(B48-IF(D48=1,$E$43,$E$38))*C48*$B$24,0) -> 0 | M48: =IF(AND(E48=1,A48=0),$D$39*(1+$B$16)^(B48-$E$39)*$B$24,0) -> 0 | N48: =IF(AND(E48=1,A48=0),$D$40*(1+$B$17)^(B48-$E$40)*$B$24,0) -> 0 | O48: =IF(AND(E48=1,A48=0),$D$41*(1+$B$17)^(B48-$E$41)*$B$24,0) -> 0 | P48: =F48*(1-Coverage) -> 0 | Q48: =G48*(1-Coverage) -> 0 | R48: =H48*(1-Coverage) -> 0 | S48: =I48*(1-Coverage) -> 0 | T48: =J48*(1-Coverage) -> 0 | U48: =K48*(1-Coverage) -> 0 | V48: =L48*(1-Coverage) -> 0 | W48: =M48*(1-Coverage) -> 0 | X48: =N48*1 -> 0 | Y48: =O48*1 -> 0 | Z48: =SUM(P48:Y48) -> 0 | AA48: =SUM(F48:O48) -> 0
A49: 3 | B49: =PlanYear+$B$18+A49 -> 2029 | C49: =MAX(0,MIN(1,$B$13-A49)) -> 0 | D49: =IF(A49<$B$15,1,0) -> 0 | E49: =IF(AND($B$22=1,A49<$B$19),1,0) -> 0 | F49: =IF(AND(E49=1),IF(D49=1,$D$42,$D$32)*(1+$B$16)^(B49-IF(D49=1,$E$42,$E$32))*C49*$B$24,0) -> 0 | G49: =IF(AND(E49=1),$D$33*(1+$B$17)^(B49-$E$33)*C49*$B$24,0) -> 0 | H49: =IF(AND(E49=1),$D$34*(1+$B$17)^(B49-$E$34)*C49*$B$24,0) -> 0 | I49: =IF(AND(E49=1),$D$35*(1+$B$17)^(B49-$E$35)*C49*$B$24,0) -> 0 | J49: =IF(AND(E49=1),$D$36*(1+$B$17)^(B49-$E$36)*C49*$B$24,0) -> 0 | K49: =IF(AND(E49=1),$D$37*(1+$B$17)^(B49-$E$37)*C49*$B$24,0) -> 0 | L49: =IF(AND(E49=1),IF(D49=1,$D$43,$D$38)*(1+$B$16)^(B49-IF(D49=1,$E$43,$E$38))*C49*$B$24,0) -> 0 | M49: =IF(AND(E49=1,A49=0),$D$39*(1+$B$16)^(B49-$E$39)*$B$24,0) -> 0 | N49: =IF(AND(E49=1,A49=0),$D$40*(1+$B$17)^(B49-$E$40)*$B$24,0) -> 0 | O49: =IF(AND(E49=1,A49=0),$D$41*(1+$B$17)^(B49-$E$41)*$B$24,0) -> 0 | P49: =F49*(1-Coverage) -> 0 | Q49: =G49*(1-Coverage) -> 0 | R49: =H49*(1-Coverage) -> 0 | S49: =I49*(1-Coverage) -> 0 | T49: =J49*(1-Coverage) -> 0 | U49: =K49*(1-Coverage) -> 0 | V49: =L49*(1-Coverage) -> 0 | W49: =M49*(1-Coverage) -> 0 | X49: =N49*1 -> 0 | Y49: =O49*1 -> 0 | Z49: =SUM(P49:Y49) -> 0 | AA49: =SUM(F49:O49) -> 0
A50: 4 | B50: =PlanYear+$B$18+A50 -> 2030 | C50: =MAX(0,MIN(1,$B$13-A50)) -> 0 | D50: =IF(A50<$B$15,1,0) -> 0 | E50: =IF(AND($B$22=1,A50<$B$19),1,0) -> 0 | F50: =IF(AND(E50=1),IF(D50=1,$D$42,$D$32)*(1+$B$16)^(B50-IF(D50=1,$E$42,$E$32))*C50*$B$24,0) -> 0 | G50: =IF(AND(E50=1),$D$33*(1+$B$17)^(B50-$E$33)*C50*$B$24,0) -> 0 | H50: =IF(AND(E50=1),$D$34*(1+$B$17)^(B50-$E$34)*C50*$B$24,0) -> 0 | I50: =IF(AND(E50=1),$D$35*(1+$B$17)^(B50-$E$35)*C50*$B$24,0) -> 0 | J50: =IF(AND(E50=1),$D$36*(1+$B$17)^(B50-$E$36)*C50*$B$24,0) -> 0 | K50: =IF(AND(E50=1),$D$37*(1+$B$17)^(B50-$E$37)*C50*$B$24,0) -> 0 | L50: =IF(AND(E50=1),IF(D50=1,$D$43,$D$38)*(1+$B$16)^(B50-IF(D50=1,$E$43,$E$38))*C50*$B$24,0) -> 0 | M50: =IF(AND(E50=1,A50=0),$D$39*(1+$B$16)^(B50-$E$39)*$B$24,0) -> 0 | N50: =IF(AND(E50=1,A50=0),$D$40*(1+$B$17)^(B50-$E$40)*$B$24,0) -> 0 | O50: =IF(AND(E50=1,A50=0),$D$41*(1+$B$17)^(B50-$E$41)*$B$24,0) -> 0 | P50: =F50*(1-Coverage) -> 0 | Q50: =G50*(1-Coverage) -> 0 | R50: =H50*(1-Coverage) -> 0 | S50: =I50*(1-Coverage) -> 0 | T50: =J50*(1-Coverage) -> 0 | U50: =K50*(1-Coverage) -> 0 | V50: =L50*(1-Coverage) -> 0 | W50: =M50*(1-Coverage) -> 0 | X50: =N50*1 -> 0 | Y50: =O50*1 -> 0 | Z50: =SUM(P50:Y50) -> 0 | AA50: =SUM(F50:O50) -> 0
A51: 5 | B51: =PlanYear+$B$18+A51 -> 2031 | C51: =MAX(0,MIN(1,$B$13-A51)) -> 0 | D51: =IF(A51<$B$15,1,0) -> 0 | E51: =IF(AND($B$22=1,A51<$B$19),1,0) -> 0 | F51: =IF(AND(E51=1),IF(D51=1,$D$42,$D$32)*(1+$B$16)^(B51-IF(D51=1,$E$42,$E$32))*C51*$B$24,0) -> 0 | G51: =IF(AND(E51=1),$D$33*(1+$B$17)^(B51-$E$33)*C51*$B$24,0) -> 0 | H51: =IF(AND(E51=1),$D$34*(1+$B$17)^(B51-$E$34)*C51*$B$24,0) -> 0 | I51: =IF(AND(E51=1),$D$35*(1+$B$17)^(B51-$E$35)*C51*$B$24,0) -> 0 | J51: =IF(AND(E51=1),$D$36*(1+$B$17)^(B51-$E$36)*C51*$B$24,0) -> 0 | K51: =IF(AND(E51=1),$D$37*(1+$B$17)^(B51-$E$37)*C51*$B$24,0) -> 0 | L51: =IF(AND(E51=1),IF(D51=1,$D$43,$D$38)*(1+$B$16)^(B51-IF(D51=1,$E$43,$E$38))*C51*$B$24,0) -> 0 | M51: =IF(AND(E51=1,A51=0),$D$39*(1+$B$16)^(B51-$E$39)*$B$24,0) -> 0 | N51: =IF(AND(E51=1,A51=0),$D$40*(1+$B$17)^(B51-$E$40)*$B$24,0) -> 0 | O51: =IF(AND(E51=1,A51=0),$D$41*(1+$B$17)^(B51-$E$41)*$B$24,0) -> 0 | P51: =F51*(1-Coverage) -> 0 | Q51: =G51*(1-Coverage) -> 0 | R51: =H51*(1-Coverage) -> 0 | S51: =I51*(1-Coverage) -> 0 | T51: =J51*(1-Coverage) -> 0 | U51: =K51*(1-Coverage) -> 0 | V51: =L51*(1-Coverage) -> 0 | W51: =M51*(1-Coverage) -> 0 | X51: =N51*1 -> 0 | Y51: =O51*1 -> 0 | Z51: =SUM(P51:Y51) -> 0 | AA51: =SUM(F51:O51) -> 0
A52: 6 | B52: =PlanYear+$B$18+A52 -> 2032 | C52: =MAX(0,MIN(1,$B$13-A52)) -> 0 | D52: =IF(A52<$B$15,1,0) -> 0 | E52: =IF(AND($B$22=1,A52<$B$19),1,0) -> 0 | F52: =IF(AND(E52=1),IF(D52=1,$D$42,$D$32)*(1+$B$16)^(B52-IF(D52=1,$E$42,$E$32))*C52*$B$24,0) -> 0 | G52: =IF(AND(E52=1),$D$33*(1+$B$17)^(B52-$E$33)*C52*$B$24,0) -> 0 | H52: =IF(AND(E52=1),$D$34*(1+$B$17)^(B52-$E$34)*C52*$B$24,0) -> 0 | I52: =IF(AND(E52=1),$D$35*(1+$B$17)^(B52-$E$35)*C52*$B$24,0) -> 0 | J52: =IF(AND(E52=1),$D$36*(1+$B$17)^(B52-$E$36)*C52*$B$24,0) -> 0 | K52: =IF(AND(E52=1),$D$37*(1+$B$17)^(B52-$E$37)*C52*$B$24,0) -> 0 | L52: =IF(AND(E52=1),IF(D52=1,$D$43,$D$38)*(1+$B$16)^(B52-IF(D52=1,$E$43,$E$38))*C52*$B$24,0) -> 0 | M52: =IF(AND(E52=1,A52=0),$D$39*(1+$B$16)^(B52-$E$39)*$B$24,0) -> 0 | N52: =IF(AND(E52=1,A52=0),$D$40*(1+$B$17)^(B52-$E$40)*$B$24,0) -> 0 | O52: =IF(AND(E52=1,A52=0),$D$41*(1+$B$17)^(B52-$E$41)*$B$24,0) -> 0 | P52: =F52*(1-Coverage) -> 0 | Q52: =G52*(1-Coverage) -> 0 | R52: =H52*(1-Coverage) -> 0 | S52: =I52*(1-Coverage) -> 0 | T52: =J52*(1-Coverage) -> 0 | U52: =K52*(1-Coverage) -> 0 | V52: =L52*(1-Coverage) -> 0 | W52: =M52*(1-Coverage) -> 0 | X52: =N52*1 -> 0 | Y52: =O52*1 -> 0 | Z52: =SUM(P52:Y52) -> 0 | AA52: =SUM(F52:O52) -> 0
A53: 7 | B53: =PlanYear+$B$18+A53 -> 2033 | C53: =MAX(0,MIN(1,$B$13-A53)) -> 0 | D53: =IF(A53<$B$15,1,0) -> 0 | E53: =IF(AND($B$22=1,A53<$B$19),1,0) -> 0 | F53: =IF(AND(E53=1),IF(D53=1,$D$42,$D$32)*(1+$B$16)^(B53-IF(D53=1,$E$42,$E$32))*C53*$B$24,0) -> 0 | G53: =IF(AND(E53=1),$D$33*(1+$B$17)^(B53-$E$33)*C53*$B$24,0) -> 0 | H53: =IF(AND(E53=1),$D$34*(1+$B$17)^(B53-$E$34)*C53*$B$24,0) -> 0 | I53: =IF(AND(E53=1),$D$35*(1+$B$17)^(B53-$E$35)*C53*$B$24,0) -> 0 | J53: =IF(AND(E53=1),$D$36*(1+$B$17)^(B53-$E$36)*C53*$B$24,0) -> 0 | K53: =IF(AND(E53=1),$D$37*(1+$B$17)^(B53-$E$37)*C53*$B$24,0) -> 0 | L53: =IF(AND(E53=1),IF(D53=1,$D$43,$D$38)*(1+$B$16)^(B53-IF(D53=1,$E$43,$E$38))*C53*$B$24,0) -> 0 | M53: =IF(AND(E53=1,A53=0),$D$39*(1+$B$16)^(B53-$E$39)*$B$24,0) -> 0 | N53: =IF(AND(E53=1,A53=0),$D$40*(1+$B$17)^(B53-$E$40)*$B$24,0) -> 0 | O53: =IF(AND(E53=1,A53=0),$D$41*(1+$B$17)^(B53-$E$41)*$B$24,0) -> 0 | P53: =F53*(1-Coverage) -> 0 | Q53: =G53*(1-Coverage) -> 0 | R53: =H53*(1-Coverage) -> 0 | S53: =I53*(1-Coverage) -> 0 | T53: =J53*(1-Coverage) -> 0 | U53: =K53*(1-Coverage) -> 0 | V53: =L53*(1-Coverage) -> 0 | W53: =M53*(1-Coverage) -> 0 | X53: =N53*1 -> 0 | Y53: =O53*1 -> 0 | Z53: =SUM(P53:Y53) -> 0 | AA53: =SUM(F53:O53) -> 0
A54: 8 | B54: =PlanYear+$B$18+A54 -> 2034 | C54: =MAX(0,MIN(1,$B$13-A54)) -> 0 | D54: =IF(A54<$B$15,1,0) -> 0 | E54: =IF(AND($B$22=1,A54<$B$19),1,0) -> 0 | F54: =IF(AND(E54=1),IF(D54=1,$D$42,$D$32)*(1+$B$16)^(B54-IF(D54=1,$E$42,$E$32))*C54*$B$24,0) -> 0 | G54: =IF(AND(E54=1),$D$33*(1+$B$17)^(B54-$E$33)*C54*$B$24,0) -> 0 | H54: =IF(AND(E54=1),$D$34*(1+$B$17)^(B54-$E$34)*C54*$B$24,0) -> 0 | I54: =IF(AND(E54=1),$D$35*(1+$B$17)^(B54-$E$35)*C54*$B$24,0) -> 0 | J54: =IF(AND(E54=1),$D$36*(1+$B$17)^(B54-$E$36)*C54*$B$24,0) -> 0 | K54: =IF(AND(E54=1),$D$37*(1+$B$17)^(B54-$E$37)*C54*$B$24,0) -> 0 | L54: =IF(AND(E54=1),IF(D54=1,$D$43,$D$38)*(1+$B$16)^(B54-IF(D54=1,$E$43,$E$38))*C54*$B$24,0) -> 0 | M54: =IF(AND(E54=1,A54=0),$D$39*(1+$B$16)^(B54-$E$39)*$B$24,0) -> 0 | N54: =IF(AND(E54=1,A54=0),$D$40*(1+$B$17)^(B54-$E$40)*$B$24,0) -> 0 | O54: =IF(AND(E54=1,A54=0),$D$41*(1+$B$17)^(B54-$E$41)*$B$24,0) -> 0 | P54: =F54*(1-Coverage) -> 0 | Q54: =G54*(1-Coverage) -> 0 | R54: =H54*(1-Coverage) -> 0 | S54: =I54*(1-Coverage) -> 0 | T54: =J54*(1-Coverage) -> 0 | U54: =K54*(1-Coverage) -> 0 | V54: =L54*(1-Coverage) -> 0 | W54: =M54*(1-Coverage) -> 0 | X54: =N54*1 -> 0 | Y54: =O54*1 -> 0 | Z54: =SUM(P54:Y54) -> 0 | AA54: =SUM(F54:O54) -> 0
A55: 9 | B55: =PlanYear+$B$18+A55 -> 2035 | C55: =MAX(0,MIN(1,$B$13-A55)) -> 0 | D55: =IF(A55<$B$15,1,0) -> 0 | E55: =IF(AND($B$22=1,A55<$B$19),1,0) -> 0 | F55: =IF(AND(E55=1),IF(D55=1,$D$42,$D$32)*(1+$B$16)^(B55-IF(D55=1,$E$42,$E$32))*C55*$B$24,0) -> 0 | G55: =IF(AND(E55=1),$D$33*(1+$B$17)^(B55-$E$33)*C55*$B$24,0) -> 0 | H55: =IF(AND(E55=1),$D$34*(1+$B$17)^(B55-$E$34)*C55*$B$24,0) -> 0 | I55: =IF(AND(E55=1),$D$35*(1+$B$17)^(B55-$E$35)*C55*$B$24,0) -> 0 | J55: =IF(AND(E55=1),$D$36*(1+$B$17)^(B55-$E$36)*C55*$B$24,0) -> 0 | K55: =IF(AND(E55=1),$D$37*(1+$B$17)^(B55-$E$37)*C55*$B$24,0) -> 0 | L55: =IF(AND(E55=1),IF(D55=1,$D$43,$D$38)*(1+$B$16)^(B55-IF(D55=1,$E$43,$E$38))*C55*$B$24,0) -> 0 | M55: =IF(AND(E55=1,A55=0),$D$39*(1+$B$16)^(B55-$E$39)*$B$24,0) -> 0 | N55: =IF(AND(E55=1,A55=0),$D$40*(1+$B$17)^(B55-$E$40)*$B$24,0) -> 0 | O55: =IF(AND(E55=1,A55=0),$D$41*(1+$B$17)^(B55-$E$41)*$B$24,0) -> 0 | P55: =F55*(1-Coverage) -> 0 | Q55: =G55*(1-Coverage) -> 0 | R55: =H55*(1-Coverage) -> 0 | S55: =I55*(1-Coverage) -> 0 | T55: =J55*(1-Coverage) -> 0 | U55: =K55*(1-Coverage) -> 0 | V55: =L55*(1-Coverage) -> 0 | W55: =M55*(1-Coverage) -> 0 | X55: =N55*1 -> 0 | Y55: =O55*1 -> 0 | Z55: =SUM(P55:Y55) -> 0 | AA55: =SUM(F55:O55) -> 0
A56: Total | F56: =SUM(F46:F55) -> 0 | G56: =SUM(G46:G55) -> 0 | H56: =SUM(H46:H55) -> 0 | I56: =SUM(I46:I55) -> 0 | J56: =SUM(J46:J55) -> 0 | K56: =SUM(K46:K55) -> 0 | L56: =SUM(L46:L55) -> 0 | M56: =SUM(M46:M55) -> 0 | ... AA56: =SUM(AA46:AA55) -> 0
A58: Total estimated education cost (results currency) | B58: =$Z$56 -> 0
A59: Covered by scholarship / part-time work | B59: =$AA$56-$Z$56 -> 0
A60: Tuition figure status | B60: =IF(OR($F$32="missing",AND($B$15>0,$F$42="missing")),"missing",IF(OR($F$32="estimated",AND($B$15>0,$F$42="estimated")),"estimated",IF($B$15>0,$F$42,$F$32))) -> missing
A61: Some costs have no figure (1/0) | B61: =IF(OR($F$32="missing",AND($B$15>0,$F$42="missing"),$F$33="missing"),1,0) -> 1
A63: Savings and yearly fund (results currency). Costs are paid at the start of each year, savings added at the end.
A64: Plan year | B64: Calendar year | C64: Study year | D64: Education expenses | E64: Saving factor | F64: Growth factor | G64: a (no saving) | H64: b (per 1 saved) | I64: A carried | J64: B carried | K64: Needed-now candidate | L64: Saving candidate | M64: Opening fund | N64: Family savings added | O64: Investment growth | P64: Closing fund | Q64: Studying (1/0)
A65: 1 | B65: =PlanYear+A65-1 -> 2026 | C65: =A65-1-$B$18 -> 0 | D65: =IF(AND($B$22=1,C65>=0,C65<$B$19),INDEX($Z$46:$Z$55,C65+1),0) -> 0 | E65: =IF(AND($B$22=1,A65<=$B$21),(1+SavInc)^(A65-1),0) -> 0 | F65: =(1+ReturnRate)^(A65-1) -> 1 | G65: =-D65 -> 0 | H65: =0 -> 0 | I65: =G65*(1+ReturnRate) -> 0 | J65: =H65*(1+ReturnRate)+E65 -> 0 | K65: =IF(AND(D65>0,H65<=0.000000000001,G65<0),-G65/F65,0) -> 0 | L65: =IF(AND(D65>0,H65>0.000000000001),-(G65+$B$126*F65)/H65,0) -> 0 | M65: =$B$126 -> 0 | N65: =E65*$B$127 -> 0 | O65: =IF(AND($B$22=1,A65<=$B$20),(M65-D65)*ReturnRate,0) -> 0 | P65: =M65-D65+O65+N65 -> 0 | Q65: =IF(AND($B$22=1,C65>=0,C65<$B$19),1,0) -> 0
A66: 2 | B66: =PlanYear+A66-1 -> 2027 | C66: =A66-1-$B$18 -> 1 | D66: =IF(AND($B$22=1,C66>=0,C66<$B$19),INDEX($Z$46:$Z$55,C66+1),0) -> 0 | E66: =IF(AND($B$22=1,A66<=$B$21),(1+SavInc)^(A66-1),0) -> 0 | F66: =(1+ReturnRate)^(A66-1) -> 1.06 | G66: =I65-D66 -> 0 | H66: =J65 -> 0 | I66: =G66*(1+ReturnRate) -> 0 | J66: =H66*(1+ReturnRate)+E66 -> 0 | K66: =IF(AND(D66>0,H66<=0.000000000001,G66<0),-G66/F66,0) -> 0 | L66: =IF(AND(D66>0,H66>0.000000000001),-(G66+$B$126*F66)/H66,0) -> 0 | M66: =P65 -> 0 | N66: =E66*$B$127 -> 0 | O66: =IF(AND($B$22=1,A66<=$B$20),(M66-D66)*ReturnRate,0) -> 0 | P66: =M66-D66+O66+N66 -> 0 | Q66: =IF(AND($B$22=1,C66>=0,C66<$B$19),1,0) -> 0
A67: 3 | B67: =PlanYear+A67-1 -> 2028 | C67: =A67-1-$B$18 -> 2 | D67: =IF(AND($B$22=1,C67>=0,C67<$B$19),INDEX($Z$46:$Z$55,C67+1),0) -> 0 | E67: =IF(AND($B$22=1,A67<=$B$21),(1+SavInc)^(A67-1),0) -> 0 | F67: =(1+ReturnRate)^(A67-1) -> 1.1236 | G67: =I66-D67 -> 0 | H67: =J66 -> 0 | I67: =G67*(1+ReturnRate) -> 0 | J67: =H67*(1+ReturnRate)+E67 -> 0 | K67: =IF(AND(D67>0,H67<=0.000000000001,G67<0),-G67/F67,0) -> 0 | L67: =IF(AND(D67>0,H67>0.000000000001),-(G67+$B$126*F67)/H67,0) -> 0 | M67: =P66 -> 0 | N67: =E67*$B$127 -> 0 | O67: =IF(AND($B$22=1,A67<=$B$20),(M67-D67)*ReturnRate,0) -> 0 | P67: =M67-D67+O67+N67 -> 0 | Q67: =IF(AND($B$22=1,C67>=0,C67<$B$19),1,0) -> 0
A68: 4 | B68: =PlanYear+A68-1 -> 2029 | C68: =A68-1-$B$18 -> 3 | D68: =IF(AND($B$22=1,C68>=0,C68<$B$19),INDEX($Z$46:$Z$55,C68+1),0) -> 0 | E68: =IF(AND($B$22=1,A68<=$B$21),(1+SavInc)^(A68-1),0) -> 0 | F68: =(1+ReturnRate)^(A68-1) -> 1.191016 | G68: =I67-D68 -> 0 | H68: =J67 -> 0 | I68: =G68*(1+ReturnRate) -> 0 | J68: =H68*(1+ReturnRate)+E68 -> 0 | K68: =IF(AND(D68>0,H68<=0.000000000001,G68<0),-G68/F68,0) -> 0 | L68: =IF(AND(D68>0,H68>0.000000000001),-(G68+$B$126*F68)/H68,0) -> 0 | M68: =P67 -> 0 | N68: =E68*$B$127 -> 0 | O68: =IF(AND($B$22=1,A68<=$B$20),(M68-D68)*ReturnRate,0) -> 0 | P68: =M68-D68+O68+N68 -> 0 | Q68: =IF(AND($B$22=1,C68>=0,C68<$B$19),1,0) -> 0
A69: 5 | B69: =PlanYear+A69-1 -> 2030 | C69: =A69-1-$B$18 -> 4 | D69: =IF(AND($B$22=1,C69>=0,C69<$B$19),INDEX($Z$46:$Z$55,C69+1),0) -> 0 | E69: =IF(AND($B$22=1,A69<=$B$21),(1+SavInc)^(A69-1),0) -> 0 | F69: =(1+ReturnRate)^(A69-1) -> 1.262477 | G69: =I68-D69 -> 0 | H69: =J68 -> 0 | I69: =G69*(1+ReturnRate) -> 0 | J69: =H69*(1+ReturnRate)+E69 -> 0 | K69: =IF(AND(D69>0,H69<=0.000000000001,G69<0),-G69/F69,0) -> 0 | L69: =IF(AND(D69>0,H69>0.000000000001),-(G69+$B$126*F69)/H69,0) -> 0 | M69: =P68 -> 0 | N69: =E69*$B$127 -> 0 | O69: =IF(AND($B$22=1,A69<=$B$20),(M69-D69)*ReturnRate,0) -> 0 | P69: =M69-D69+O69+N69 -> 0 | Q69: =IF(AND($B$22=1,C69>=0,C69<$B$19),1,0) -> 0
A70: 6 | B70: =PlanYear+A70-1 -> 2031 | C70: =A70-1-$B$18 -> 5 | D70: =IF(AND($B$22=1,C70>=0,C70<$B$19),INDEX($Z$46:$Z$55,C70+1),0) -> 0 | E70: =IF(AND($B$22=1,A70<=$B$21),(1+SavInc)^(A70-1),0) -> 0 | F70: =(1+ReturnRate)^(A70-1) -> 1.3382256 | G70: =I69-D70 -> 0 | H70: =J69 -> 0 | I70: =G70*(1+ReturnRate) -> 0 | J70: =H70*(1+ReturnRate)+E70 -> 0 | K70: =IF(AND(D70>0,H70<=0.000000000001,G70<0),-G70/F70,0) -> 0 | L70: =IF(AND(D70>0,H70>0.000000000001),-(G70+$B$126*F70)/H70,0) -> 0 | M70: =P69 -> 0 | N70: =E70*$B$127 -> 0 | O70: =IF(AND($B$22=1,A70<=$B$20),(M70-D70)*ReturnRate,0) -> 0 | P70: =M70-D70+O70+N70 -> 0 | Q70: =IF(AND($B$22=1,C70>=0,C70<$B$19),1,0) -> 0
A71: 7 | B71: =PlanYear+A71-1 -> 2032 | C71: =A71-1-$B$18 -> 6 | D71: =IF(AND($B$22=1,C71>=0,C71<$B$19),INDEX($Z$46:$Z$55,C71+1),0) -> 0 | E71: =IF(AND($B$22=1,A71<=$B$21),(1+SavInc)^(A71-1),0) -> 0 | F71: =(1+ReturnRate)^(A71-1) -> 1.4185191 | G71: =I70-D71 -> 0 | H71: =J70 -> 0 | I71: =G71*(1+ReturnRate) -> 0 | J71: =H71*(1+ReturnRate)+E71 -> 0 | K71: =IF(AND(D71>0,H71<=0.000000000001,G71<0),-G71/F71,0) -> 0 | L71: =IF(AND(D71>0,H71>0.000000000001),-(G71+$B$126*F71)/H71,0) -> 0 | M71: =P70 -> 0 | N71: =E71*$B$127 -> 0 | O71: =IF(AND($B$22=1,A71<=$B$20),(M71-D71)*ReturnRate,0) -> 0 | P71: =M71-D71+O71+N71 -> 0 | Q71: =IF(AND($B$22=1,C71>=0,C71<$B$19),1,0) -> 0
A72: 8 | B72: =PlanYear+A72-1 -> 2033 | C72: =A72-1-$B$18 -> 7 | D72: =IF(AND($B$22=1,C72>=0,C72<$B$19),INDEX($Z$46:$Z$55,C72+1),0) -> 0 | E72: =IF(AND($B$22=1,A72<=$B$21),(1+SavInc)^(A72-1),0) -> 0 | F72: =(1+ReturnRate)^(A72-1) -> 1.5036303 | G72: =I71-D72 -> 0 | H72: =J71 -> 0 | I72: =G72*(1+ReturnRate) -> 0 | J72: =H72*(1+ReturnRate)+E72 -> 0 | K72: =IF(AND(D72>0,H72<=0.000000000001,G72<0),-G72/F72,0) -> 0 | L72: =IF(AND(D72>0,H72>0.000000000001),-(G72+$B$126*F72)/H72,0) -> 0 | M72: =P71 -> 0 | N72: =E72*$B$127 -> 0 | O72: =IF(AND($B$22=1,A72<=$B$20),(M72-D72)*ReturnRate,0) -> 0 | P72: =M72-D72+O72+N72 -> 0 | Q72: =IF(AND($B$22=1,C72>=0,C72<$B$19),1,0) -> 0
A73: 9 | B73: =PlanYear+A73-1 -> 2034 | C73: =A73-1-$B$18 -> 8 | D73: =IF(AND($B$22=1,C73>=0,C73<$B$19),INDEX($Z$46:$Z$55,C73+1),0) -> 0 | E73: =IF(AND($B$22=1,A73<=$B$21),(1+SavInc)^(A73-1),0) -> 0 | F73: =(1+ReturnRate)^(A73-1) -> 1.5938481 | G73: =I72-D73 -> 0 | H73: =J72 -> 0 | I73: =G73*(1+ReturnRate) -> 0 | J73: =H73*(1+ReturnRate)+E73 -> 0 | K73: =IF(AND(D73>0,H73<=0.000000000001,G73<0),-G73/F73,0) -> 0 | L73: =IF(AND(D73>0,H73>0.000000000001),-(G73+$B$126*F73)/H73,0) -> 0 | M73: =P72 -> 0 | N73: =E73*$B$127 -> 0 | O73: =IF(AND($B$22=1,A73<=$B$20),(M73-D73)*ReturnRate,0) -> 0 | P73: =M73-D73+O73+N73 -> 0 | Q73: =IF(AND($B$22=1,C73>=0,C73<$B$19),1,0) -> 0
A74: 10 | B74: =PlanYear+A74-1 -> 2035 | C74: =A74-1-$B$18 -> 9 | D74: =IF(AND($B$22=1,C74>=0,C74<$B$19),INDEX($Z$46:$Z$55,C74+1),0) -> 0 | E74: =IF(AND($B$22=1,A74<=$B$21),(1+SavInc)^(A74-1),0) -> 0 | F74: =(1+ReturnRate)^(A74-1) -> 1.689479 | G74: =I73-D74 -> 0 | H74: =J73 -> 0 | I74: =G74*(1+ReturnRate) -> 0 | J74: =H74*(1+ReturnRate)+E74 -> 0 | K74: =IF(AND(D74>0,H74<=0.000000000001,G74<0),-G74/F74,0) -> 0 | L74: =IF(AND(D74>0,H74>0.000000000001),-(G74+$B$126*F74)/H74,0) -> 0 | M74: =P73 -> 0 | N74: =E74*$B$127 -> 0 | O74: =IF(AND($B$22=1,A74<=$B$20),(M74-D74)*ReturnRate,0) -> 0 | P74: =M74-D74+O74+N74 -> 0 | Q74: =IF(AND($B$22=1,C74>=0,C74<$B$19),1,0) -> 0
A75: 11 | B75: =PlanYear+A75-1 -> 2036 | C75: =A75-1-$B$18 -> 10 | D75: =IF(AND($B$22=1,C75>=0,C75<$B$19),INDEX($Z$46:$Z$55,C75+1),0) -> 0 | E75: =IF(AND($B$22=1,A75<=$B$21),(1+SavInc)^(A75-1),0) -> 0 | F75: =(1+ReturnRate)^(A75-1) -> 1.7908477 | G75: =I74-D75 -> 0 | H75: =J74 -> 0 | I75: =G75*(1+ReturnRate) -> 0 | J75: =H75*(1+ReturnRate)+E75 -> 0 | K75: =IF(AND(D75>0,H75<=0.000000000001,G75<0),-G75/F75,0) -> 0 | L75: =IF(AND(D75>0,H75>0.000000000001),-(G75+$B$126*F75)/H75,0) -> 0 | M75: =P74 -> 0 | N75: =E75*$B$127 -> 0 | O75: =IF(AND($B$22=1,A75<=$B$20),(M75-D75)*ReturnRate,0) -> 0 | P75: =M75-D75+O75+N75 -> 0 | Q75: =IF(AND($B$22=1,C75>=0,C75<$B$19),1,0) -> 0
A76: 12 | B76: =PlanYear+A76-1 -> 2037 | C76: =A76-1-$B$18 -> 11 | D76: =IF(AND($B$22=1,C76>=0,C76<$B$19),INDEX($Z$46:$Z$55,C76+1),0) -> 0 | E76: =IF(AND($B$22=1,A76<=$B$21),(1+SavInc)^(A76-1),0) -> 0 | F76: =(1+ReturnRate)^(A76-1) -> 1.8982986 | G76: =I75-D76 -> 0 | H76: =J75 -> 0 | I76: =G76*(1+ReturnRate) -> 0 | J76: =H76*(1+ReturnRate)+E76 -> 0 | K76: =IF(AND(D76>0,H76<=0.000000000001,G76<0),-G76/F76,0) -> 0 | L76: =IF(AND(D76>0,H76>0.000000000001),-(G76+$B$126*F76)/H76,0) -> 0 | M76: =P75 -> 0 | N76: =E76*$B$127 -> 0 | O76: =IF(AND($B$22=1,A76<=$B$20),(M76-D76)*ReturnRate,0) -> 0 | P76: =M76-D76+O76+N76 -> 0 | Q76: =IF(AND($B$22=1,C76>=0,C76<$B$19),1,0) -> 0
A77: 13 | B77: =PlanYear+A77-1 -> 2038 | C77: =A77-1-$B$18 -> 12 | D77: =IF(AND($B$22=1,C77>=0,C77<$B$19),INDEX($Z$46:$Z$55,C77+1),0) -> 0 | E77: =IF(AND($B$22=1,A77<=$B$21),(1+SavInc)^(A77-1),0) -> 0 | F77: =(1+ReturnRate)^(A77-1) -> 2.0121965 | G77: =I76-D77 -> 0 | H77: =J76 -> 0 | I77: =G77*(1+ReturnRate) -> 0 | J77: =H77*(1+ReturnRate)+E77 -> 0 | K77: =IF(AND(D77>0,H77<=0.000000000001,G77<0),-G77/F77,0) -> 0 | L77: =IF(AND(D77>0,H77>0.000000000001),-(G77+$B$126*F77)/H77,0) -> 0 | M77: =P76 -> 0 | N77: =E77*$B$127 -> 0 | O77: =IF(AND($B$22=1,A77<=$B$20),(M77-D77)*ReturnRate,0) -> 0 | P77: =M77-D77+O77+N77 -> 0 | Q77: =IF(AND($B$22=1,C77>=0,C77<$B$19),1,0) -> 0
... A124: 60 | B124: =PlanYear+A124-1 -> 2085 | C124: =A124-1-$B$18 -> 59 | D124: =IF(AND($B$22=1,C124>=0,C124<$B$19),INDEX($Z$46:$Z$55,C124+1),0) -> 0 | E124: =IF(AND($B$22=1,A124<=$B$21),(1+SavInc)^(A124-1),0) -> 0 | F124: =(1+ReturnRate)^(A124-1) -> 31.120463 | G124: =I123-D124 -> 0 | H124: =J123 -> 0 | I124: =G124*(1+ReturnRate) -> 0 | J124: =H124*(1+ReturnRate)+E124 -> 0 | K124: =IF(AND(D124>0,H124<=0.000000000001,G124<0),-G124/F124,0) -> 0 | L124: =IF(AND(D124>0,H124>0.000000000001),-(G124+$B$126*F124)/H124,0) -> 0 | M124: =P123 -> 0 | N124: =E124*$B$127 -> 0 | O124: =IF(AND($B$22=1,A124<=$B$20),(M124-D124)*ReturnRate,0) -> 0 | P124: =M124-D124+O124+N124 -> 0 | Q124: =IF(AND($B$22=1,C124>=0,C124<$B$19),1,0) -> 0
A126: Amount needed now | B126: =IF($B$22=1,MAX(K65:K124),0) -> 0
A127: Required yearly saving (first year) | B127: =IF($B$22=1,IF(MAX(0,MAX(L65:L124))<0.000000001,0,MAX(0,MAX(L65:L124))),0) -> 0

Sheet Child 4
